Workbook

Sheet Snowflake YT Channel
A1: Scheduled / Published | B1: YouTube Publishing Date | D1: Time of Publishing (PST) | E1: Title / Wrike | F1: Social Request Submitted? | G1: Producer | H1: Playlist Designated? | I1: MP4 | J1: THUMB | K1: NOTES | L1: LENGTH OF VIDEO | N1: YT Link | O1: Thumbnail Title | P1: YouTube Title | Q1: YouTube Description | R1: Link to Thumbnail LINK TO THUMBNAIL FOLDER | S1: Link to Video Transcript | T1: Link to Social Cut | U1: Link to Social Cut on LI | V1: Link to Social Cut on X | X1: Tally - Summit (shorts are duplicated in Shorts column) | Y1: Tally - Customer | Z1: Short | AA1: Tally - Demos | AB1: Tally - Individual Videos | AC1: Snow Report | AD1: Tally - Podcast | AE1: Tally - promos | AF1: Tally - International Channel | AG1: Tally - BuiltBy | AH1: Tally-event workshops | AI1: Feature Friday | AJ1: Temp tally - PbS | AK1: BUILD | AL1: Tally - Horizon | AM1: Tally -Truck Talk
B2: Day | C2: Date | L2: Minutes | M2: Seconds
B3: NOTE: The YouTube tracking sheet for 2024 and 2023 can be found by clicking here.
B4: Wed | C4: 45693 | D4: 8 a.m. | E4: Accelerate 2025 Teaser | G4: x | H4: NA | K4: MP4; Wrike; done | L4: 1 | M4: 12 | O4: Accelerate 2025 | P4: Accelerate 2025 | Registration Is Now Open For This Virtual Event Series That Runs From March - April | Q4: Accelerate, Snowflake’s annual virtual event series, showcases how industry technology leaders are accelerating with data and AI strategies using The AI Data Cloud. Learn about the blueprints of an enterprise data architecture that puts secure self-service data consumption at its core. Hear about the latest AI / ML use cases driving efficiencies AND new data experiences. See customer proof points, demos, and real-world use cases that turn the art of the possible into real implementations. VIRTUAL EVENT DATES: Financial Services - March 6, 2025 Retail & Consumer Goods - March 20, 2025 Manufacturing - March 27, 2025 Advertising, Media & Entertainment - April 3, 2025 Public Sector - April 24, 2025 Healthcare & Life Sciences - April 30, 2025 Register now at https://www.snowflake.com/Accelerate | R4: Link | AE4: 1
A24: WEEK 6 | B24: 2/02 - 2/06
A25: TRUE | B25: Tues | C25: 46056 | E25: (Ice, Steel & Data) Frank Del Duca | G25: Jason | J25: https://files.wrike.com/1989536/669893874 | K25: See TRACKER for details | N25: https://youtu.be/d6IYxIq1OCo | R25: Approved thumbnail
A26: TRUE | B26: Thurs | C26: 46058 | E26: BUILD London 2026 Opening Keynote | G26: Bobby | J26: https://files.wrike.com/1989536/675862000 | N26: https://youtu.be/9LOP86qaw34 | O26: CORTEX CODE GA | P26: Snowflake Build London Keynote | Q26: Tune into the BUILD London Keynote. Hear what’s new from Snowflake - Shared Workspaces and the GA release of Cortex Code to Snowflake Postgres, semantic view autopilot, and interactive workloads for low-latency analytics. See demos across Snowflake ML, including notebooks in Workspaces, model registry, and online inference, plus how Cortex Agents API and Snowflake Intelligence help teams build trusted agent apps. The keynote also covers Snowflake’s partnership with OpenAI and why governance stays central as AI moves from answers to action.
A27: WEEK 7 | B27: 2/09 - 2/13 | W27: FALSE
A28: TRUE | B28: Mon | C28: 46062 | E28: Olympic commercial | G28: Jason | I28: SNOWFLAKE_Social.mp4 | J28: https://www.wrike.com/open.htm?id=4369560148 | N28: https://youtu.be/phT1wRZGUi8 | O28: Powering Team USA | P28: Snowflake Powers Team USA | Q28: Snowflake is proud to be the Official Data Collaboration Provider for Team USA. Team USA relies on Snowflake to unify their data and drive secure collaboration across the organization. It’s a partnership dedicated to innovation, ensuring that the team behind the Team has the insights they need to succeed. | W28: FALSE
A29: TRUE | B29: Mon | C29: 46062 | E29: SOCIAL: BUILD London Opening Keynote Sizzle | G29: Elani | J29: https://www.wrike.com/open.htm?id=4363419405 | N29: https://youtube.com/shorts/6kojZpCB93k
A30: TRUE | B30: Tues | C30: 46063 | E30: History of Skeleton | G30: Jason | I30: V16 History of Skeleton_Prt1_Cut01_020226.mp4 | J30: YouTube_Thumb-BSS_History_of_Skeleton-A3.jpg | K30: See TRACKER for details | N30: https://youtu.be/rqioJgLxhCo
A31: TRUE | B31: Tues | C31: 46063 | E31: SOCIAL: PS Kargo Video | G31: Elani | H31: x | I31: 26-PRG - SocialPSKargo_020626_AB_v2.mp4 | N31: https://youtube.com/shorts/sd5D2sO-3lM
A32: TRUE | B32: Wed | C32: 46064 | E32: Austin Florian | G32: Jason | I32: AustinFlorian_Athlete_EDIT_v12.mp4 | J32: YouTube_Thumb-BSS_History_of_Skeleton-A3.jpg | K32: See TRACKER for details | N32: https://youtu.be/piip_h8k3rg
A33: TRUE | B33: Wed | C33: 46064 | E33: BUILD London Vendor Cut | I33: https://next.frame.io/share/0e1f64ca-2222-4f2e-870d-ff8faa04e14b/view/1f28a5ab-84e6-4813-9143-22b38028113a | J33: https://www.wrike.com/open.htm?id=4372719906 | N33: https://youtu.be/qb2NuWOItQ4 | O33: BUILD LONDON 2026 | P33: Snowflake Build London Highlights | Q33: Recap the action from Snowflake Build London 2026. From the biggest moments to product announcements, to technical deep dives, and hands-on labs.
A34: TRUE | B34: Thurs | C34: 46065 | E34: History of Bobsled | G34: Jason | I34: Main Cut | J34: Thumbnail | K34: See TRACKER for details | N34: https://youtu.be/9uzcfLM5e5Q
A35: TRUE | B35: Fri | C35: 46066 | E35: February Snow Report | G35: Jason | I35: 26-PRG-SR February 2026_021026_MP_v4_1.mp4 | J35: https://files.wrike.com/1989536/677783296 | N35: https://youtu.be/K2DQKUGRe-A | O35: Snow Report February 2026 | P35: Snow Report: What's Happening At Snowflake In February | Q35: Get the latest Snowflake updates and announcements from February, including new innovations across the AI Data Cloud. This Snow Report covers the general availability of Cortex Code, Snowflake’s native AI coding agent, now available in Snowside and the command line to help teams move faster from question to action. You will also hear about upcoming and on-demand events, including webinars, hands-on virtual labs, and major community moments designed to help data and AI teams build production-ready agents, scale generative AI initiatives, and connect with the Snowflake community.
A36: TRUE | B36: Sat | C36: 46067 | E36: Kaysha Profile Part 2 | G36: Jason | I36: KayshaLove_Pt2_Cut10_021126_JF.mp4 | J36: BSS Kaysha Love Winter Games - A1.jpg | K36: See TRACKER for details | N36: https://youtu.be/2jCJZACeqLw | P36: Kaysha Love Finds A Winning Edge With Data | Q36: Team USA bobsled pilot Kaysha Love is gearing up for the Winter Olympics. Using Snowflake's Data Collaboration Platform, she turns raw track data and equipment choices into measurable performance gains. Hear what it really feels like to race at full speed, the gear she uses, and why confidence comes from mastering every detail and trusting the data.
A37: WEEK 8 | B37: 2/16 - 2/20 | W37: FALSE
A38: TRUE | B38: Tues | C38: 46070 | D38: x | E38: Jasmine Jones | G38: Jason | I38: JasmineJones__Prt1_Cut11_020526_WR.mp4 | J38: BSS Jasmine-Jones-Profile.jpg | K38: See TRACKER for details | L38: 1 | M38: 56 | N38: https://youtu.be/bjbqISUZDJg | O38: ATHLETE PROFILE: JASMINE JONES | P38: The Data Behind Jasmine Jones’ Fast Start | Q38: Jasmine Jones is a brakeman for USA Bobsled who knows the start can define the entire run. In this athlete profile, Jasmine breaks down her technique, body positioning, and split-second decisions that turn a push into podium speed. From step-in versus long-jump loading to reading velocity and start times against the field, she explains how trusting her training and the data helps her attack every run. With support from Snowflake’s Data Collaboration Platform, teams can align around what matters most as Jasmine embraces the challenge at Milano Cortina 2026.
A39: WEEK 9 | B39: 2/23 - 2/27 | W39: FALSE
A40: TRUE | B40: Mon | C40: 46076 | E40: Cortex Code "Announcement" motion graphics video | G40: Elani | N40: https://youtu.be/XV_Cs4DfZ4o
A41: TRUE | B41: Tues | C41: 46077 | E41: CS - NZHL x Deloitte Video | G41: Bobby | I41: NZHL Video (with subtitles).mp4 | J41: https://www.wrike.com/open.htm?id=4375017083 | N41: https://youtu.be/IlJcjgxx_yI | O41: AI-READY DATA FOUNDATION | P41: How NZHL Builds AI-Ready Data With Snowflake | Q41: Learn how New Zealand Home Loans replaces a fragmented, manual reporting environment with Snowflake to create a scalable, future-focused data foundation. By moving away from outdated tools and spreadsheets, NZHL establishes a trusted single source of truth that delivers faster insights and more consistent client experiences. With Snowflake, advisers prepare annual reviews at the push of a button using AI-powered insights, helping identify gaps and better support customers on their path to financial freedom. See how strong data foundations position NZHL to move quickly with AI and agentic AI, driving measurable business outcomes across people, process, data, and technology. | W41: FALSE
A42: TRUE | B42: Tues | C42: 46076 | D42: x | E42: Curt SI and Coaching with Data | G42: Jason | I42: CurtisTomasevicz_Coach_EDIT_v9.mp4 | J42: Curt SI and Coaching with Data - G-edit2.jpg | N42: https://youtu.be/JrQynsRTh6w
A43: TRUE | B43: Tues | C43: 46076 | D43: x | E43: CoCo - Customer Testimonial - WHOOP | G43: Elani | I43: 08-Released - WHOOP | J43: https://www.wrike.com/open.htm?id=4379695811 | W43: FALSE
A44: TRUE | B44: Wed | C44: 46078 | D44: x | E44: Curt's Path | G44: Jason | I44: CurtisTomasevicz_Coach_EDIT_2_v6.mp4 | J44: BSS Curts Path - A1 - Alt2.jpg | N44: https://youtu.be/b1XVYe0GFAM
A45: TRUE | B45: Wed | C45: 46078 | E45: CoCo - Customer Testimonial - Fanatics | G45: Elani | I45: 08-Released - Customer -Fanatics | J45: https://www.wrike.com/open.htm?id=4379694614 | W45: FALSE
A46: TRUE | B46: Thurs | C46: 46079 | E46: CoCo - Customer Testimonial - Shelter Insurance | G46: Elani | J46: https://www.wrike.com/open.htm?id=4379693904 | W46: FALSE
A47: TRUE | B47: Fri | C47: 46080 | D47: 0.33333333 | E47: Ordance Survey Customer Case Study Youtube Video | G47: Bobby | I47: 1169_-_sno_-_ordnance_survey_-_edit_v7_v1.mov | J47: https://www.wrike.com/open.htm?id=4384568207 | N47: https://youtu.be/mfBLAH-adTM | O47: Mapping Britain in Real-Time | P47: Ordnance Survey Transforms Geospatial Data Into Insight With Snowflake | Q47: Ash Wheeler, Chief Product Officer at Ordnance Survey, explains how they unlocked the power of geospatial data by migrating their National Geographic Database to the Snowflake AI Data Cloud. Learn how they’ve moved beyond traditional spreadsheets to offer instant, frictionless access to data for urban planning, emergency services, and environmental monitoring. | W47: FALSE
A48: WEEK 10 | B48: 3/02 - 3/06 | W48: FALSE
A49: TRUE | B49: Wed | C49: 46085 | E49: Tracksuit Video Case Study | G49: Bobby | I49: SWT_Tracksuit_CC_HD_FINAL.mp4 | J49: https://files.wrike.com/1989536/684673051 | N49: https://youtu.be/EAxOrdkEr8k | O49: BRAND INTELLIGENCE | P49: Tracksuit Delivers Always-On Brand Intelligence with Snowflake | Q49: With help from Snowflake, Tracksuit provides real-time, actionable performance insights to marketers, replacing static reports with a unified, AI-powered platform. | W49: FALSE
A50: TRUE | B50: Wed | C50: 46085 | E50: SOCIAL - Cortex Customer Testimonial - Lending Tree | G50: Elani | N50: https://youtube.com/shorts/Iz8MNf-h__M?si=rkCHqOEtUHhfzyYt | P50: LendingTree Scales Smarter Queries With Cortex Code | Q50: LendingTree uses Snowflake Cortex Code to speed up query development and deployment, eliminate context switching, and democratize data access across teams. | W50: FALSE
A51: TRUE | B51: Fri | C51: 46087 | E51: Bynder Case Study YouTube Video Request | G51: Bobby | I51: Bynder Customer Video.mov | J51: https://files.wrike.com/1989536/684687514 | K51: Pending Thumb | N51: https://youtu.be/EAxOrdkEr8k | O51: ENDING CONTENT CHAOS | P51: Bynder Eliminates Content Chaos With Snowflake | Q51: Learn how Bynder transforms digital asset management with Snowflake to eliminate data silos, improve performance, and scale with confidence. With more than 4,000 customers, 20 million assets uploaded quarterly, and 60 billion assets distributed each quarter, Bynder needs a data platform that keeps up. After moving to Snowflake, the team establishes a single source of truth across three data teams, processes massive CDN data sets, and scales without limits. The results: 60% cost reduction, 4x faster data ingestion, 2x faster data delivery, and nearly 50% productivity gains. See how Snowflake helps Bynder turn content chaos into actionable insight. | W51: FALSE
A52: WEEK 11 | B52: 3/09 - 3/13 | W52: FALSE
A53: TRUE | B53: Mon | C53: 46090 | E53: March Snow Report | F53: Sonia | I53: 26-PRG-SR - March 2026_030326_MP_FINAL.mp4 | J53: https://files.wrike.com/1989536/684501307 | K53: Pending Copy | N53: https://youtu.be/i6sVPVKPU30 | O53: MARCH SNOW REPORT | P53: Snow Report: What's Happening At Snowflake In March | Q53: Hear what’s new at Snowflake in March, from major product launches to upcoming community events, and more. Next generation Snowflake Notebooks are now generally available, delivering a familiar Jupyter-based experience directly in Snowflake workspaces. Online model inference in the online feature store is also generally available, enabling millisecond predictions for real-time use cases like fraud detection and personalized recommendations, with no extra infrastructure to manage. Plus, get the latest on Snowflake Summit 2026, Data for Breakfast, and March technical sessions covering AI pipelines, autonomous SQL, prompt-to-production workflows, and Apache Iceberg. | W53: FALSE
A54: TRUE | B54: Wed | C54: 46092 | E54: CoCo - Customer Testimonial - Dentisu | G54: Elani | H54: Cortex | I54: 08-Released - Braze | J54: https://www.wrike.com/open.htm?id=4379699048 | N54: https://youtube.com/shorts/ahiqBbxNq6A | O54: CORTEX CODE: RELIABILITY AT SCALE | P54: Dentisu Boosts AI Reliability With Snowflake Cortex Code | Q54: Dentisu shares how Snowflake Cortex Code improves reliability, streamlines AI workflows, and connects tools directly to the Snowflake AI Data Cloud. By using Cortex Code and the CLI as connective tissue between AI tools and Snowflake, Dentisu brings Snowflake context into the code generation layer. This closes the loop between development and production while supporting complex, market-specific variations at scale. Built-in code review capabilities catch broken syntax and risky patterns before they reach pipelines, reducing errors and strengthening performance. The result is faster iteration, greater reliability, and measurable return on investment powered by Snowflake. | W54: FALSE
A55: TRUE | B55: Fri | C55: 46094 | E55: Imperial College Healthcare NHS Trust YouTube Video | I55: Snowflake - NHS Imperial - Subtitled.mp4 | J55: https://files.wrike.com/1989536/684694184 | N55: https://youtu.be/CBaLM0qkIr0 | O55: SECURE DATA. BETTER CARE. | P55: Securely Transforming Healthcare Data In The AI Data Cloud | Q55: Learn how Imperial College Healthcare NHS Trust uses Snowflake to accelerate secure, data-driven healthcare across Northwest London. By implementing a Secure Data Environment, the Trust ingests and transforms data in days instead of weeks, enabling clinicians, data engineers, analysts, and researchers to collaborate in one unified platform. With access to Snowflake Marketplace data, including environmental data sets, teams can better predict demand, improve patient safety, and enhance care quality. See how Snowflake powers trusted, secure collaboration to support real-time insights, operational decision-making, and better patient outcomes across London. | W55: FALSE
A56: TRUE | B56: Fri | C56: 46094 | E56: CoCo - Customer Testimonial - Braze | G56: Elani | H56: Cortex | I56: 08-Released - Braze | J56: https://www.wrike.com/open.htm?id=4379695200 | N56: https://youtube.com/shorts/bOIWVovf0_o | O56: CORTEX CODE: FROM DATA TO ACTION | P56: Braze Goes Deeper Into Data With Cortex Code | Q56: Braze shares how Snowflake Cortex Code helps teams move faster and uncover deeper insights across structured and unstructured data. By simplifying complex analysis, Cortex Code reduces hours or days of effort into minutes. Braze uses it to explore customer engagement, from opens and clicks to downstream behaviors like purchases and subscriptions. The result is greater operational efficiency and the ability to pursue high-impact analyses that were previously too time intensive to justify. | W56: FALSE
A57: WEEK 12 | B57: 3/16 - 3/20 | W57: FALSE
A58: TRUE | B58: Mon | C58: 46097 | E58: SOCIAL - Cortex Code - Evolv Customer testimony | G58: Elani | H58: Cortex | I58: 3-RELEASED_Evolv | P58: Evolve Unlocks 500 Hours With Snowflake Cortex Code | Q58: Learn how Evolve uses Snowflake Cortex to accelerate development, eliminate backlogs, and deliver customer demos in hours instead of weeks. | W58: FALSE
A59: TRUE | B59: Wed | C59: 46099 | E59: SOCIAL - Anahita SnowWork Launch | G59: Elani | H59: Cortex | I59: 08-Released - Anahita SnowWork | P59: Introducing Project SnowWork | Q59: Introducing Project SnowWork. An autonomous AI platform that embeds intelligence directly into your business workflows and tools. | W59: FALSE
A60: TRUE | B60: Wed | C60: 46099 | E60: Project SnowWork - Motion Graphics video | G60: Elani | H60: Cortex | I60: 08-Released - Project SnowWork MG Video | J60: 06-Thumbnail | P60: Automate Any Workflow — No Code | Project SnowWork | Q60: Project SnowWork empowers business teams to automate multi-step workflows end-to-end,and drive real outcomes. Create revenue snapshots, diagnose missed forecasts, and generate summary slides with next steps — all without any coding experience needed. | W60: FALSE
A61: TRUE | B61: Thurs | C61: 46100 | E61: Mukuru Case Study YouTube Video Request | G61: Bobby | I61: 1144 - SNO - Mukuru - South Africa Story - FINAL.mp4 | J61: https://files.wrike.com/1989536/692649490 | N61: https://youtu.be/srnMmEwwy1c | O61: Real-Time Financial Intelligence | P61: Mukuru Delivers Personalized Financial Services Across Africa with Snowflake | Q61: Saad Panjwani, Head of Business Intelligence at Mukuru, discusses how migrating to Snowflake led to a new way to power financial services. Snowflake helps Mukuru to transform transactional data at large volumes - whilst still prioritizing customer experiences. | W61: FALSE
A62: WEEK 13 | B62: 3/23 - 3/27 | W62: FALSE
A63: TRUE | B63: Wed | C63: 46106 | E63: MAIN: Marketers Forum #1- Summit 2026 | G63: Sonia | I63: 26-PRG - Marketer Forum 1_032326_MP_v4.mp4 | J63: https://www.wrike.com/open.htm?id=4408715895 | N63: https://youtu.be/DV11HJDy_jU | O63: MAKE AI REAL FOR MARKETING | P63: Marketers Forum: Make AI Real For Marketing At Snowflake Summit | Q63: Introducing Marketing Forum at Snowflake Summit 2026. Learn how to move faster with AI while maintaining customer trust. Discover how to govern and activate your customer data to prove ROI, accelerate execution, and reduce time spent managing your data stack. Plus, hear from Snowflake CMO Denise Persson and get a first look at the latest Modern Marketing Data Stack. Join us June 2 and 3 in San Francisco. https://www.snowflake.com/en/summit/ | W63: FALSE
A64: TRUE | B64: Thurs | C64: 46107 | D64: 0.25 | E64: CoCo Day MG Features Update | G64: Elani | H64: Cortex | I64: Coco_Day_Mar_26_MG_Video-AH-v04_CAPTIONS_vC.mp4 | J64: https://youtu.be/E17bqBxIFbs | W64: FALSE
A65: FALSE | B65: Thurs | C65: 46107 | D65: 0.33333333 | E65: SOCIAL - Cortex Customer Testimonial - TS Imagine | G65: Elani | H65: Cortex | I65: 08-Released - Cortex_Customer_TS Imagine | W65: FALSE
A66: TRUE | B66: Fri | C66: 46108 | D66: 0.54166667 | E66: The Agentic Enterprise: Strategy to ROI Promo | G66: Jason | I66: 25-EVT-AgenticEnterpriseStrategyToROI_PROMO_16x9_032626_VC_v8.mp4 | J66: https://www.wrike.com/open.htm?id=4416578496 | K66: Reg Page, V1 Promo | N66: https://youtu.be/4snYMbw6S-U | O66: Put Agents to Work | P66: The Agentic Enterprise: From Strategy To ROI | Virtual Event April 9 | Q66: Join Snowflake, AWS and Accenture for an exclusive virtual event exploring how organizations are transforming AI momentum into measurable business results. New research shows 92% of early gen AI adopters are seeing positive ROI, and among organizations with multiple gen AI use cases in production, 44% are already using agentic AI. Get actionable insights on: Success patterns from global AI adoption research Implementation strategies from enterprise leaders Building scalable agentic frameworks Architecting data foundations for AI workflows Featured speakers include experts from Snowflake, AWS, Accenture and more. Register now: https://www.snowflake.com/events/the-agentic-enterprise-from-strategy-to-roi/ | W66: FALSE
A67: TRUE | B67: Sat | C67: 46109 | E67: Snowflake Semantic Views Demo | G67: Bobby | I67: 26-PRG - SnowflakeSemanticViews_032726_AB_v2.mp4 | J67: https://www.wrike.com/open.htm?id=4420097208 | N67: https://youtu.be/a6SDInK-nrE | P67: Unlock Your BI Business Logic in 6 Minutes — Snowflake Semantic Views Demo | Q67: Your BI team has spent years building measures, relationships, and business rules — but it's all locked inside one tool. This 6-minute demo from Josh Klahr (Snowflake VP of Product) shows how Snowflake Semantic Views let you extract that logic, define it once, and make it queryable from any tool — including plain English via Cortex Analyst. See the Semantic View Autopilot in action. | W67: FALSE
A68: WEEK 14 | B68: 3/30 - 4/3 | W68: FALSE
A69: FALSE | W69: FALSE
A70: FALSE | W70: FALSE
A71: FALSE | W71: FALSE
A72: WEEK 15 | B72: 4/06 - 4/10 | W72: FALSE
A73: FALSE | B73: Fri | C73: 46122 | E73: Startup Challenge Promo | W73: FALSE
A74: FALSE | W74: FALSE
A75: WEEK 16 | B75: 4/13 - 4/17 | W75: FALSE
A76: FALSE | W76: FALSE
A77: FALSE | W77: FALSE
A78: WEEK 17 | B78: 4/20 - 4/24 | W78: FALSE
A79: FALSE | W79: FALSE
A80: FALSE | W80: FALSE
A81: WEEK 18 | B81: 4/27 - 5/01 | W81: FALSE
A82: FALSE | W82: FALSE
A83: FALSE | W83: FALSE
A84: FALSE | W84: FALSE
B85: NOT YET SCHEDULED
A86: FALSE | B86: Mon | C86: 46104 | E86: SOCIAL Marketers Forum #1- Summit 2026 | G86: Sonia | I86: 26-PRG - Marketer Forum 1 Social_032026_MP_FINAL.mp4 | N86: https://youtube.com/shorts/uXlB5B51WMU | W86: FALSE
A87: FALSE | E87: NRF Session | F87: Bobby | J87: https://files.wrike.com/1989536/679883736 | O87: DATA TO REAL EXPERIENCES | P87: AI for Retail: Turning Data Into Authentic Experiences | Q87: AI is reshaping how retailers and consumer brands understand customers and deliver more relevant experiences. In this session, you learn how leading brands apply data and AI to improve engagement, strengthen loyalty, and drive measurable growth. Snowflake’s Rosemary DeAragon, Global Head of Retail, joins Ngai Yuen Low, Managing Director of AEON360, and Kayla Itsines, co-founder of Sweat, to share practical strategies for activating customer data at scale. See how Snowflake Intelligence and Retail AI capabilities help teams deliver more dynamic, personalized, and authentically aligned customer journeys. | W87: FALSE
A88: FALSE | E88: SOCIAL: Lexington Partners | G88: Elani | O88: 25-PRG-CS - LexingtonPartners_Transcript
A89: FALSE | E89: EDD - Mats Pellback | G89: Sonia | O89: DATA DRIVES SUSTAINABILITY | P89: End Data Disparity: Using Data To Drive Global Sustainability | Q89: Sustainability expert Mats Pellback shares how data driven decisions Help organizations advance the UN Sustainable Development Goals. Drawing on his experience leading sustainability at Ericsson, Mats explains why closing data gaps is critical to digital inclusion, climate action, and responsible innovation. He also shares how companies can use data, AI, and industry collaboration to improve sustainability outcomes, support ethical data use, and build long term business value.
A90: FALSE | B90: Fri | C90: 46080 | E90: Harsha Kapre | G90: Sonia | J90: https://www.wrike.com/open.htm?id=1768702087 | O90: THE SNOWFLAKE VENTURES VISION | P90: Snowflake Ventures on Backing The Next AI Startups | Q90: Harsha Kapre, Director of Snowflake Ventures, explains how Snowflake supports founders building AI-driven business applications and industry solutions. The video covers the evolution of Snowflake for Startups, how Snowflake aligns venture investing, accelerators, and partnerships under one umbrella, and why applied AI is becoming a top priority for founders and VCs.
A91: FALSE | B91: Fri | C91: 46066 | E91: Snowflake DCR Video Series: Video 4 | G91: Bobby | J91: https://www.wrike.com/open.htm?id=4348587367 | K91: awaiting approval | O91: ML IN DATA CLEAN ROOMS | P91: Snowflake Data Clean Rooms: Machine Learning | Q91: Derek Leckner, Solutions Engineering for DCR, walks through a Quickstart video on how to use ML in Snowflake Data Clean Rooms.
A92: FALSE | E92: CS- Cox Automotive | G92: Elani | K92: tracker spreadsheet; (Pending customer approval) | O92: AI Power At Scale | P92: How Cox Automotive Accelerates AI With Snowflake | Q92: Learn how Cox Automotive strengthens its data foundation and accelerates AI-driven workflows using Snowflake and AWS. David Mitchell shares how unified data, unstructured data integration, and an enterprise data marketplace help the company build knowledge stores, unlock Gen AI, and shorten model delivery from months to days. Discover how centralizing data enables faster product development, smarter decision making, and better business outcomes.
A93: FALSE
A94: FALSE | E94: Agentic Enterprise: Strategy to ROI Promo | K94: script, program brief.
A95: FALSE | E95: Startup Challenge Promo | K95: Previous Year's Promo, will be a simple refresh | O95: STARTUP CHALLENGE 2026 | P95: The Snowflake Startup Challenge 2025 Kicks Off | Q95: Snowflake and the New York Stock Exchange are once again teaming up to sponsor the Snowflake Startup Challenge. This year marks the sixth anniversary of this important competition, that will bring $1 million in investment capital to the top three winners. Do you have a Snowflake-based product that you think will excite the hearts and minds of the Startup Challenge judges? If so, now's the time to register your interest in participating.
A96: FALSE | E96: Dash Summit Promo | I96: MP4 | O96: Snowflake Summit 2026 | P96: Snowflake Summit 2026: Making AI Real for Business | Q96: The data and AI event of the year returns! Join thousands of data engineers, scientists, developers, and business leaders at Snowflake Summit 2026. Experience groundbreaking sessions on AI, agents, analytics, app development, enterprise data collaboration, and more. Register now at to secure your spot. https://www.snowflake.com/summit
A97: FALSE | E97: Christian Summit Promo | I97: MP4 | O97: Snowflake Summit 2027 | P97: Snowflake Summit 2026: Making AI Real for Business | Q97: The data and AI event of the year returns! Join thousands of data engineers, scientists, developers, and business leaders at Snowflake Summit 2026. Experience groundbreaking sessions on AI, agents, analytics, app development, enterprise data collaboration, and more. Register now at to secure your spot. https://www.snowflake.com/summit
A98: FALSE | E98: Benoit Summit Promo | I98: MP4 | O98: Snowflake Summit 2028 | P98: Snowflake Summit 2026: Making AI Real for Business | Q98: The data and AI event of the year returns! Join thousands of data engineers, scientists, developers, and business leaders at Snowflake Summit 2026. Experience groundbreaking sessions on AI, agents, analytics, app development, enterprise data collaboration, and more. Register now at to secure your spot. https://www.snowflake.com/summit
B100: THESE VIDEOS ARE NOT SCHEDULED YET
A101: FALSE | E101: SOCIAL - New Year New Job at Snowflake (Part ) | G101: Elani | Q101: Look to this tracker until published
A102: FALSE | E102: CS- Stellarus | G102: Elani | J102: https://www.wrike.com/open.htm?id=4333252041 | K102: NOT APPROPVED - Presenter was fired but Stellarus apologized and is happy to do another video with us. tracker spreadsheet | O102: [Stellarus + Snowflake Logos] | P102: Stellarus Engineers Scale Secure Data Solutions With Snowflake | Q102: Learn how Stellarus leverages Snowflake certifications to strengthen engineering expertise, improve collaboration, and deliver scalable, secure data solutions for customers. Lead database engineer Julia Ozmolski explains how Snowflake helps Stellarus optimize deployments, reduce production issues, and apply features such as streaming, cost optimization, Cortex, and LLMs for deeper insights.
A103: FALSE | E103: SOCIAL - New Year New Job at Snowflake (Part 2) | G103: Elani
E104: NRF Teaser | K104: MP4; Wrike; Thumb | O104: AI DRIVES RETAIL'S FUTURE | P104: Snowflake At NRF 2026 | Q104: Discover how the Snowflake AI Data Cloud powers the next wave of retail transformation at NRF 2026. Join us in New York City, January 11 to 13, for Retail’s Big Show.
E105: Podcast -- Sallie Mae | K105: Podcast tracking sheet
B106: ?? | C106: ?? | E106: EDD - Harvard Climate Action Week | K106: MP4; FrameIO; WrikeProject ; WrikeEdit; WrikeThumb; thumb done (DESCRIPTION TO BE PROVIDED) (ON HOLD) | O106: Using Data To Battle Extreme Heat | P106: Harvard Climate Action Week | Phoenix Heat Emergency Simulation | R106: Link
B107: ?? | C107: ?? | E107: Venture Interview - Snowflake - Harsha | K107: MP4; WrikeEdit; WrikeThumb; thumb done (NEED STATUS ON THIS) | O107: The Snowflake Ventures Vision | P107: Snowflake Ventures And The New Silicon Valley AI Hub | Q107: Harsha Kapre, Director of Snowflake Ventures, talks with "Data Cloud Now" Anchor Ryan Green | R107: Link
B109: ?? | C109: ?? | E109: Short - Sridhar | K109: MP4; FrameIO; WrikePost; WrikeEdit; (ON HOLD ASK KAREN)
E110: Short - EDD Hackathon MOTS Mike Johnson | K110: MP4; WrikeEdit;
E111: CKE Summit 2025 Demo | K111: MP4; Wrike;
B114: THESE VIDEOS WERE NEVER USED
B115: Tues | C115: 46014 | D115: 0.375 | E115: Davos Teaser | K115: MP4; Wrike; WrikeEdit; WrikeThumb (need mp4) | O115: The World Economic Forum: January 19 - 23 | P115: Snowflake Brings The AI Data Cloud To Switzerland For The World Economic Forum 2026 | Q115: Snowflake is heading to Davos, Switzerland in January to the World Economic Forum 2026, carrying with it its message about the End Data Disparity initiative and its knowledge of how AI is revolutionizing all that can be accomplished with data. Stay tuned for "Data Cloud Now's" upcoming coverage of the event and its conversations with industry leaders. The Forum runs from January 19 - 23.
B117: Fri | C117: 46010 | D117: 8 a.m. | E117: Feature Friday for Public Sector - Document AI in Snowflake | K117: MP4; FrameIO; Wrike; WrikeThumb; thumb done (NEED MP4) | O117: Document AI for Data Extraction | P117: Unlock Your Document Data With Snowflake's Document AI | Q117: Transforming unstructured data from documents into a structured, queryable format is a major challenge for many organizations, especially in the public sector and higher education. This demo shows how Snowflake's Document AI, a powerful capability within the Snowflake Cloud Data Platform, solves this problem by using a Snowflake LLM to extract key information. | R117: Link
B118: Tues | C118: 45979 | D118: TBD | E118: 25-PRG - Marketplace & MCD | G118: EC | K118: MP4; Wrike; WrikeThumb; (THIS IS NOT GOING ON YT)
C119: expected to publish sometime in August | E119: Unlock More Value from Unstructured Data with Snowflake's Document AI | K119: Wrike;
B120: ??? | C120: ??? | E120: PbS--Comcast | K120: Frame IO link; thumb done (ON HOLD) | O120: Enhancing Data Security And Compliance | P120: How Comcast's DataBee Hive Helps Large Enterprises Enhance Data Security And Compliance | Q120: Why does Erin Hamm, Field Chief Data Officer and Director of Engineering at Comcast, say that Comcast's DataBee Hive and Snowflake's Data Cloud go together like peanut butter and jelly? In this "Powered by Snowflake" episode, she explains the analogy to host Felipe Hoffa and provides a demo of the platform. The DataBee Hive is a cloud-native security, risk, and compliance data fabric platform targeted at Fortune 1000 companies that delivers the connected data and deep insights that security and GRC teams need to address security and compliance gaps faster and more affordably. To learn more about DataBee Hive, go to: https://www.comcasttechnologysolutions.com/databee-suite/databee-platform/hive To connect with Erin Hamm, go to: --LinkedIn: | R120: LINK
E121: PbS--Bluesky | K121: FrameIO link; thumb done (ON HOLD) | O121: Enhancing Data Cloud Cost Optimization | P121: Bluesky Helps Snowflake Users Achieve Maximum Data Cloud Efficiency | Q121: In this episode of "Powered by Snowflake, Mingsheng Hong, Co-founder and CEO of Bluesky, sits down with host Julian Forero to discuss his company's platform for managing Snowflake Data Cloud workload optimization. The goal is to free developers and users of Snowflake from the need to worry about tuning workloads so that they can focus on building apps. The conversation includes a look at Bluesky's operating environment and a demo of the platform in action. To learn more about Bluesky, go to: Website: https://www.getbluesky.io/ LinkedIn: https://www.linkedin.com/company/bluesky-data/ Twitter: https://twitter.com/getbluesky_io To connect with Mingsheng, go to: LinkedIn: https://www.linkedin.com/in/mingshenghong/ | R121: LINK | S121: LINK | T121: LINK
B122: ??? | C122: ??? | E122: Data Cloud Podcast -- Marriott
B123: ??? | C123: ??? | E123: Data Cloud Podcast-Nashville Government
B124: ??? | C124: ??? | E124: PbS--BigGeo | K124: MP4; FrameIO; Wrike; thumb done (WAITING FOR FINAL VIDEO--MAY NEED TO BE PUT ON HOLD) | O124: Using Natural Language To Tap Geospatial Data | P124: BigGeo Lets Snowflake Users Manage And Query Geospatial Data Using Natural Language | Q124: In this episode of "Powered by Snowflake," host Felipe Hoffa chats with Big Geo CEO Brent Lane about his company's geospatial intelligence application. The application allows anyone to extract information from large amounts of location-based data with incredible speed and efficiency using natural language. BigGeo was a finalist in this year's Snowflake Startup Challenge, and its application can be downloaded from the Data Marketplace. For more infomation about BigGeo: --Website: https://biggeo.com --LinkedIn: https://www.linkedin.com/company/biggeo To connect with Brent Lane: --LinkedIn: https://www.linkedin.com/in/lanebrent | R124: Link
...

Sheet Dev YT Channel
A1: d | B1: YouTube Publishing Date | D1: Time of Publishing (PST) | E1: Wrike Request Name | F1: Social Request Submitted? | G1: Producer | H1: Playlist Designated? | I1: MP4 | J1: THUMB | K1: NOTES | L1: LENGTH OF VIDEO | N1: YT Link | O1: Thumbnail Title | P1: YouTube Title | Q1: YouTube Description | R1: Link to Thumbnail | S1: Link to Video Transcript | T1: Link to Social Cut MP4 | U1: Link to Social Cut on LI | V1: Link to Social Cut on X | X1: Summit (The shorts in this tally are duplicated in the Shorts column) | Y1: Demos | Z1: Shorts | AA1: Professional Services | AB1: Behind the Cape | AC1: Solutions Center (also marked as Demo) | AD1: User Groups | AE1: Individual Videos | AF1: Events | AG1: BUILD/Builder Bytes | AH1: Customer | AI1: AI Builders | AJ1: Podcast
A2: WEEK 6 | B2: 2/02 - 2/06
A3: TRUE | B3: Mon | C3: 46055 | E3: Behind The Cape - Snowflake Apache Iceberg and Polaris - Saurabh Kumar | G3: Bobby | I3: Behind the Cape - Apache Iceberg and Polaris Final.mp4 | J3: https://www.wrike.com/open.htm?id=4359850229 | L3: 30 | M3: 11 | N3: https://youtu.be/glDWNpHX8g4 | O3: OPEN CATALOG + ICEBERG | P3: Behind The Cape - Snowflake Apache Iceberg and Polaris | Q3: In this episode of Behind the Cape, Data Superhero Keith Belanger hosts fellow Data Superhero Saurabh Kumar as he breaks down how Snowflake, Apache Iceberg, and Apache Polaris are coming together to redefine what a modern, interoperable lakehouse really looks like. They chat through why open table formats and open catalogs matter more than ever, how Snowflake integrates with Iceberg and Polaris to support cross-cloud interoperability, and how teams can maintain vendor neutrality without sacrificing enterprise-grade performance, security, or governance.
A4: TRUE | B4: Mon | C4: 46055 | E4: Snowflake Postgres 2 minute demo | G4: Elani | I4: 26-PRG - Snowflake Postgres demo_020226_MP_v6.mp4 | J4: https://files.wrike.com/1989536/675754084 | L4: 2 | M4: 29 | N4: https://youtu.be/HhzpDM36Pzg | O4: POSTGRES ON SNOWFLAKE!? | P4: Snowflake Postgres In 2 Minutes: Fully Managed Postgres On Snowflake | Q4: Snowflake Postgres brings the world’s most popular open source database onto the Snowflake platform in a fully managed way. See how it unifies transactional and analytical workloads, and how developers can get started in minutes directly from Snowsight. The demo walks through provisioning an instance, connecting with standard Postgres tools, and using familiar features like extensions and permissions. You also learn how Snowflake Postgres simplifies operations with built in insights for performance, storage, and long running queries. Find out more: https://www.snowflake.com/postgres
A5: TRUE | B5: Tues | C5: 46056 | E5: DuckDB querying Snowflake-managed Apache Iceberg via Horizon (Iceberg REST) Catalog | G5: Elani | I5: 26-PRG - DuckDBQuerying_012125_AB_v2.mp4 | J5: https://files.wrike.com/1989536/674725516 | L5: 4 | M5: 51 | N5: https://youtu.be/vpbUbh4KRwo | O5: ICEBERG WITH DUCKDB | P5: Query Snowflake Managed Iceberg Tables With DuckDB | Q5: This demo shows how to query Snowflake managed Apache Iceberg tables using DuckDB through the Snowflake Horizon Iceberg REST Catalog. What you'll learn: • Set up Snowflake's Horizon Catalog for external engine access • Configure DuckDB with PAT (Programmatic Access Token) authentication • Query Iceberg tables from DuckDB with zero data movement • Handle RBAC and common troubleshooting scenarios Resources: https://github.com/kameshsampath/hirc-duckdb-demo
A6: TRUE | B6: Wed | C6: 46058 | E6: Online ML demo | G6: Sonia | I6: Online ML Demo_3.mp4 | J6: https://files.wrike.com/1989536/675871734 | L6: 11 | M6: 44 | N6: https://youtu.be/jnjQaYTNq6k | O6: REAL-TIME FRAUD ML | P6: Build and Serve Real-Time Fraud Detection Models in Snowflake ML | Q6: Moving ML from experimentation to production shouldn't require rebuilding from scratch or navigating lengthy development cycles. In this video, learn how to build, test, and deploy online ML models directly from Snowflake using an agentic approach to generate production-ready pipelines from simple natural language prompts.
A7: TRUE | B7: Wed | C7: 46057 | E7: SOCIAL: Anahita CoCo Social Video | G7: Elani | I7: 26-PRG - Anahita CoCo Social Video_012926_MP_v5.mp4 | J7: n/a | L7: 1 | M7: 13 | N7: https://youtube.com/shorts/XzPw-BfPkGw
A8: TRUE | B8: Thurs | C8: 46058 | E8: Snowflake Intelligence + Domo: Marketing Mix Modeling Integration | G8: Bobby | I8: 26-PRG - Snowflake Intelligence + Domo - Marketing Mix Modeling Integration_012726.mp4 | J8: https://files.wrike.com/1989536/675738167 | L8: 15 | M8: 28 | N8: https://youtu.be/9p2jYKR13QY | O8: CONVERSATIONAL MMM WITH AI | P8: Conversational Marketing Mix Modeling With Snowflake Intelligence | Q8: Andreina Toledo, Partner Solutions Consultant at Domo, demonstrates how to build conversational AI for Marketing Mix Modeling using Domo and Snowflake Intelligence. Marketing teams are constantly asked which channels truly drive results. Traditional platform metrics show clicks and conversions but cannot separate correlation from causation or measure true incremental impact. Domo MMM addresses this gap using Bayesian statistical modeling to analyze historical marketing spend alongside revenue, accounting for seasonality, carryover effects, and diminishing returns to deliver confidence-based ROI insights. What sets Domo MMM apart is how teams interact with these insights. By integrating with Snowflake Intelligence, Domo adds a conversational layer on top of MMM results. Marketers can ask natural language questions like which channels to prioritize or why spend should shift and receive clear, actionable answers grounded directly in the underlying analysis. Learn More: https://www.snowflake.com/en/developers/guides/domo-mmm-guide/
A9: TRUE | B9: Fri | C9: 46059 | E9: Keyless Data Engineering: AWS Lambda & Snowflake WIDF Explained | G9: Elani | I9: 26-PRG - Keyless Data Engineering: AWS Lambda | J9: https://files.wrike.com/1989536/675730159 | N9: https://youtu.be/gAVPzo0VJZ0 | O9: KEYLESS DATA WITH AWS LAMBDA | P9: Keyless Data Engineering With Snowflake And AWS Lambda | Q9: Learn how to build a secure, serverless data pipeline using Snowpark Python, AWS Lambda, and Snowflake Workload Identity Federation. You will see how an S3 event triggers Lambda, how temporary credentials are exchanged using identity federation, and how data is written securely into Snowflake. The walkthrough covers deployment, trust configuration, and validation, ending with Snowflake Dynamic Tables automatically refreshing as new data arrives. This pattern combines strong security with serverless speed for modern data engineering workflows. 👉 Get the demo code and documentation: https://github.com/kameshsampath/snowpark-widf-lambda-loader-demo
A10: WEEK 7 | B10: 2/09 - 2/13 | W10: FALSE
A11: TRUE | B11: Tues | C11: 46063 | E11: How to Integrate Akave Cloud with Snowflake | G11: Bobby | I11: 26 - PRG - How to Integrate Akave Cloud with Snowflake.mp4 | J11: https://files.wrike.com/1989536/675870896 | N11: https://youtu.be/OexaY_Qz5to | O11: AKAVE CLOUD INTEGRATION | P11: How to Integrate Akave Cloud with Snowflake | Q11: Bart Hofkin, Systems Architect at Akave, walks through how to integrate Akave Cloud with Snowflake. In this demo, you’ll see how to create an Akave bucket, configure it as an external stage in Snowflake, and read and write data between Snowflake and Akave using standard Snowflake workflows. This video is a step-by-step walkthrough focused on setup and usage, showing how S3-compatible object storage can be used directly within Snowflake. For more details and written instructions, refer to the Akave + Snowflake integration guide: https://akave.com/blog/akave-cloud-the-first-decentralized-object-storage-integrated-with-snowflake
A12: WEEK 8 | B12: 2/16 - 2/20 | W12: FALSE
A13: TRUE | B13: Fri | C13: 46073 | E13: BUILD London Cortex Code Breakout Session | G13: Bobby | H13: Coretex Code | I13: 08-Released - BUILD London CortexCode | J13: https://snowflake.enterprise.slack.com/files/U09J7RPTR7A/F0AGWTVBV4G/build25-dev_channel-center_title.png | N13: https://youtu.be/ZUJl6sUGnFk | O13: Cortex Code: Agents for Snowflake Development | P13: Cortex Code: The Purpose Built Agent for Snowflake Development | Q13: The process of building production-ready applications can have a lot of friction points - wrestling with connections, debugging permissions, and generating repetitive, complex configurations. If you spend more time managing the platform than writing business logic, your productivity is suffering. We believe your terminal should be a launchpad for innovation, not a place to solve administrative puzzles. This is the core mission of Cortex Code. This session introduces the new agentic CLI that puts the collective expertise of Snowflake directly into your command line. Through a rapid-fire live demonstration, we’ll show you how to use simple, natural language commands to instantly scaffold entire Snowpark projects, generate secure SQL, and orchestrate complex multi-step deployments. Discover how Cortex Code becomes your resident expert, allowing you to focus purely on value creation. | W13: FALSE
A14: TRUE | B14: Fri | C14: 46073 | E14: Cortex Code Overview | G14: Elani | H14: Cortex Code | I14: 26_PRG - CC_101__Overview_021626_AB_v5.mp4 | J14: https://www.wrike.com/open.htm?id=4379417935 | N14: https://youtu.be/lftWaAcG2nE | O14: All your data, one AI Coding agent | P14: Cortex Code CLI Expands to Support Any data, Anywhere | Q14: Learn what is new in Cortex Code CLI and how it accelerates your enterprise data lifecycle inside Snowflake. Introducing dbt and Apache Airflow support, expanded model choice across Claude Opus 4.6, Sonnet 4.6, and GPT 5.2, new enterprise-grade governance controls, and a self-serve subscription option. See how Cortex Code CLI helps you ship workflows faster, integrate data systems, and build with confidence using natural language. | W14: FALSE
A15: WEEK 9 | B15: 2/23 - 2/27 | W15: FALSE
A16: TRUE | B16: Mon | C16: 46076 | D16: 0.33333333 | E16: SOCIAL - Cortext Code Overview | G16: Elani | H16: Cortex Code | I16: 26_PRG - CC_Social_101_Overview_022026_AB_v6.mp4 | J16: https://www.wrike.com/open.htm?id=4379417935 | W16: FALSE
A17: TRUE | B17: Mon | C17: 46076 | E17: Cortex Code Overview (101) - Basics - Cortex Code | G17: Elani | H17: Cortex Code | W17: FALSE
A18: TRUE | B18: Tues | C18: 46077 | D18: 0.47916667 | E18: Accelerate FY27 | Teaser Trailer | F18: Elani | G18: Elani | I18: 08-Released - Accelerate26_Trailer | J18: https://www.wrike.com/open.htm?id=4367247238 | N18: https://youtu.be/04AkmzB0QP0 | O18: ACCELERATE 2026 | P18: Accelerate 2026: Industry AI Transformation With Snowflake | Q18: Learn how AI is transforming six major industries and how to build a practical, industry-ready AI strategy with Snowflake. Registration is now open. 👉 https://www.snowflake.com/accelerate Accelerate, Snowflake’s flagship virtual series, returns April 21 with two weeks of deep industry insight across advertising, media and entertainment, retail and consumer goods, public sector, financial services, manufacturing, and healthcare and life sciences. Hear from leaders across the AI and data ecosystem, including SAP and Accenture, and explore real-world use cases, Enterprise Super Intelligence architectures, semantic views, and connected data strategies in the AI Data Cloud. | W18: FALSE
A19: TRUE | B19: Tues | C19: 46077 | D19: 0.52083333 | E19: Openflow Oracle CDC | G19: Bobby | I19: 08-Released - Project Title | J19: https://www.wrike.com/open.htm?id=4382441783 | N19: https://youtu.be/nLGnb1VoJuc | O19: Near Real-Time Oracle CDC to Snowflake | P19: How-to Set Up Near Real-Time Oracle CDC to Snowflake using Openflow | Q19: Learn how to leverage Snowflake Openflow to establish near real-time Change Data Capture (CDC) replication from your Oracle database directly to Snowflake. This video showcases how Openflow ensures your critical transactional data from Oracle is unified and always up-to-date in Snowflake.
A20: TRUE | B20: Tues | C20: 46077 | E20: SOCIAL: DBT101 | G20: Elani | H20: Cortex Code | I20: 26-PRG - CC_Social_101_Dbt_022326_V4.mp4 | N20: https://youtube.com/shorts/SXKnsd9j6dY | W20: FALSE
A21: TRUE | B21: Wed | C21: 46077 | D21: 0.0625 | E21: Airflow - Debugging a failed DAG run | G21: Elani | H21: Cortex Code | I21: 4_Airflow_Released | J21: https://www.wrike.com/open.htm?id=4379708564 | W21: FALSE
A22: TRUE | B22: Thurs | C22: 46078 | E22: SOCIAL: Airflow | G22: Elani | H22: Cortex Code | I22: 26-PRG - CC_Social_Airflow_022626_AB_v3.mp4 | W22: FALSE
A23: TRUE | B23: Thurs | C23: 46078 | E23: Optimizing dbt for speed and cost (201) - Cortex Code | G23: Elani | H23: Cortex Code | I23: 08-Released - Coco_Customer_ShelterIns | J23: https://www.wrike.com/open.htm?id=4379690455 | O23: Optimize dbt Projects for Speed | P23: Optimize dbt Projects on Snowflake for Speed With Cortex Code | Q23: dbt projects on Snowflake are easy to build, but keeping them fast and cost-efficient is another challenge. As source tables grow and models become more complex, runtimes increase and performance issues get harder to pinpoint. In this demo, you'll see how to direct Cortex Code CLI to analyze your project’s run_results.json, identify the slowest models, flag unused ones, and find suggestions for specific optimizations you can apply immediately, all from a single prompt in your terminal. | W23: FALSE
A24: WEEK 10 | B24: 3/02 - 3/06 | W24: FALSE
A25: TRUE | B25: Tues | C25: 46083 | E25: Demo videos for newly launched enterprise-grade sharing | G25: Bobby | I25: 26-PRG - Enterprise-grade sharing_030326_MP_v1.mp4 | J25: https://files.wrike.com/1989536/683191137 | N25: https://youtu.be/H-l8IgbIlqE | O25: Data Product Resiliency | P25: Enterprise-grade Sharing Demo Videos - Part 1: Listing BCDR | Q25: Explore how Snowflake Listing BCDR, helps customer's to streamlines data product protection with automated failover and seamless recovery workflows. See firsthand how this enterprise-grade sharing capability minimize downtime and keep your critical data product resilient against any disruption. | W25: FALSE
A26: TRUE | B26: Tues | C26: 46083 | E26: Demo video for Resharing GA | G26: Bobby | I26: 26-PRG -Resharing GA_030326_MP_v1.mp4 | J26: https://www.wrike.com/open.htm?id=4384622738 | N26: https://youtu.be/EJsJ2qNK41s | O26: Zero-ETL Data Enrichment | P26: Data Product Enrichment With Zero-ETL Transformations: Resharing GA | Q26: Resharing, a new Snowflake AI & Data sharing feature that builds on our Zero-ETL, cross-cloud and cross-region capabilities, allows customers to reuse shared data products without having to manage local copies (materialize) and apply light-weight transformations on the fly. Resharing can help customers simplify their sharing architecture by providing simple, light-weight transformation for shared data product enrichment, without having to move, extract or load the data. | W26: FALSE
A27: TRUE | B27: Tues | C27: 46084 | E27: Cortex Code - dbt core | G27: Elani | H27: Cortex Code | N27: https://youtu.be/airYxlLRTBE | O27: FASTER dbt CORE BUILDS | P27: Make Your dbt Core Builds Faster with Cortex Code | Q27: When dbt builds fail or pipelines slow down, Cortex Code CLI accelerates troubleshooting by bringing Snowflake expertise directly to your terminal. By reading your project files—including models, tests, and lineage—without requiring a manual compile, it can instantly identify bottlenecks, perform blast radius analysis, and audit test coverage. This data-native AI agent combines dbt project structure with Snowflake query history to provide a prioritized improvement plan, allowing you to trace dependencies and refactor code from a single prompt with total confidence.
A28: TRUE | B28: Thurs | E28: SOCIAL: Ddbt 201 | G28: Elani
A29: TRUE | B29: Fri | C29: 46085 | D29: x | E29: Cortex Code - Building Agents Demo | G29: Elani | H29: Cortex Code | I29: 26_PRG - CC_201_BuildingDataAgents_030426_AB_v5.mp4 | N29: https://youtu.be/wKvVkHO0fOw | O29: AI Agents That Scale | P29: Ship AI Agents Fast with Cortex Code CLI | Q29: Vibe-coded agents can look impressive, but they often become brittle when exposed to real enterprise data. In this walkthrough, we use Cortex Code CLI to build a Cortex Agent powered directly by governed Snowflake data. We combine structured metrics, unstructured search, routing logic, and guardrails, then deploy to Snowflake Intelligence. | W29: FALSE
A30: WEEK 11 | B30: 3/09 - 3/13 | W30: FALSE
A31: TRUE | B31: Tues | C31: 46091 | E31: SOCIAL: Cortex Code - Building Agents Demo | G31: Elani | H31: Cortex Code | I31: 26_PRG - CC_Social_201_BuildingDataAgents_030426_AB_v2.mp4 | W31: FALSE
A32: TRUE | B32: Wed | C32: 46092 | E32: SOCIAL: Cortex Code - dbt core | G32: Elani | H32: Cortex Code
A33: TRUE | B33: Wed | C33: 46092 | E33: Cortex Code - Data Exploration Demo | G33: Elani | H33: Cortex Code | O33: From Data Chaos to Clarity | P33: Rapid Data Exploration with Cortex Code CLI | Q33: Data exploration usually means inspecting schemas, profiling columns, and writing exploratory code just to understand what’s there. In this demo, we use Cortex Code CLI to handle that work directly from the terminal on real Snowflake data. Anything you want to understand in your data, just ask Cortex Code. | W33: FALSE
A34: TRUE | B34: Thurs | C34: 46093 | E34: How To Build A Churn Insights Agent Using Snowflake Intelligence | G34: Sonia | H34: professional svcs | I34: 26-PRG - How To Build A Churn Insights Agent Using Snowflake Intelligence_WR_03092026.mp4 | J34: https://www.wrike.com/open.htm?id=4364867447 | N34: https://youtu.be/ELf1LpzgxTc | O34: REDUCE CUSTOMER CHURN | P34: Build A Churn Insights Agent With Snowflake Intelligence | Q34: In this video, we'll show you how to transform raw machine learning models into actionable AI insights. Using Snowflake Intelligence, you'll learn to build an AI Agent that: Leverages the Snowflake Model Registry to provide clear, transparent model explainability. Constructs a semantic layer of intelligence directly over your ML models. Bridges the gap for non-technical stakeholders to interact with complex data. Link to code: https://github.com/sfc-gh-sujoshi/sf-samples/tree/main/samples/churn_intelligence_agent Links to relevant documentation: https://www.snowflake.com/en/developers/guides/getting-started-with-snowflake-intelligence/ https://docs.snowflake.com/en/developer-guide/snowflake-ml/model-registry/overview Link to background music used throughout this video: https://www.fesliyanstudios.com/royalty-free-music/download/smooth-presentation/382 | W34: FALSE
A35: TRUE | B35: Thurs | C35: 46093 | E35: Horizon Catalog overview | G35: Bobby | I35: 26-PRG - SCQ4_HorizonCatalogOverview_031026_AB.mp4 | J35: https://www.wrike.com/open.htm?id=4402902969 | N35: https://youtu.be/S66kaS5uoVc | O35: HORIZON CATALOG POWERS AI | P35: Snowflake Horizon Catalog: Powering Trusted AI And Open Data | Q35: Learn how Snowflake Horizon Catalog helps you build a data strategy that makes AI safe, trusted, and scalable. Get an overview of interoperability with Apache Iceberg and open standards, discovery with hybrid search, lineage and observability, and semantic enrichment that improves agent accuracy. | W35: FALSE
A36: TRUE | B36: Fri | C36: 46094 | E36: Bi-directional Interoperability with Horizon Catalog demo | G36: Bobby | I36: 26-PRG - SCQ4_Bi-directionalInteroperability_031026_AB.mp4 | J36: https://www.wrike.com/open.htm?id=4402897474 | N36: https://youtu.be/4ld80bFUBq8 | O36: BI-DIRECTIONAL INTEROP DEMO | P36: Bi-Directional Interoperability With Snowflake Horizon Catalog | Q36: Learn how Snowflake Horizon Catalog enables bi-directional interoperability across your open lakehouse architecture. In this demo, Riccardo Muti shows how to create and manage Apache Iceberg tables in Snowflake, access them from external engines like Spark, and securely read and write data using the Iceberg REST Catalog API. You also see the reverse scenario: federating external catalogs such as AWS Glue into Snowflake for seamless query and write access. | W36: FALSE
A37: TRUE | B37: Fri | C37: 46094 | E37: Accelerate FY27 | Teaser Trailer | G37: Jason | I37: 26-PRG - Accelerate FY27 Teaser_031226_MP_v4.mp4 | N37: https://youtu.be/dm5SsNCmu68 | W37: FALSE
A38: WEEK 12 | B38: 3/16 - 3/20 | W38: FALSE
A39: TRUE | B39: Mon | C39: 46097 | E39: Data and AI Governance with Horizon Catalog | G39: Bobby | I39: 26-PRG - SCQ4_DataAndAIGovernance_031026_AB.mp4 | J39: https://www.wrike.com/open.htm?id=4402906865 | N39: https://youtu.be/42GWL5x3Xpg | O39: HORIZON CATALOG GOVERNANCE | P39: Horizon Catalog: Governing Data For Trusted AI | Q39: Learn how Horizon Catalog detects and protects sensitive data, enforces tag-based masking and automatic tag propagation, and delivers observability for lineage and data quality so AI can run safely on trusted data. This demo shows practical governance workflows in Snowflake. Creating classification profiles, applying tag-based masking policies, tracing column-level lineage, and using universal search and conversational discovery to find and understand data. | W39: FALSE
A40: TRUE | B40: Tues | C40: 46098 | E40: Semantic Views with Horizon Catalog | G40: Bobby | I40: 26-PRG - SCQ4_SemanticViews _031026_AB.mp4 | J40: https://www.wrike.com/open.htm?id=4402909705 | N40: https://youtu.be/6TUckfUdweE | O40: HORIZON CATALOG SEMANTIC VIEWS | P40: Semantic Views In Horizon Catalog | Q40: Learn how to create and use semantic views in Snowflake Horizon Catalog to make data understandable and actionable for both humans and AI. This video demonstrates how Cortex Analyst turns business prompts into correct SQL using semantic views, how to enrich metadata with descriptions, relationships, verified queries, and custom metrics, and how to expose agents via MCP so external AI tools can query your semantic models securely. | W40: FALSE
A41: TRUE | B41: Tues | C41: 46098 | E41: Analyst Briefing - Snowflake for Work - Cortex Code | G41: Bobby | H41: Unlisted | I41: 26-PRG - AnalystBriefing_SnowWorkCoCo_031726_AB_v6.mp4 | N41: https://youtu.be/Et-bu5Fbphg | P41: Project SnowWork - Work at the Speed of AI | Q41: Introducing Project SnowWork! An autonomous enterprise AI platform that helps business users get work done faster. | W41: FALSE
A42: TRUE | B42: Wed | C42: 46099 | E42: Apache Polaris (incubating) 1.4 Release Video | G42: Bobby | H42: Unlisted | I42: DEV_ApachePolaris_01_04_031326_VC_v4.mp4 | J42: https://www.wrike.com/open.htm?id=4390848467 | N42: https://youtu.be/YFPXuYdfO5Q | P42: An Overview Of The Features of Apache Polaris 1.4 | Q42: #apachepolaris #iceberg #apacheiceberg Apache Polaris 1.4 is here! Follow along as Danica Fine (Sr. Manager, OSS Developer Relations, Snowflake), shares the features that users have to look forward to in this latest version. TIMESTAMPS 0:00 - Intro 0:19 - Polaris graduation 0:54 - Storage-scoped AWS credentials 1:09 - Enhanced KMS support 1:27 - ADLS hierarchical flag 1:41 - AWS STS session tag customization 1:51 - Principal names in sub-scoped credentials 2:05 - Persist Iceberg metrics 2:25 - JSON schema file in Helm charts 2:45 - UV for Python package management 2:58 - Updated rate-limiter 3:09 - PolarisConfigurationStore deprecation 3:16 - gcpServiceAccount configuration is active 3:31 - Close RESOURCES ► Peruse the Apache Polaris 1.4 features on Github: https://github.com/apache/polaris/tree/apache-polaris-1.4 ► Check out the Apache Polaris roadmap: https://github.com/apache/polaris/discussions/1028 ► Download Apache Polaris : https://polaris.apache.org/downloads/ #apachepolaris #iceberg #apacheiceberg
A43: TRUE | B43: Fri | C43: 46101 | E43: How to Connect Snowflake to Excel | G43: Bobby | J43: https://files.wrike.com/1989536/699092981 | N43: https://youtu.be/YEHnYFqOFhY | O43: Connect Live Snowflake to Excel | P43: How to Connect Snowflake to Excel | Q43: Frank Ferris, Sr Product Specialist at Coefficient, show you how to automatically connect Snowflake with Excel using Coefficient’s one-click data connector. Watch the video to see a quick demo on how you can increase productivity in your workflows with our Snowflake integration for Excel. See how you can get more out of your Snowflake data in Excel: https://coefficient.io/snowflake/connect-snowflake-google-sheets | W43: FALSE
A44: FALSE | W44: FALSE
A45: WEEK 13 | B45: 3/23 - 3/27 | W45: FALSE
A46: TRUE | B46: Mon | C46: 46104 | E46: BUILD Snapshot: Smarter Pipelines | G46: Elani | H46: BUILD | I46: 26-PRG -The BUILD Snapshot- Smarter Pipelines_032026_AB_v1.mp4 | J46: https://drive.google.com/file/d/1-cdZov0K0F0azO2RzpbN4m4HDVr0nPne/view?usp=sharing | N46: https://youtu.be/_YxKFnBoQ9Y | P46: Smarter Data Pipelines: AI Ingestion, Apache Iceberg & Git Workflows in Snowflake | Q46: Modern data pipelines need to do more than move data — they need to understand, enrich, and serve it through open, interoperable layers. Join Snowflake's James Stone and Yoav Ostrinsky as they show you how to: - Build AI-powered ingestion pipelines - Use native Apache Iceberg interoperability - Implement Git-native development workflows - Connect unstructured and structured data seamlessly - Apply intelligence with built-in AI Functions - Publish results through open standards any engine can consume Fast, intelligent, interoperable pipelines — built end-to-end in Snowflake. #Snowflake #DataPipelines #ApacheIceberg #DataEngineering | W46: FALSE
A47: TRUE | B47: Wed | C47: 46106 | D47: 0.33333333 | E47: Cortex - ML Feature Importance (Long) | G47: Elani | H47: Cortex Code | I47: 08_Released_07_Feature Engineering_long | J47: https://files.wrike.com/1989536/705344136 | W47: FALSE
A48: TRUE | B48: Wed | C48: 46106 | D48: 0.29166667 | E48: SOCIAL: Cortex - What is Agentic ML Overview | G48: Elani | H48: Cortex Code | I48: 26_PRG_MLCoCo_6_WhatisAgenticML_SHORT_032426_v3_VC.mp4 | N48: https://youtube.com/shorts/bLKDFv2A3PA | P48: Agentic ML in Snowflake | Q48: Data science teams can now automate development of production-ready ML pipelines from simple natural language prompts on the same platform as the governed data. Learn more about agentic workflows in Snowflake ML: https://www.snowflake.com/en/product/features/end-to-end-ml-workflows/ | W48: FALSE
A49: TRUE | B49: Thurs | C49: 46107 | D49: 0.25 | E49: Cortex CoCo Day - March 26 MGFX Explainer | G49: Elani | H49: Cortex Code | I49: Coco_Day_Mar_26_MG_Video-AH-v04_CAPTIONS_vC.mp4 | N49: https://youtu.be/E17bqBxIFbs | W49: FALSE
A50: TRUE | B50: Fri | C50: 46107 | D50: 0.33333333 | E50: Cortex Demo - AI Function | G50: Elani | H50: Cortex Code | I50: 9_AI Functions | W50: FALSE
A51: TRUE | B51: Fri | C51: 46107 | D51: 0.33333333 | E51: SOCIAL: Cortex - AI Function | G51: Elani | H51: Cortex Code | I51: 9_AI Functions | W51: FALSE
A52: WEEK 14 | B52: 3/30 - 4/3 | W52: FALSE
A53: TRUE | B53: Mon | C53: 46111 | D53: 0.33333333 | E53: 5_The BUILD Snapshot: Better Tools & Open Source | H53: BUILD | I53: 26-PRG-5_BUILD Snapshot- Better Tools_PG_v01.mp4 | N53: https://youtu.be/z9XKgZPIN5Q | P53: Snowflake Developer Tools: Terraform, Snow CLI, Notebooks, Streamlit & AI Coding (2026) | Q53: What's new in the Snowflake developer stack? What should you be adding to your toolbox this year? Join Snowflake's Matt Nunn for a whistlestop tour of the tools that extend your reach: - Infrastructure-as-code with Terraform - The powerful Snow CLI - Next-gen Notebooks - Streamlit for data apps - AI-assisted coding workflows Whether you're managing Snowflake objects, building data apps, or accelerating with AI, this session shows how each tool fits into a modern development workflow. #Snowflake #DeveloperTools #Terraform #SnowCLI #Streamlit | W53: FALSE
A54: FALSE | B54: Mon | C54: 46111 | D54: 0.33333333 | E54: Agent Teams - Cortex Code | G54: Elani | H54: Cortex Code | I54: 10_Agent Teams | W54: FALSE
A55: FALSE | B55: Mon | C55: 46111 | D55: 0.33333333 | E55: SOCIAL: Cortex - Agent Teams | G55: Elani | H55: Cortex Code | I55: 10_Agent Teams | W55: FALSE
A56: FALSE | B56: Tues | C56: 46112 | E56: What is Snowflake? | G56: Elani | P56: What is Snowflake? Developer Demo (2026) | Q56: Snowflake is a unified, fully-managed, multi-cloud data and AI platform that lets you build data pipelines, train ML models, and deploy AI-powered applications, and more, all without managing infrastructure. In this complete walkthrough, we'll show you how developers, data engineers, and ML teams use Snowflake to go from raw data to production-ready insights. Whether you're building your first data pipeline or scaling enterprise ML workloads, this video covers everything you need to get started. 🔗 Start your free trial: https://signup.snowflake.com/developers ⏱️ TIMESTAMPS 0:00 - Introduction 0:35 - Data Engineering with Snowflake – Ingestion, Transformation, Delivery 2:23 - AI with Snowflake: Snowflake Cortex, Snowflake Intelligence, AI Agents 4:19 - Building Applications with Snowflake: Streamlit in Snowflake, Snowflake Native Apps, Snowflake Postgres 5:32 - MLOps & Model Deployment with Snowflake - Feature Engineering, ML Jobs, Snowflake Notebooks, Model Registry 6:48 - Open Source at Snowflake - Apache™️ Iceberg, Apache™️ Polaris, Streamlit, Terraform 8:41 - Snowflake Platform Architecture & Security 10:22 - Start building with Snowflake 📌 WHAT'S NEW FOR 2026 • Snowflake Openflow for unified ingestion • Snowflake Dynamic Tables for end-to-end incremental pipelines • Snowflake Cortex (Cortex Analyst, Cortex Search, AI functions) • Snowflake Intelligence for agentic workflows • Snowflake Postgres for transactional workloads • Apache™️ Iceberg & Apache™️ Polaris integration • MLOps with Snowflake – ML Jobs with distributed GPU compute 🔧 TOPICS COVERED Data Engineering Pipelines | AI & ML | Cortex | Streamlit | Native Apps | MLOps | Apache™️ Iceberg | Multi-Cloud | Security & Governance #Snowflake #DataEngineering #WhatIsSnowflake #DataPlatform #CloudData #AI #MachineLearning #Cortex #Streamlit #ApacheIceberg ——— 👩🏽‍💻 Snowflake Developer Portal: https://www.snowflake.com/en/developers/ 📘 Docs: https://docs.snowflake.com 💬 Community: https://community.snowflake.com | W56: FALSE
A57: WEEK 15 | B57: 4/06 - 4/10 | W57: FALSE
A58: FALSE | B58: Mon | C58: 46118 | D58: 0.29166667 | E58: BUILD Snapshot: Agentic Applications | G58: Elani | H58: BUILD | I58: 26-PRG - 3_The BUILD Snapshot- Agentic Applications_032426_AB_v2.mp4 | J58: BUILD25-Dev_Channel-Left_Title.png | P58: Building Agentic AI Applications on Snowflake: From Query to MCP | BUILD 2025 | Q58: What do data agents really mean for your applications — and how do you build production-ready ones? Join Snowflake's Grace Adamson and Teresa Nascimento as they cover the full journey from query to MCP: - What agentic applications are and why they matter - Ensuring accurate retrieval and context for AI agents - Implementing the right access controls - Building for interoperability and production readiness Learn more here: - https://www.snowflake.com/en/developers/guides/oss-deploy-snowflake-intelligence-routing-agent/?utm_source=youtube&utm_content=buildlondon #Snowflake #AgenticAI #MCP #AIAgents #DataCloud | W58: FALSE
A59: FALSE | W59: FALSE
A60: WEEK 16 | B60: 4/13 - 4/17 | W60: FALSE
A61: FALSE | B61: Mon | C61: 46125 | E61: 4_The BUILD Snapshot: Better Analytics | H61: BUILD | J61: AIANALYTICS.png | P61: Supercharge Analytics with Snowflake AI Functions, Document Intelligence & Semantic Modeling | Q61: Enterprises generate massive volumes of raw signals that models can't use without structure, context, and access to fresh transactional data. Join Snowflake's Ravi Bhatta and Fawad Qureshi as they show developers how to: - Transform raw data into intelligent products - Extract meaning from unstructured files with Document Intelligence - Combine AI Functions with semantic modeling - Unify analytical and transactional data - Expose clean, consistent interfaces for apps and AI agents Turn your data into products that applications and agents can consume in real time. #Snowflake #AIAnalytics #SemanticModeling #DocumentAI #DataProducts | W61: FALSE
A62: FALSE | W62: FALSE
A63: FALSE | W63: FALSE
A64: WEEK 17 | B64: 4/20 - 4/24 | W64: FALSE
A65: FALSE | B65: Mon | C65: 46132 | E65: BUILD_Fast-Track Your Way to Agentic AI | G65: Elani | W65: FALSE
A66: FALSE | W66: FALSE
A67: WEEK 18 | B67: 4/27 - 5/01 | W67: FALSE
A68: FALSE | B68: Mon | C68: 46139 | E68: BUILD AI Beyond the Chatbot | G68: Elani | W68: FALSE
A69: FALSE | W69: FALSE
A70: FALSE | W70: FALSE
B71: NOT YET SCHEDULED
E72: LONDON BUILD
A73: FALSE | E73: dbt Development in a Single Prompt (101) - Cortex Code | G73: Elani | J73: https://www.wrike.com/open.htm?id=4379495846 | W73: FALSE
A79: FALSE | E79: "What's New" Videos - Cortex Code | J79: https://www.wrike.com/open.htm?id=4379707278 | W79: FALSE
A80: FALSE | E80: dbt OSS Cloud | J80: https://www.wrike.com/open.htm?id=4379708887 | W80: FALSE
A81: FALSE | E81: dbt core | J81: https://www.wrike.com/open.htm?id=4382104004 | W81: FALSE
A82: FALSE | B82: Thurs | C82: 46072 | E82: Cortex Agent from Demo to Production | G82: Bobby | J82: https://files.wrike.com/1989536/679563461 | O82: SNOWFLAKE CORTEX DEMO TO PRODUCTION | P82: 9 Things You Need to Do to Take Your Cortex Agent from Demo to Production | Q82: Learn the nine essential best practices for taking a Snowflake Cortex Agent from demo to production. The session walks through what changes when real users interact with your agent and how to move beyond proofs of concept to trusted, production-ready AI applications. Learn how to improve reliability, governance, security, and performance while operationalizing Cortex Agents in the AI Data Cloud. This video helps data and AI teams avoid common pitfalls and build agents that scale with confidence. Best Practices Guide: https://www.snowflake.com/en/developers/guides/best-practices-to-building-cortex-agents/
A83: FALSE
B84: THE VIDEOS BELOW WERE NEVER USED
B85: Fri | C85: 46059 | E85: SOCIAL: BUILD OpenAI | G85: Elani | Q85: Moving ML from experimentation to production shouldn't require rebuilding from scratch or navigating lengthy development cycles. In this video, Sumit Kumar, Staff Product Manager, shows you how to build, test, deploy and run realtime Inference on ML models directly from Snowflake using an agentic approach to generate production-ready pipelines from simple natural language prompts. Learn more about Snowflake ML at https://www.snowflake.com/en/product/features/end-to-end-ml-workflows/ Try a ML quickstart today at https://docs.snowflake.com/en/developer-guide/snowflake-ml/quickstart New Real Time Docs: https://docs.snowflake.com/en/developer-guide/snowflake-ml/inference/real-time-inference-rest-api (edited)
E86: Data Science with Snowpark and Hex | K86: thumb requested; (THIS HAS BEEN PLACED ON HOLD | O86: Data Science with Snowpark and Hex | P86: A Demonstration Of How To Use Hex To Get Started With Snowpark For Python | Q86: Ariel Harnik, Head of Partnerships at Hex, demonstrates how to use Hex to get started with Snowpark for Python, using built-in environments and helper functions to create new Snowpark sessions. You can even natively return SQL queries as Snowpark dataframes.
E87: Cortex AI for Financial Services | K87: MP4; Wrike; draft of thumb is done but may need to revise it to conform to Dev channel branding (requester is Samual Lee; doc with info is here) | O87: AI FOR FINANCIAL SERVICES | P87: Snowflake Cortex AI For Financial Services: Bringing Agentic AI To A Portfolio Management Workflow | Q87: Snowflake's Senior Product Manager Renee Huang demonstrates how to leverage Snowflake Cortex AI for Financial Services, a suite of AI tools designed to help financial institutions build and deploy agentic AI applications. Her demonstration focuses on 3 use cases: How to transform and summarize unstructured data from earning transcripts with Cortex AISQL How to build a ML model using simple text prompts with Data Science Agent How to use natural language to derive insights with Snowflake Intelligence For more information, check out this blog post: | R87: Link
E88: Hybrid Tables and Unistore demo | K88: MP4 review link;
E89: Snowflake Python AP Functions & Capabilities
E90: Snowflake Connector for MySQL and PostgreSQL Demo (Public Preview) | K90: Wrike;
B91: ??? | C91: ??? | E91: NextMV Demo | K91: MP4; FrameIO; Wrike; WrikePrep; thumb done | O91: A Native App For Route Planning | P91: Route Planning is Broken. Here's How to Fix It Instantly with Snowflake And Nextmv | Q91: Is your route planning stuck in the slow lane? Manual processes, spreadsheets, and outdated tools are holding businesses back. Missed deliveries, rising costs, and frustrated teams are the result. In this video, discover how Nextmv Routing, a Snowflake Native App, transforms route planning into a strategic advantage with optimized routes generated in seconds, not days. And it is all done directly within your Snowflake environment. No data movement. No extra infrastructure. Just faster, smarter decisions. In this video, you’ll see: ➡️ Real-world delivery challenges solved ➡️ A live demo of setup and route generation ➡️ How to optimize routes at scale with SQL, stored procedures, and more Tune in to learn how to put your route planning on autopilot. | R91: Link
Q95: Apache Polaris (incubating) 1.3 is here! Follow along as Danica Fine (Sr. Manager, OSS Developer Relations, Snowflake), shares the features that users have to look forward to in this latest version. RESOURCES ► Peruse the Apache Polaris (incubating) 1.3 features on Github: https://github.com/apache/polaris/tree/apache-polaris-1.3.0-incubating ► Check out the Apache Polaris (incubating) roadmap: https://github.com/apache/polaris/discussions/1028 ► Download Apache Polaris (incubating): https://polaris.apache.org/downloads/ #apachepolaris #iceberg #apacheiceberg

Sheet DCN YT Channel
A1: "Scheduled / Published" | B1: YouTube Publishing Date | D1: Time of Publishing (PST) | E1: Video Request [CONTENT MASTER] | F1: Producer | G1: Social Request Submitted? | H1: Playlist Designated? | I1: MP4 | J1: THUMB | K1: NOTES | L1: LENGTH OF VIDEO | N1: YT Link | O1: Thumbnail Title | P1: YouTube Title | Q1: YouTube Description | S1: Tally - Summt (shorts are dupulicated in Shorts column) | T1: Interviews | U1: Shorts | V1: Promos | W1: Special Reports
B2: Day | C2: Date | K2: Ryan's DCN Source of Truth can be found here | L2: Minutes | M2: Seconds | S2: 1
A3: WEEK 6 | B3: 2/02 - 2/06
A4: TRUE | B4: Mon | C4: 46055 | D4: 0.99305556 | E4: Product Exec Video - Snowflake & Microsoft | F4: Sonia | I4: 25-PRG - Product Exec Video - Snowflake Microsoft_v06_Deliverable.mp4 | J4: https://www.wrike.com/open.htm?id=4361272385 | N4: https://youtu.be/SNgPjz6pA1s | O4: ENTERPRISE ANALYTICS TOGETHER | P4: The Future Of Open Data Architectures With Snowflake And Microsoft | Q4: Arun Ulag, President of Azure Data at Microsoft, and Christian Kleinerman, Executive Vice President of Product at Snowflake discuss the major milestone of the bidirectional integration between Microsoft OneLake and Snowflake through Apache IcebergTM becoming generally available. Hear how Snowflake and Microsoft are partnering to help customers build a unified data foundation with interoperability at its core– empowering data teams to adapt as quickly as their businesses evolve without data movement. Interested to learn more? Read more about Microsoft OneLake and Snowflake interoperability on the Microsoft Fabric Blog. Visit this Snowflake developers page to get started and watch this step-by-step guided demo. Join the Data Cloud Now Community: https://bit.ly/3GdXtgD Learn more about Data Cloud Now: Website: https://www.TheDataCloudNow.com Podcast: https://bit.ly/3sFXst6 #MicrosoftFabric #Snowflake #ApacheIceberg #DataEngineering #Interoperability
A5: TRUE | B5: Wed | C5: 46057 | E5: SOCIAL: Data Cloud Now Energy Solutions Announcement Interview | F5: Sonia | I5: 26-PRG-DCN - SOCIAL_Energy Solutions_PG_v06.mp4 | N5: https://youtube.com/shorts/tHRCVXuDVCE
A6: TRUE | B6: Thurs | C6: 46058 | E6: SAP and Sridhar at Davos 2026 | F6: Sonia | I6: 26-PRG-SAP_SRIDHAR_020226_PG_v08.mp4 | J6: https://files.wrike.com/1989536/674713185 | N6: https://youtu.be/Pcr6oqqbxAA | O6: DAVOS 2026 [SAP LOGO] | [Snowflake Logo] | P6: SAP And Snowflake On Delivering Real ROI With Agentic AI | Q6: In this episode of Data Cloud Now, learn how the SAP and Snowflake partnership helps customers move from AI experimentation to measurable business value. Leaders from both companies share what they are hearing directly from customers, why large-scale AI deployments still struggle to show ROI, and how harmonized data and shared semantics unlock more impactful AI use cases. The conversation explores how combining operational SAP data with Snowflake analytics gives enterprises tangible proof of value, from sales and HR to finance and supply chain. You will also hear why agentic AI is becoming critical to the future of work, how it removes technical and organizational blockers, and what it takes to drive real adoption across the enterprise.
A7: TRUE | B7: Fri | C7: 46059 | E7: SOCIAL: Money 20/20 DCN PayPal | F7: Sonia | I7: 25-PRG-DCN - PayPal at Money2020_SOCIAL_PG_v03.mp4 | N7: https://youtube.com/shorts/tKUkJREDXlc
A8: WEEK 7 | B8: 2/09 - 2/13
A9: TRUE | B9: Mon | C9: 46062 | E9: SOCIAL: Product Exec Video - Snowflake & Microsoft | F9: Sonia | I9: 25-PRG - Product Exec Video - SOCIAL - Snowflake Microsoft_v02_Deliverable.mp4 | N9: https://youtube.com/shorts/WShWLDxNIX4
A10: TRUE | B10: Tues | C10: 46063 | E10: DCN Money2020 #3 (Fiserv) | F10: Sonia | I10: 25_DCN_Fiserv_Money2020_120525_PG_v01_Deliverables.mp4 | J10: https://www.wrike.com/open.htm?id=4328723900 | N10: https://youtu.be/wk9yV3xq0V0 | O10: DATA-DRIVEN PAYMENTS | P10: How Fiserv Use Data And AI To Personalize Payments | Q10: Learn how financial institutions and merchants use data and AI to deliver real-time, personalized payment experiences. Recorded at Money20/20, this episode of Data Cloud Now features Brandy Wood, Head of Client Experience Product at Fiserv, sharing how converged payments and loyalty data help drive hyper-personalization, customer retention, and revenue growth. Brandy explains how expectations for instant gratification are reshaping the payments ecosystem, why data must move beyond reconciliation to actionable insight, and how zero-copy data sharing on Snowflake reduces cost and complexity while enabling real-time collaboration with partners like PayPal. The conversation also explores how upstarts and established institutions work together on the AI Data Cloud to innovate securely and at scale.
A11: TRUE | B11: Wed | C11: 46064 | E11: DCN Predictions - Anahita + Vivek + Dwarak - Agents | F11: Sonia | I11: 25-PRG-DCN - Predictions_AnahitaVivekDwarak_020226_AB_v2.mp4 | J11: https://www.wrike.com/open.htm?id=4369503284 | N11: https://youtu.be/qPDT2XgbFb0 | O11: THE YEAR OF AI AGENTS | P11: AI + Data Predictions 2026 | Q11: Listen into AI + Data Prediction for 2026. They year enterprise leaders move beyond AI hype to put agents into production and drive measurable business outcomes. In this Data Cloud Now discussion, Snowflake leaders and experts share why 2026 is shaping up to be the year of AI agents, and what it takes to make them work at scale. The conversation explores why solving real business problems matters more than experimenting with AI for its own sake, how unified data platforms enable trustworthy agents, and why governance, semantics, and change management are critical. You will hear practical guidance on moving from prototypes to production, embedding agents into daily workflows, and using the AI Data Cloud to deliver reliable, high-impact results across the enterprise.
A12: TRUE | B12: Thurs | C12: 46065 | E12: Sridhar at Davos 2026 | F12: Sonia | J12: https://www.wrike.com/open.htm?id=4369508101 | N12: https://youtu.be/VVQ_WhhWsNA | O12: ROI ON AGENTIC AI | P12: Snowflake CEO On Agentic AI And ROI At Davos 2026 | Q12: Snowflake CEO Sridhar Ramaswamy talks with Ryan Green about key takeaways from Davos 2026. Hear how agent AI is reshaping enterprise strategy and business outcomes, and why clarity around what drives top line and bottom line growth is essential as AI capabilities accelerate. Sridhar outlines how agentic AI moves beyond chatbots to deliver real ROI, from replacing traditional dashboards to transforming customer support, life sciences, and analytics. He also explains why governed data platforms, model choice, and AI sovereignty matter for global enterprises, and what Snowflake is doing next to help customers deploy AI and agents faster at scale.
A13: TRUE | B13: Fri | C13: 46066 | E13: SOCIAL: SAP and Sridhar at Davos 2026 | F13: Sonia | I13: 26-PRG-SAP_SOCIAL_SRIDHAR_020226_PG_v06_CC.mp4 | N13: https://youtube.com/shorts/8u0ptDr4CFI
A14: WEEK 8 | B14: 2/16 - 2/20
A15: CONTENT FREEZE (OLYMPICS) | BI15: FALSE | BJ15: FALSE | BK15: FALSE | BL15: FALSE | BM15: FALSE | BN15: FALSE | BO15: FALSE
A16: WEEK 9 | B16: 2/23 - 2/27
A17: TRUE | B17: Tues | C17: 46077 | E17: SOCIAL: DCN Money2020 #3 (Fiserv) | F17: Sonia | I17: 25_DCN_Fiserv_Money2020_SOCIAL_120925_PG_v03_Deliverable.mp4 | J17: https://files.wrike.com/1989536/677629493 | N17: https://youtube.com/shorts/z1i2YZ18NJc
A18: TRUE | B18: Tues | C18: 46077 | E18: DCN Starburst | F18: Sonia | H18: https://f.io/Jt0gLhkH | J18: https://www.wrike.com/open.htm?id=4380385931 | N18: https://youtu.be/VsKtmVA6slM | O18: INTEROPERABLE DATA | P18: Snowflake And Starburst Power Interoperable AI Data | Q18: Learn how Snowflake and Starburst help organizations unify distributed data to power enterprise AI. In this episode of Data Cloud Now, Starburst Founder & CEO Justin Borgman explains why AI is fundamentally a data story and how interoperability, open standards like Apache Iceberg, and the Open Semantic Interchange enable governed, scalable access across platforms.
A19: TRUE | B19: Thurs | C19: 46079 | E19: SOCIAL: Sridhar at Davos 2026 | F19: Sonia | I19: 26-PRG-DCN - DavosSridhar_SOCIAL_021126_PG_v04_Deliverable.mp4 | N19: https://youtube.com/shorts/X7Z9tJc9OJ8
A20: TRUE | B20: Fri | C20: 46080 | E20: Christian Kleinerman at Davos 2026 | F20: Sonia | J20: https://www.wrike.com/open.htm?id=4382299202 | N20: https://youtu.be/HCQp4mDve_g | O20: AI Innovation At Davos | P20: Christian Kleinerman At Davos 2026 On AI Innovation | Q20: In this Davos 2026 interview, Christian Kleinerman, SVP of Product at Snowflake, shares how AI is reshaping data strategy and why 2026 is a defining year for enterprise innovation. From Snowflake Intelligence to Cortex Code, Christian explains how Snowflake helps organizations unlock insights from structured and unstructured data, simplify data operations, and accelerate decision-making. He also discusses interoperability, Iceberg tables, sovereign clouds, governance with Horizon Catalog, and how leaders can build teams ready to adapt in a fast-moving AI landscape.
A21: WEEK 10 | B21: 3/02 - 3/06 | W21: FALSE
A22: TRUE | B22: Mon | C22: 46083 | E22: SOCIAL: DCN Predictions - Anahita + Vivek + Dwarak - Agents | F22: Sonia | I22: 25-PRG-DCN - Predictions_AnahitaVivekDwarak_Social_022426_AB_v7.mp4 | N22: https://youtube.com/shorts/8OwLKa8YzME
A23: TRUE | B23: Tues | C23: 46084 | E23: Samsung Ads at AdWeek 2025 | F23: Sonia | I23: https://f.io/bcvzLz1N | J23: https://www.wrike.com/open.htm?id=4386330526 | N23: https://youtu.be/-W90t2VEjUM | O23: PRIVACY-FIRST ADS | P23: Samsung Ads Powers Privacy First CTV With Snowflake | Q23: Learn how Samsung Ads uses the Snowflake AI Data Cloud to power privacy first, full funnel advertising across streaming and linear TV. At Advertising Week in New York City, Samsung shares how advertisers shift from fragmented campaigns to unified planning across CTV, OTT, and linear. With more than 60 million households, Samsung Ads delivers actionable insights that reduce wasted impressions and duplicated reach. | W23: FALSE
A24: TRUE | B24: Wed | C24: 46085 | E24: SOCIAL: DCN Starburst | F24: Sonia | I24: 25_DCN_Starburst_SOCIAL_022526_v03_Deliverable.mp4 | N24: https://youtube.com/shorts/7srlli-yX88 | P24: Snowflake And Starburst Power Interoperable AI Data | W24: FALSE
A25: TRUE | B25: Wed | C25: 46085 | E25: Mike + Anahita + Chris - The Agent-Enabled Workforce | F25: Sonia | I25: https://f.io/KJcJbjXr | J25: https://www.wrike.com/open.htm?id=4386300829 | N25: https://youtu.be/027aEI-i3ro | O25: AI CO-WORKERS | P25: The Agent Enabled Workforce | Q25: Learn how AI agents are reshaping the enterprise and what it takes to build an agent enabled workforce in 2026. Snowflake leaders explore how agents evolve from assistants to virtual coworkers, transforming data engineering, analytics, and go to market teams. As AI adoption accelerates, success depends on strong data foundations, clear business context, and the ability to think like an agent. | W25: FALSE
A26: TRUE | B26: Thurs | C26: 46086 | E26: Mike Gannon at Davos 2026 | F26: Sonia | I26: 26-DCN-MikeGannon_Davos_030426_PG_v05_Deliverable.mp4 | J26: https://www.wrike.com/open.htm?id=4386331975 | N26: https://youtu.be/YbMMyhQgKMg | O26: AI AT DAVOS 2026 | P26: Snowflake At Davos: AI As A Competitive Advantage | Q26: Learn how Snowflake is turning AI into measurable business outcomes and competitive advantage in 2026. At Davos, Mike Gannon shares how leaders are moving from AI experimentation to enterprise wide prioritization. From case deflection that saves hundreds of hours to internal AI agents like Raven that deliver real time customer insights, Snowflake embeds AI across sales, support, and professional services. Discover how data sovereignty, governance, and observability are shaping global AI strategy, and why top down alignment is critical to scaling agent AI responsibly on the Snowflake AI Data Cloud. | W26: FALSE
A27: TRUE | B27: Fri | C27: 46087 | E27: SOCIAL: Christian Kleinerman at Davos 2026 | F27: Sonia | I27: 26-PRG-DCN-SOCIAL_ChristianKleinerman_DAVOS_021026_v04.mp4 | N27: https://youtube.com/shorts/Hw7NVXk9an4 | P27: Christian Kleinerman At Davos 2026 On AI Innovation | W27: FALSE
A28: WEEK 11 | B28: 3/09 - 3/13 | W28: FALSE
A29: TRUE | B29: Mon | C29: 46090 | E29: SOCIAL: Samsung Ads at AdWeek 2025 | F29: Sonia | I29: 25-PRG-DCN-Samsung_SOCIAL_PG_022526_v02.mp4 | N29: https://youtube.com/shorts/cYsXF5hc1yM | W29: FALSE
A30: TRUE | B30: Wed | C30: 46092 | E30: Brad Jones, CISO, Snowflake | F30: Sonia | I30: 25-PRG-DCN - Predictions_Brad_031026_AB_v3.mp4 | J30: https://www.wrike.com/open.htm?id=4390211799 | N30: https://youtu.be/FG4-dCQtgYE | O30: AI SECURITY | P30: Agentic AI And Cybersecurity In 2026 | Q30: In this predictions conversation Snowflake CISO Brad Jones shares how security teams are using AI for log analysis, case summarization, and workflow automation, and why governance, identity, and data protection must come first. He explains how attackers are leveraging generative AI across the full attack lifecycle, what consolidation in the AI security market could look like, and why building a controlled AI playground helps reduce sprawl. Discover how to apply the fundamentals while preparing your data and AI strategy for a fast-moving threat landscape. | W30: FALSE
A31: TRUE | B31: Wed | C31: 46092 | E31: SOCIAL: Mike + Anahita + Chris - The Agent-Enabled Workforce | F31: Sonia | I31: 25-PRG-DCN - Predictions_MikeAnahitaChris_SociaL_030326_AB_v6.mp4 | N31: https://youtube.com/shorts/IjXlabooA3M | W31: FALSE
A32: TRUE | B32: Thurs | C32: 46093 | E32: Accenture London | F32: Sonia | I32: 25-PRG-DCN - Accenture_PG_0030626_v03_Deliverable.mp4 | J32: https://www.wrike.com/open.htm?id=1759271086 | N32: https://youtu.be/8qiZ4claTaM | O32: SCALE AI WITH CONFIDENCE | P32: Scaling AI With Snowflake And Accenture | Q32: Learn how Snowflake and Accenture help enterprises scale AI with a strong data foundation and a people-first strategy. In this conversation from London, leaders share how organizations move from AI experimentation to enterprise-wide impact, and why every AI strategy requires a data strategy. Snowflake and Accenture combine platform and practice, with thousands of certified professionals and hundreds of enterprise engagements, to help customers accelerate innovation, reinvent operations, and keep a human in the loop. | W32: FALSE
A33: TRUE | B33: Fri | C33: 46094 | E33: SOCIAL: Mike Gannon at Davos 2026 | F33: Sonia | I33: 26-DCN-MikeGannon_Davos_SOCIAL_030426_PG_v08_Deliverable.mp4 | N33: https://youtube.com/shorts/mPomwB4-Hz4 | W33: FALSE
A34: WEEK 12 | B34: 3/16 - 3/20 | W34: FALSE
A35: TRUE | B35: Mon | C35: 46097 | E35: SOCIAL: Brad Jones, CISO, Snowflake | F35: Sonia | I35: 25-PRG-DCN - Predictions_Brad_Social_031025_AB_v4.mp4 | N35: https://youtube.com/shorts/xeYkFmzdESI | W35: FALSE
A36: TRUE | B36: Tues | C36: 46098 | E36: Snowflake @ NRF | F36: Sonia | I36: 26-DCN_Snowflake_NRF_031626_PG_v01_Deliverable.mp4 | J36: https://www.wrike.com/open.htm?id=4402884245 | N36: https://youtu.be/z3EII8B5NE0 | O36: AGENTS FOR RETAIL | P36: How AI Agents Transform Retail With Snowflake | Q36: AI agents are reshaping retail. From product discovery to supply chain automation, meaning data quality is now mission critical. Recorded live at NRF in New York City, Snowflake’s Rosemary DeAragon shares how retailers use AI from LLMs to agents to drive personalization, forecasting, and real-time decision-making. | W36: FALSE
A37: TRUE | B37: Thurs | C37: 46100 | E37: Microsoft London | F37: Sonia | I37: 25-PGM-DCN - Microsoft at SWT London_121025_RL_v1 (1).mp4 | J37: https://www.wrike.com/open.htm?id=4390212320 | N37: https://youtu.be/Irlai6ZCcLk | O37: AI Without Data Silos | P37: Snowflake And Microsoft Accelerate Enterprise AI In Europe | Q37: Learn how Snowflake and Microsoft are expanding interoperability across Fabric and the AI Data Cloud to accelerate enterprise AI adoption in Europe. In this conversation from London, leaders from Snowflake and Microsoft share how bidirectional data access and Iceberg table support help customers break down data silos and speed time to value. Hear how integrations across Teams, Power BI, Dynamics 365, and Microsoft Fabric enable natural language access to governed data. | W37: FALSE
A38: TRUE | B38: Fri | C38: 46101 | E38: SOCIAL: Accenture London | F38: Sonia | I38: 25-PRG-DCN - Accenture_SOCIAL_PG_031026_v05_Deliverable.mp4 | N38: https://youtube.com/shorts/XZNw3OmLd5Q | W38: FALSE
A39: WEEK 13 | B39: 3/23 - 3/27 | W39: FALSE
A40: TRUE | B40: Tues | C40: 46105 | E40: SOCIAL: Snowflake @ NRF | F40: Sonia | I40: 26-DCN_Snowflake_NRF_SOCIAL_031626_PG_v02_Deliverable.mp4 | N40: https://youtube.com/shorts/Cdf3hKbmcvg | W40: FALSE
A41: TRUE | B41: Wed | C41: 46106 | E41: Predictions Block 4 | F41: Sonia | I41: 26-PRG-DCN_Mike_Arnnon_Enterprise_032326_PG_v06_Deliverable.mp4 | J41: https://www.wrike.com/open.htm?id=4411588687 | N41: https://youtu.be/9cPwkwits0U | O41: AI AGENTS AT WORK | P41: How AI Agents Transform Enterprise Work | Q41: Learn how AI agents are reshaping enterprise workflows by uniting HR and IT to deliver better employee experiences. Discover practical strategies for building AI agents, from targeting high-impact use cases to creating safe environments for experimentation. | W41: FALSE
A42: TRUE | B42: Fri | C42: 46108 | E42: SOCIAL: Microsoft London | F42: Sonia | I42: 25-PGM-DCN - Microsoft at SWT London Social_030326_MP_v3.mp4 | N42: https://youtube.com/shorts/eYJ5WUm7UQA | W42: FALSE
A43: WEEK 14 | B43: 3/30 - 4/3 | W43: FALSE
A44: TRUE | B44: Tues | C44: 46112 | E44: Deloitte @ Davos | F44: Sonia | I44: 26-PRG-DCN_Deloitte_Davos_032626_v05_Deliverable.mp4 | J44: https://www.wrike.com/open.htm?id=4403102278 | N44: https://youtu.be/k6ysySs4ygA | O44: DELOITTE AT DAVOS | P44: Deloitte At Davos: Reimagining Business With AI And Data | Q44: Learn how Deloitte is helping organizations move from AI experimentation to real business impact. Recorded at the World Economic Forum in Davos, Ranjit Bawa, Chief Strategy and Technology Officer at Deloitte, shares how a client-first mindset, strong data infrastructure, and scalable architecture are critical to unlocking value from AI. | W44: FALSE
A45: TRUE | B45: Wed | C45: 46113 | E45: SOCIAL: Predictions Block 4 | F45: Sonia | I45: 26-PRG-DCN_Mike_Arnnon_Enterprise_SOCIAL_032326_PG_v06_Deliverable.mp4 | J45: https://youtube.com/shorts/2S-JH_wpH8Q | W45: FALSE
A46: TRUE | B46: Thurs | C46: 46114 | E46: NRF 2026 - Sweat | F46: Sonia | I46: 26-DCN_Sweat_NRF_032626_v03_Deliverable.mp4 | J46: https://www.wrike.com/open.htm?id=4411587054 | N46: https://youtu.be/CkD_ZSCZJPM | O46: DATA-DRIVEN FITNESS AT SCALE | P46: How Sweat Scales Personalized Fitness With Snowflake | Q46: Learn how Sweat uses Snowflake to scale a global digital fitness platform while delivering tailored experiences to millions of women. In this Data Cloud Now conversation, Sweat Co-Founder Kayla Itsines and CEO Adam Koch share how data-driven decision-making, customer insights, and real-time visibility shape product innovation, content strategy, and community engagement. Discover how a strong data foundation powers a 360-degree customer view, enabling relevance, loyalty, and growth in a rapidly evolving fitness industry.
A47: WEEK 15 | B47: 4/06 - 4/10 | W47: FALSE
A48: FALSE | B48: Mon | C48: 46118 | E48: SOCIAL Deloitte @ Davos | F48: Sonia | W48: FALSE
A49: FALSE | B49: Tues | C49: 46119 | E49: EY Davos | F49: Sonia | I49: https://f.io/Df-cm-Su | J49: https://www.wrike.com/open.htm?id=4416429182 | O49: DAVOS 2026 FINANCIAL TRENDS | P49: Financial Services Trends From Davos 2026 With EY | Q49: Learn what top financial services leaders are prioritizing in 2026, from AI adoption to transformation strategy and risk management. Recorded at the World Economic Forum in Davos, this conversation with EY’s Omar Ali, Global Financial Services Leader explores how firms are shifting from macro-driven performance to execution-driven results. Discover how generative AI is moving from pilot to proof, where it is delivering ROI today, and what is holding back enterprise-scale deployment. | W49: FALSE
A50: FALSE | B50: Wed | C50: 46120 | E50: SOCIAL NRF 2026 - Sweat | F50: Sonia | W50: FALSE
A51: FALSE | B51: Thurs | C51: 46121 | E51: Global Payments at Money 2020 | F51: Sonia | I51: https://f.io/p0f1G3sb | J51: https://www.wrike.com/open.htm?id=4416369303 | O51: Next-Gen Payment Analytics | P51: Global Payments Powers Real-Time Analytics | Q51: Global Payments processes millions of transactions daily across 170+ countries. In this interview from Money 20/20, Billy Cummins, Head of Enterprise Data Platforms, explains how the company uses Snowflake's AI Data Cloud to deliver real-time analytics and insights that help merchants streamline operations, understand customer behavior, and grow their businesses. Learn how Global Payments is evolving from payment processing to providing comprehensive business intelligence through conversational analytics powered by AI. | W51: FALSE
A52: WEEK 16 | B52: 4/13 - 4/17 | W52: FALSE
A53: FALSE | F53: Sonia | W53: FALSE
A54: FALSE | W54: FALSE
A55: WEEK 17 | B55: 4/20 - 4/24 | W55: FALSE
A56: FALSE | W56: FALSE
A57: FALSE | W57: FALSE
A58: WEEK 18 | B58: 4/27 - 5/01 | W58: FALSE
A59: FALSE | W59: FALSE
A60: FALSE | W60: FALSE
A61: NOT YET SCHEDULED
A62: FALSE | E62: London EY | F62: Sonia | J62: https://www.wrike.com/open.htm?id=4403102727 | O62: SCALING RESPONSIBLE AI | P62: Powering Responsible AI With Snowflake And EY | Q62: Learn how Snowflake and EY help enterprises scale AI responsibly while driving long-term value. Recorded at Snowflake World Tour London, leaders from EY and Snowflake share how organizations move beyond siloed RFPs to an ecosystem-led model that accelerates AI adoption with governance, security, and trust built in. | W62: FALSE
A63: FALSE | B63: Thurs | E63: Microsoft at SWT London 2025 | F63: Sonia | O63: MICROSOFT + SNOWFLAKE AI | P63: How Microsoft And Snowflake Scale AI In The Enterprise | Q63: In this Data Cloud Now interview from SWT London 2025, learn how Microsoft and Snowflake help joint customers simplify data access, accelerate AI adoption, and move from experimentation to production. Alison Say, Head of UK Partner at Microsoft, and Gill Newsome, Director of Cloud and Strategic Partners at Snowflake, explain Fabric plus Snowflake interoperability, bidirectional data flow, and a zero data movement approach built on open standards like Iceberg. They also discuss bringing governed data into tools like Teams, Power BI, and Copilot, plus how customers scale responsible AI with Cortex AI and Azure AI Foundry. Hear real-world momentum, including UK financial services wins and the Hastings Direct story.
A64: FALSE | B64: TBD | E64: SWT London - Microsoft | K64: MP4; WrikePost; WrikeEdit; WrikeSocial; WrkieThumb
A65: FALSE | B65: Wed | E65: Money 20/20 - Fiserv | K65: MP4; Wrike; WrikeSocial; (ELI WILL WRITE TEXT)
A66: FALSE | E66: NRF 2026 - Microsoft
A67: FALSE | E67: NRF 2026 - Deloitte
A68: FALSE | E68: NRF 2026 - Under Armour
A69: FALSE | E69: NRF 2026 - Janie and Jack
A70: FALSE | E70: NRF 2026 - Tractor Supply
A71: FALSE | E71: NRF 2026 - Snowflake
A72: FALSE | E72: NRF 2026 - Staples
A73: FALSE | E73: NRF 2026 - Social #1
A74: FALSE | E74: NRF 2026 - Social #2
A75: FALSE
A76: THESE VIDEOS ARE NOT YET SCHEDULED
A77: FALSE | E77: Summit - DCN_005 - Rosemary DeAragon + Kimberly Clark and Tredence | K77: MP4; FrameIO; WrikeEdit; WrikeSocial; WrikeThumb; thumb done (GOOD TO GO) (WAITING FOR APPROVAL TO RELEASE) | L77: 10 | M77: 26 | O77: Transformation In The Consumer Goods Industry | P77: The Digital Transformation Journey Of Consumer Goods Giant Kimberly-Clark | Q77: Kimberly-Clark has been a leader and innovator in the consumer goods market for nearly 150 years. Now it is harnessing that spirit of innovation to prepare the company for the future. In this conversation with "Data Cloud Now" Anchor Ryan Green, Ray Bajaj of Kimberly-Clark explains how the company is working with Snowflake and Tredence, an AI and data analytics services company, to maximize its use of data to power R&D innovation, enhance digital marketing efforts, and drive supply chain and manufacturing efficiencies. Joining the conversation are Tredence's Sagar Balan and Snowflake's Rosemary DeAragon.
A78: FALSE | E78: AdWeek - Samsung | K78: MP4; Wrike; WrikeSocial; (ELI WILL WRITE TEXT)
A79: FALSE | E79: SWT London - Deloitte | K79: MP4; WrikePost; WrikeEdit; WrikeSocial; WrkieThumb; (ELI WILL WRITE TEXT)
A80: FALSE | E80: Summit--Startup Challenge | K80: MP4; WrikeEdit; WrikeSocial; (MAY NEED TO POSTPONE_
A81: FALSE | E81: Summit - AT&T & Snowflake | K81: MP4; FrameIO; WrikeEdit; WrikeSocial; WrikeThumb; thumb done (GOOD TO GO-BUT NO FIRM PUBLISH DATE) | O81: Innovation & Transformation In Telecom | P81: Telecom's Data Revolution: AT&T And Snowflake Drive Innovation | Q81: "Data Cloud Now" anchor Ryan Green sits down with Matt Dugan, VP of Data Platforms at AT&T, and Phil Kippen, Global Head of Telecom at Snowflake, for a conversation about the transformative power of data in the telecommunications industry. The conversation sheds light on how AT&T is strategically leveraging data to unlock new business opportunities and how the data needs of telecom companies have evolved. Phil shares insights into Snowflake innovations specifically designed for this dynamic sector. The conversation highlights impactful examples of the AT&T and Snowflake partnership enabling unprecedented capabilities and efficiencies. Matt discusses AT&T's thoughtful implementation of AI to enhance customer experiences while maintaining responsible data stewardship. Both guests share their excitement for the future of data in telecom as they look ahead to 2026 and beyond.
A82: FALSE | E82: Summit - Tim Tutt and IDPH | K82: MP4; WrikeEdit; WrikeThumb; WrikeSocial; (GOOD TO GO)
A83: FALSE | E83: Summit - DCN_006 - Jesse Cugliotta + Northeast Georgia Health System | K83: MP4; FrameIO; WrikeEdit; WrikePrep; WrikeThumb;
A84: FALSE | E84: Summit - DCN_021 - Phil Kippen & ATT | K84: MP4; FrameIO; WrikeEdit; WrikePrep; WrikeThumb;
A85: FALSE | C85: ?? | E85: Franklin German of Florida Cancer Specialists | K85: MP4; Wrike;
A86: FALSE | E86: Davos-Karen | K86: MP4; FrameIO-Raw; Wrike; thumb done | O86: Promoting The Use Of Data For Good | P86: Snowflake Brings The Message Of Its End Data Disparity Initiative To Davos | Q86: Karen Beauné, VP of EMEA Marketing at Snowflake and Chair of Snowflake's End Data Disparity Expert Panel, joined "Data Cloud Now" anchor Ryan Green out at the World Economic Forum in Davos, Switzerland to discuss Snowflake's End Data Disparity Initiative. The initiative's mission is to make data equally accessible to all as a way to help the world achieve the United Nations' Sustainable Development Goals.
A87: FALSE | E87: DCN re:invent Chris Gruz social cut | K87: MP4; Wrike;(GOOD TO GO)
A88: FALSE | E88: Kraft Heinz-Short | K88: MP4; Wrike; Wrike-Prep; (waiting for final MP4) | O88: NA | P88: Understanding Changing Consumer Behaviors | Q88: Watch the full DCN interview with NielsenIQ and Kraft Heinze here: https://www.youtube.com/watch?v=WlSrLYs-jH8
A89: FALSE | E89: Shweta interview | H89: X | K89: MP4; Wrike; done | L89: 12 | M89: 38 | O89: Capitalizing on Impactful AI Implementations | P89: Moving AI From Experimentation To Productive Implementation | Q89: How can organizations effectively move AI out of the testing phase and into productive usage? That's the topic of conversation in this "Data Cloud Now" discussion between DCN anchor Ryan Green and Snowflake's Shweta Gummidipudi, VP Enterprise Apps and Data. Among other things, Shweta shares details about the specific ways Snowflake itself is implementing AI internally for a range of applications, such as QA testing in app development and document knowledge capture for legal services.
A90: FALSE | E90: Domo re:invent interview-short | K90: MP4; Wrike
A91: FALSE | E91: AWS/Snowflake re:invent interview-short | K91: MP4; Wrike
A92: FALSE | C92: ??? | E92: Ad Week -- Axciom | K92: MP4; Wrike; thumb done | O92: Data Strategies for a Changing Ad Industry | P92: Strategies For Leveraging Data In The Evolving World Of Advertising | Q92: For more than 50 years, Acxiom has been in the business of helping leading brands and ad agencies use data to create successful targeted advertising campaigns. But much about that world has changed in the last half-century, and in this "Data Cloud Now" interview, DCN anchor Ryan Green talks with Keith Camoosa, Chief Product and Technology Innovation Officer at Acxiom, about that changing world and how Snowflake helps Acxiom implement seamless collaboration across the marketing ecosystem.
A93: FALSE
B94: THE VIDEOS BELOW WERE EITHER COMPLETED OR NEARLY SO BUT NEVER SCHEDULED
B95: ??? | C95: TBD | E95: Tim Long--Summit Rerelease | H95: X | K95: MP4; Wrike; done (WAITING TO BE SCHEDULED) | L95: 6 | M95: 10 | O95: Manufacturers Embrace The Promise of Gen AI | P95: Exploring The Dramatic Efficiency Gains That Gen AI Promises To Bring To Manufacturing | Q95: According to a recent report, investment in AI by manufacturers will grow 57% by 2026. In this "Data Cloud Now" conversation with Ryan Green, Tim Long, Snowflake's Global Head of Manufacturing, talks about what's driving that growth. Although manufacturers have been employing AI and ML for some time as part of the push toward "Industry 4.0," Tim explains that manufacturers are now upping their investments to take advantage of advances in gen AI that will help them bring more robotics to the shop floor, improve safety, advance product quality evaluation, and transform supply chains.
B96: ?? | C96: December ? | E96: Matthew Rose, Industry Principal for Public Sector, Snowflake | H96: X | K96: MP4; Wrike edit; Wrike prep; done (WAITING TO BE SCHEDULED) | L96: 9 | M96: 55 | O96: Snowflake Obtains Critical DOD Impact Level 5 Authorization | P96: Snowflake's DOD Authorization Opens New Opportunities In Mission-Critical Applications | Q96: Snowflake recently announced that it has acheived Department of Defense Impact Level 5 Provisional Authorization from the Defense Information Systems Agency. "Data Cloud Now" anchor Ryan Green explores the significance of this achievement with Matthew Rose, Snowflake's Industry Principal for Global Public Sector. The authorization, says Matthew, represents Snowflake's committment to meet the stringent, foundational requirements needed to serve mission-critical workloads.
B97: ???? | C97: ???? | E97: DCWT-Stockholm--Savings Bank | H97: X | K97: MP4 link; done THIS HAS NOT YET BEEN APPROVED FOR PUBLISHING | L97: 7 | M97: 0 | O97: Prioritizing Customer Service & Sustainability | P97: Finland's Savings Banks Makes Historic Investment in Data Modernization | Q97: In order to make better use of data to improve customer service while also reducing its carbon footprint, Finland's Savings Bank is making an historic $100 million Euro investment to modernize its data platform. During the Stockholm stop of the Data Cloud World Tour, Markus Saari, Chief Technology Officer at Savings Bank, proudly shared this news with DCN anchor Ryan Green, saying, "This puts us n the forefront of public cloud adoption." During the conversation, Saari explains how this strategy will allowthe bank to develop better services for its customers, while also enhancing its ability to pursue organizational sustainability practices, such as having the excess heat generated by its workloads be used to heat homes in the community.
B98: ???? | C98: ???? | E98: DCWT-Stockholm--Fennia | K98: Frame IO Link; Be sure to do captions
B99: ??? | C99: ??? | E99: DCWT-NYC-Footlocker | H99: X | K99: done; waiting for approval | L99: 5 | M99: 38 | O99: Bringing Data To Frontline Decision Makers | P99: How Foot Locker Makes Data More Accessible To All | Q99: Matthew Guinipero, Global Head of Data, Analytics and Insights at Foot Locker, talks with "Data Cloud Now" anchor Ryan Green about all the exciting developments happening in the field of data analytics--from new data sharing capabiliites to gen AI--and how Foot Locker is in the process of undergoing a major data transformation as it brings in Snowflake to make data more available to frontline decision makers.
B100: ??? | E100: Dr. Aaron J. Drew, U.S. Department of Veterans Affairs | K100: Waiting for approval | L100: 12 | M100: 56 | O100: Providing Mental Health Services for Veterans | P100: Using Data To Change The Way Mental Health Services Are Delivered To U.S. Veterans | Q100: In order to effectively provide mental health services to more than 34 million U.S veterans and their families, the U.S. Department of Veterans Affairs is enhancing its use of data to predict where those services will be most needed in the future. In this episode of “Data Cloud Now,” Dr. Aaron J. Drew talks with DCN host Ryan Green about the importance of being able to predict ahead of time where in the world, from New York to Manilla, the demand for such services will be most needed so that preparations can be made in advance to have those services available when the demand materializes. It’s all part of the Department’s larger effort to break down decades-old data silos, enhance interagency data collaboration, and create a more user-friendly experience for those who need not only the services of the Veteran Affairs Department but the services of the Federal Emergency Management Agency (FEMA) as well. Join the Data Cloud Now Community: https://bit.ly/3GdXtgD Learn more about Data Cloud Now: Website: https://www.TheDataCloudNow.com Podcast: https://bit.ly/3sFXst6
...

Sheet International Channel
A1: Scheduled / Published | B1: YouTube Publishing Date | D1: Time of Publishing (PST) | E1: Title / Wrike | F1: Social Request Submitted? | G1: Producer | H1: Playlist Designated? | I1: MP4 | J1: THUMB | K1: NOTES | L1: LENGTH OF VIDEO | N1: YT Link | O1: Thumbnail Title | P1: YouTube Title | Q1: YouTube Description | R1: Link to Thumbnail LINK TO THUMBNAIL FOLDER | S1: Link to Video Transcript | T1: Link to Social Cut | U1: Link to Social Cut on LI | V1: Link to Social Cut on X | X1: Tally - Summit (shorts are duplicated in Shorts column) | Y1: Tally - Customer | Z1: Short | AA1: Tally - Demos | AB1: Tally - Individual Videos | AC1: Snow Report | AD1: Tally - Podcast | AE1: Tally - promos | AF1: Tally - International Channel | AG1: Tally - BuiltBy | AH1: Tally-event workshops | AI1: Feature Friday | AJ1: Temp tally - PbS | AK1: BUILD | AL1: Tally - Horizon | AM1: Tally -Truck Talk
B2: Day | C2: Date | L2: Minutes | M2: Seconds
B3: NOTE: The YouTube tracking sheet for 2024 and 2023 can be found by clicking here.
B4: Wed | C4: 45693 | D4: 8 a.m. | E4: Accelerate 2025 Teaser | G4: x | H4: NA | K4: MP4; Wrike; done | L4: 1 | M4: 12 | O4: Accelerate 2025 | P4: Accelerate 2025 | Registration Is Now Open For This Virtual Event Series That Runs From March - April | Q4: Accelerate, Snowflake’s annual virtual event series, showcases how industry technology leaders are accelerating with data and AI strategies using The AI Data Cloud. Learn about the blueprints of an enterprise data architecture that puts secure self-service data consumption at its core. Hear about the latest AI / ML use cases driving efficiencies AND new data experiences. See customer proof points, demos, and real-world use cases that turn the art of the possible into real implementations. VIRTUAL EVENT DATES: Financial Services - March 6, 2025 Retail & Consumer Goods - March 20, 2025 Manufacturing - March 27, 2025 Advertising, Media & Entertainment - April 3, 2025 Public Sector - April 24, 2025 Healthcare & Life Sciences - April 30, 2025 Register now at https://www.snowflake.com/Accelerate | R4: Link | AE4: 1
B6: Tues | C6: 45699 | D6: 6 a.m. | E6: Customer Testimonial- eSentire | H6: X | K6: MP4; Wrike; done | L6: 3 | M6: 14 | O6: Transforming Cybersecurity Operations | P6: eSentire Saves 50% And Builds A Data Mesh With Snowflake | Q6: Discover how eSentire transformed its cybersecurity operations with Snowflake. In this testimonial, CTO Dustin Hillard shares how the company reduced analytical costs by 50% and built a powerful data mesh using Snowflake. By leveraging hybrid tables, eSentire delivers real-time protection to its customers while the AI Data Cloud accelerates GenAI innovation—keeping security and governance at the forefront. | R6: Link | Y6: 1
B8: Mon | C8: 45705 | D8: 9 a.m. | E8: Predictions -- AI Moves Into Production | H8: X | K8: MP4; Wrike-Edit; Wrike-Prep; done | L8: 18 | M8: 44 | O8: AI & Data Predictions 2025: AI Moves Into Production | P8: Key Considerations For Enterprises Moving AI Into Production | Q8: Data Cloud Now" anchor Ryan Green kicks off the 2025 AI & Data Predictions event with Snowflake's Baris Gultekin, Head of AI, and Vivek Raghunathan, SVP of Engineering, who join him for a conversation about moving AI into production. The conversation includes thoughts about the rise of agentic systems, the importance of addressing security and governance issues, and the challenges that AI teams face in keeping up with the rapidly evolving technology. For more on this and other predictions about the road ahead, download the AI & Data Predictions 2025 e-book here: https://www.snowflake.com/en/lp/snowflake-ai-data-predictions/ | R8: Link | AH8: 1
B9: Mon | C9: 45705 | D9: 9 a.m. | E9: Predictions -- Shweta Interview | H9: X | K9: MP4; FrameIO; Wrike1;done | L9: 13 | M9: 2 | O9: AI & Data Predictions 2025: Implementing AI Internally At Snowflake | P9: Pursuing Results-Driven AI: How Snowflake Is Implementing Gen AI Internally To Drive Outcomes | Q9: Join "Data Cloud Now" anchor Ryan Green for a conversation with Snowflake's Shweta Gummidipudi, VP of Enterprise Apps and Data, to explore how Snowflake is shifting generative AI initiatives from experimentation to actual implementation to drive real business value. For more on this and other predictions about the road ahead, download the AI & Data Predictions 2025 e-book here: https://www.snowflake.com/en/lp/snowflake-ai-data-predictions/ | R9: Link | AH9: 1
B10: Mon | C10: 45705 | D10: 9 a.m. | E10: Predictions -- AI Ethics w/Christian and Jennifer | H10: X | K10: MP4; FrameIO; Wrike1;done | L10: 16 | M10: 44 | O10: AI & Data Predictions 2025: Generative AI Ethics And Regulation | P10: A Conversation About Generative AI Ethics And Regulation | Q10: As AI continues to impact business and everyday life, it raises questions about ethics and regulation. Hear what two top Snowflake executives, EVP of Product Christian Kleinerman and Snowflake Principal Data Strategist Jennifer Belissent, have to say about these important topics in this conversation with "Data Cloud Now" anchor Ryan Green. For more on this and other predictions about the road ahead, download the AI & Data Predictions 2025 e-book here: https://www.snowflake.com/en/lp/snowflake-ai-data-predictions/ | R10: Link | AH10: 1
B11: Mon | C11: 45705 | D11: 9 a.m. | E11: Predictions -- Cybersecurity | H11: X | K11: MP4; Wrike; done | L11: 13 | M11: 54 | O11: AI & Data Predictions 2025: Evolving Security Threats | P11: Cybersecurity Predictions From Snowflake | Q11: In this session from Snowflake's AI & Data Predictions 2025 virtual event, Snowflake's CISO Brad Jones and Head of Product Security Anoosh Saboori share their thoughts about the security threats that lie ahead. One prediction: Bad actors will start to move into the ML infrastructure layer itself, forcing the model to provide the wrong answer or, worse, divulge private information—such as the data on which it was trained. Organizations then will be forced to establish a rigorous security approach to operationalizing AI. For more on this and the rest of the cybersecurity predictions, download the AI & Data Predictions 2025 e-book here: https://www.snowflake.com/en/lp/snowflake-ai-data-predictions/ | R11: link | AH11: 1
B12: Mon | C12: 45705 | D12: 9 a.m. | E12: Predictions - Forward Motion Round Robin | H12: X | K12: MP4; FrameIO; Wrike;done | L12: 9 | M12: 33 | O12: AI & Data Predictions 2025: A Roud Robin Discussion About the Road Ahead | P12: AI Is Rapidly Transforming How Businesses Operate. Are You Ready For What’s Next? | Q12: AI remains the top story across every business and sector. As we all look out on 2025, Baris Gultekin, Head of AI, Christian Kleinerman, EVP of Product, and Vivek Raghunathan, SVP of Engineering, join Amanda Kelly, Director of Product Experiences and Co-Founder of Streamlit, to discuss what they are most excited about and their hot takes. For more on this and other predictions about the road ahead, download the AI & Data Predictions 2025 e-book here: https://www.snowflake.com/en/lp/snowflake-ai-data-predictions/ | R12: Link | AH12: 1
B14: Tues | C14: 45713 | D14: 6 a.m. | E14: Customer-One NZ Dials in its AI Strategy | H14: X | K14: MP4; Wrike; done | L14: 2 | M14: 15 | O14: Key Benefits of Cortex AI | P14: One NZ Dials In Its AI Strategy With The Help Of Snowflake Cortex AI | Q14: One NZ, New Zealand's leading network provider, embraces Snowflake's Cortex AI to drive its implementation of generative AI. In this video, Johnny Huang, Head of Data and AI Products at One NZ, explains how Cortex AI's easy-to-use interface and its ability to keep data secure have been critical to One NZ's ability to use AI to enhance its operations. | R14: Link | Y14: 1
B15: Wed | C15: 45714 | D15: 8 a.m. | E15: Customer-Spark NZ sets data foundations | H15: X | K15: MP4; Wrike; done | L15: 2 | M15: 26 | O15: Building AI Solutions On A Strong Data Foundation | P15: Spark NZ Sets Secure, Governed Data Foundations For The Era Of AI | Q15: Over the past few years, Spark New Zealand has tackled the challenge of creating a strong data foundation by moving all of its data warehouses into Snowflake to create a centralised data platform. Now, explains Pritha Chattopadhyay, Domain Chapter Lead at Spark, this telecommunications leader and digital services provider is diving into artificial intelligence with the help of Snowflake Cortex AI. Tune in to learn about the benefits it provides. | R15: Link | Y15: 1
B16: Wed | C16: 45714 | D16: 3:45 p.m. | E16: Short-Sridhar Announces Open AI Partnership with MS | H16: X | K16: MP4; Wrike; done | L16: 1 | M16: 26 | O16: NA | P16: Snowflake Securely Integrates Microsoft Azure OpenAI Service | Q16: Learn how Snowflake is expanding its partnership with Microsoft to bring OpenAI’s state-of-the-art models to Snowflake Cortex AI. Go here to learn more: https://bit.ly/SnowflakeIntegrateOpenAI | R16: NA | AE16: 1
B17: Thurs | C17: 45715 | D17: 11 a.m. | E17: DCN at HIMSS Promo | H17: X | K17: MP4; Wrike; | L17: 0 | M17: 38 | O17: The AI Data Cloud For Healthcare and Life Sciences | P17: Snowflake Brings The AI Data Cloud For Healthcare and Life Sciences To HIMSS 2025 | Q17: "Data Cloud Now" anchor Ryan Green will be traveling to the 2025 HIMSS Global Health Conference & Exhibition in Las Vegas during the first week of March to report on data and AI trends in the healthcare and life sciences industries. Snowflake will be there in force showcasing how its technology can improve health outcomes, speed time to market, optimize supply chains and build client 360s. To learn more about Snowflake's presence at the show, click here: https://www.snowflake.com/visit-snowflake-at-himss-2025-2/ | R17: Link | AE17: 1
B18: Friday | C18: 45716 | D18: 10 a.m. | E18: Feature Friday-Data Quality Monitoring | H18: X | K18: MP4; Wrike; done | L18: 12 | M18: 54 | O18: Continuous Data Quality Monitoring | P18: Data Quality Monitoring: Enabling Reliable, High-Integrity Data | Q18: In this demo, we’ll show you how to create a custom Data Metric Function (DMF), associate it with your tables for continuous data quality monitoring, and query the results from a centralized table. Watch to learn how built-in monitoring helps you track critical data objects, identify quality issues, and take quick action to ensure reliable, high-integrity data across your organization. | R18: Link | T18: Link | AI18: 1 | AQ18: 1
B19: Friday | C19: 45716 | D19: 11 a.m. | E19: Promo--Snowflake BUILD EMEA 2025 | H19: X | K19: MP4; Wrike; (leave this as Unlisted?) | L19: 1 | M19: 6 | O19: Just used a still from the video | P19: Get Ready for BUILD 2025 | Q19: BUILD: The Dev Conference for AI and Apps is coming soon! Make your plans now to join developers, data scientists, engineers, and all data professionals for three days of exclusive product announcements,“how to” technical sessions, and hands-on labs focused on Snowflake’s latest innovations. Learn how to build data pipelines, models and apps in the age of generative AI and LLMs. | R19: NA | AE19: 1
B21: Wed | C21: 45721 | D21: 6 a.m. | E21: Customer-BAMA Creates a Fresh and Healthy Future with Snowflake | H21: X | K21: MP4; Wrike; done | L21: 1 | M21: 51 | O21: Bulding ML Models To Enhance Financial Operations | P21: BAMA Creates A Fresh And Healthy Future With Snowflake | Q21: BAMA Gruppen AS is Norway's largest private distributor of fruits and vegetables. In this video, Hans Martin Espegren, Manager of Data Science at BAMA, explains how Snowflake’s centralized data platform makes BAMA’s data more available across the organization, empowering them to make smarter business decisions. | R21: Link | Y21: 1
B22: Thur | C22: 45722 | D22: 11:30 a.m. | E22: 30-second Version of Accelerate Trailer | H22: X | K22: MP4; Wrike; (leave this unlisted) | L22: 0 | M22: 27 | O22: Accelerate 2025 | P22: Accelerate 2025 | Registration Is Now Open For This Virtual Event Series That Runs From March - April | Q22: Accelerate, Snowflake’s annual virtual event series, showcases how industry technology leaders are accelerating with data and AI strategies using The AI Data Cloud. Learn about the blueprints of an enterprise data architecture that puts secure self-service data consumption at its core. Hear about the latest AI / ML use cases driving efficiencies AND new data experiences. See customer proof points, demos, and real-world use cases that turn the art of the possible into real implementations. VIRTUAL EVENT DATES: Financial Services - March 6, 2025 Retail & Consumer Goods - March 20, 2025 Manufacturing - March 27, 2025 Advertising, Media & Entertainment - April 3, 2025 Public Sector - April 24, 2025 Healthcare & Life Sciences - April 30, 2025 Register now at https://www.snowflake.com/Accelerate | R22: Link | AE22: 1
B23: Friday | C23: 45723 | D23: 10 a.m. | E23: Feature Friday-Dynamic Tables | H23: X | K23: MP4; Wrike; done | L23: 16 | M23: 35 | O23: Dynamic Tables for Data Engineering | P23: Building Cost-Effective, Real-Time Pipelines with Snowflake Dynamic Tables | Q23: Join Sales Engineer Gabriel Mullen as he demonstrates how Snowflake’s Dynamic Tables streamline real-time data pipelines. Discover a simple, declarative approach to ingest data incrementally, maintain cost efficiency, and keep insights fresh. This demo will walk through setting target lag, leveraging incremental refreshes, and automating orchestration, allowing you to power analytics and BI dashboards with minimal overhead and maximum performance. | R23: Link | AI23: 1
A24: TRUE | B24: Mon | C24: 46041 | E24: Discover AI - Korea Teaser Video | I24: Discover-AI-Openning-25-sec-V5-RegisterNow-Korea-v2.mp4 | N24: https://youtu.be/0GxZhEOcz4Y
A26: TRUE | B26: Thurs | C26: 46051 | E26: Snowflake BUILD KOREA 2025 Video 1 | G26: Bobby | I26: 1.SNOWFLAKE BUILD KOREA_SOO LEE_v2.mp4 | J26: https://files.wrike.com/1989536/670633339 | N26: https://youtu.be/lrY3JzzddFA | O26: BUILD KOREA: 오프닝 키노트 | P26: BUILD KOREA: 오프닝 키노트 | Q26: 2025.12. 09 ㅣ BUILD KOREA 2025 이번 Snowflake BUILD KOREA에서는 AI 시대, 전에 없던 개발을 위한 가장 혁신적인 솔루션 구축 방법을 소개드렸습니다. 1) 조직의 모든 데이터를 한 곳으로 모으고, 2) AI 툴로 개발 워크플로우의 효율성일 높이며, 3) Agent AI로 누구나 AI를 활용할 수 있도록 지원하는 Snowflake AI-Ready 데이터 플랫폼의 혁신 기술들을 만나보세요. #BUILD #DeveloperConference #AIDataCloud #AgentAI
A27: TRUE | B27: Fri | C27: 46052 | E27: Snowflake BUILD KOREA 2025 Video 2 | G27: Bobby | I27: 2.SNOWFLAKE BUILD KOREA_황주연_v2.mp4 | J27: https://files.wrike.com/1989536/674995762 | N27: https://youtu.be/7skTuN-UIoY | O27: Snowflake 관리형 MCP 서버: 엔터프라이즈 AI를 위한 효율적인 데이터 전략 | P27: Snowflake 관리형 MCP 서버: 엔터프라이즈 AI를 위한 효율적인 데이터 전략 | Q27: 2025.12. 09 ㅣ BUILD KOREA 2025 이번 Snowflake BUILD KOREA에서는 AI 시대, 전에 없던 개발을 위한 가장 혁신적인 솔루션 구축 방법을 소개드렸습니다. 1) 조직의 모든 데이터를 한 곳으로 모으고, 2) AI 툴로 개발 워크플로우의 효율성일 높이며, 3) Agent AI로 누구나 AI를 활용할 수 있도록 지원하는 Snowflake AI-Ready 데이터 플랫폼의 혁신 기술들을 만나보세요. #BUILD #DeveloperConference #AIDataCloud #MCPserver
A28: TRUE | B28: Mon | C28: 46055 | E28: Snowflake BUILD KOREA 2025 Video 3 | G28: Bobby | I28: 3.SNOWFLAKE BUILD KOREA_김기우_v3.mp4 | J28: https://files.wrike.com/1989536/674998733 | N28: https://youtu.be/P9nv41amXfI | O28: Snowflake Cortex AI Functions: 모든 유형의 고객 서비스 데이터에서 인사이트 발견하기 | P28: Snowflake Cortex AI Functions: 모든 유형의 고객 서비스 데이터에서 인사이트 발견하기 | Q28: 2025.12. 09 ㅣ BUILD KOREA 2025 이번 Snowflake BUILD KOREA에서는 AI 시대, 전에 없던 개발을 위한 가장 혁신적인 솔루션 구축 방법을 소개드렸습니다. 1) 조직의 모든 데이터를 한 곳으로 모으고, 2) AI 툴로 개발 워크플로우의 효율성일 높이며, 3) Agent AI로 누구나 AI를 활용할 수 있도록 지원하는 Snowflake AI-Ready 데이터 플랫폼의 혁신 기술들을 만나보세요. #BUILD #DeveloperConference #AIDataCloud #CortexAIFunctions
A29: TRUE | B29: Tues | C29: 46056 | E29: Snowflake BUILD KOREA 2025 Video 4 | G29: Bobby | I29: 4.SNOWFLAKE BUILD KOREA_김덕하.mp4 | J29: https://files.wrike.com/1989536/675004856 | N29: https://youtu.be/1rT0tJPsjCM | O29: 처음부터 시작하는 엔드 투 엔드 머신러닝 프로젝트 구축 가이드 | P29: 처음부터 시작하는 엔드 투 엔드 머신러닝 프로젝트 구축 가이드 | Q29: 2025.12. 09 ㅣ BUILD KOREA 2025 이번 Snowflake BUILD KOREA에서는 AI 시대, 전에 없던 개발을 위한 가장 혁신적인 솔루션 구축 방법을 소개드렸습니다. 1) 조직의 모든 데이터를 한 곳으로 모으고, 2) AI 툴로 개발 워크플로우의 효율성일 높이며, 3) Agent AI로 누구나 AI를 활용할 수 있도록 지원하는 Snowflake AI-Ready 데이터 플랫폼의 혁신 기술들을 만나보세요. #BUILD #DeveloperConference #AIDataCloud #MachineLearning
A30: TRUE | B30: Fri | C30: 46073 | E30: Snowflake World Tour Seoul 2025 (30 Videos) | G30: Bobby | H30: Snowflake World Tour Seoul 2025 | J30: media-seoul-1920x1080 .12.png | N30: https://youtube.com/playlist?list=PL8PIJ9SpWQWrIJecFtSmqPW6jSafSSGMr&si=QJjr8j27XXWeEv5N
A31: TRUE | B31: Thurs | C31: 46065 | E31: Data for breakfast | Germany | 2026 | G31: Bobby | N31: https://youtu.be/azO4iiewKVY | P31: Data for breakfast | Germany | 2026 | Q31: Join us for breakfast to gain actionable AI insights and strategies. Leave ready to lead your team in this new era of data and agentic intelligence.
A32: FALSE
A33: FALSE
A34: FALSE
A35: FALSE
A36: FALSE
A37: FALSE
A38: FALSE
A39: FALSE
A40: FALSE
A41: FALSE
A42: FALSE
A43: FALSE
... A65: FALSE

Sheet 2025 Archive Snowflake Inc.
A1: Scheduled / Published | B1: YouTube Publishing Date | D1: Time of Publishing (PST) | E1: Title / Wrike | F1: Social Request Submitted? | G1: Producer | H1: Playlist Designated? | I1: MP4 | J1: THUMB | K1: NOTES | L1: LENGTH OF VIDEO | N1: YT Link | O1: Thumbnail Title | P1: YouTube Title | Q1: YouTube Description | R1: Link to Thumbnail LINK TO THUMBNAIL FOLDER | S1: Link to Video Transcript | T1: Link to Social Cut | U1: Link to Social Cut on LI | V1: Link to Social Cut on X | X1: Tally - Summit (shorts are duplicated in Shorts column) | Y1: Tally - Customer | Z1: Short | AA1: Tally - Demos | AB1: Tally - Individual Videos | AC1: Snow Report | AD1: Tally - Podcast | AE1: Tally - promos | AF1: Tally - International Channel | AG1: Tally - BuiltBy | AH1: Tally-event workshops | AI1: Feature Friday | AJ1: Temp tally - PbS | AK1: BUILD | AL1: Tally - Horizon | AM1: Tally -Truck Talk
A2: FALSE
A3: FALSE | B3: Thurs | C3: 45694 | D3: 10 a.m. | E3: Snow Report for February | H3: X | K3: MP4; FrameIO; Wrike; done | L3: 2 | M3: 9 | O3: Snow Report February | P3: Snow Report: What's Happening At Snowflake In February | Q3: This month's edition of the Snow Report features insights from venture capitalists on starting an AI business in 2025. It also includes new product announcements, such as the integration of Anthropic's Claude 3.5 Sonnet into Cortex AI, as well customer stories, technical tips, and info on upcoming events. To access the full newsletter, click here (INSERT LINK) | R3: Link | AC3: 1
B5: Tues | C5: 45699 | D5: 6 a.m. | E5: Customer Testimonial- eSentire | H5: X | K5: MP4; Wrike; done | L5: 3 | M5: 14 | O5: Transforming Cybersecurity Operations | P5: eSentire Saves 50% And Builds A Data Mesh With Snowflake | Q5: Discover how eSentire transformed its cybersecurity operations with Snowflake. In this testimonial, CTO Dustin Hillard shares how the company reduced analytical costs by 50% and built a powerful data mesh using Snowflake. By leveraging hybrid tables, eSentire delivers real-time protection to its customers while the AI Data Cloud accelerates GenAI innovation—keeping security and governance at the forefront. | R5: Link | Y5: 1
B7: Mon | C7: 45705 | D7: 9 a.m. | E7: Predictions -- AI Moves Into Production | H7: X | K7: MP4; Wrike-Edit; Wrike-Prep; done | L7: 18 | M7: 44 | O7: AI & Data Predictions 2025: AI Moves Into Production | P7: Key Considerations For Enterprises Moving AI Into Production | Q7: Data Cloud Now" anchor Ryan Green kicks off the 2025 AI & Data Predictions event with Snowflake's Baris Gultekin, Head of AI, and Vivek Raghunathan, SVP of Engineering, who join him for a conversation about moving AI into production. The conversation includes thoughts about the rise of agentic systems, the importance of addressing security and governance issues, and the challenges that AI teams face in keeping up with the rapidly evolving technology. For more on this and other predictions about the road ahead, download the AI & Data Predictions 2025 e-book here: https://www.snowflake.com/en/lp/snowflake-ai-data-predictions/ | R7: Link | AH7: 1
B8: Mon | C8: 45705 | D8: 9 a.m. | E8: Predictions -- Shweta Interview | H8: X | K8: MP4; FrameIO; Wrike1;done | L8: 13 | M8: 2 | O8: AI & Data Predictions 2025: Implementing AI Internally At Snowflake | P8: Pursuing Results-Driven AI: How Snowflake Is Implementing Gen AI Internally To Drive Outcomes | Q8: Join "Data Cloud Now" anchor Ryan Green for a conversation with Snowflake's Shweta Gummidipudi, VP of Enterprise Apps and Data, to explore how Snowflake is shifting generative AI initiatives from experimentation to actual implementation to drive real business value. For more on this and other predictions about the road ahead, download the AI & Data Predictions 2025 e-book here: https://www.snowflake.com/en/lp/snowflake-ai-data-predictions/ | R8: Link | AH8: 1
B9: Mon | C9: 45705 | D9: 9 a.m. | E9: Predictions -- AI Ethics w/Christian and Jennifer | H9: X | K9: MP4; FrameIO; Wrike1;done | L9: 16 | M9: 44 | O9: AI & Data Predictions 2025: Generative AI Ethics And Regulation | P9: A Conversation About Generative AI Ethics And Regulation | Q9: As AI continues to impact business and everyday life, it raises questions about ethics and regulation. Hear what two top Snowflake executives, EVP of Product Christian Kleinerman and Snowflake Principal Data Strategist Jennifer Belissent, have to say about these important topics in this conversation with "Data Cloud Now" anchor Ryan Green. For more on this and other predictions about the road ahead, download the AI & Data Predictions 2025 e-book here: https://www.snowflake.com/en/lp/snowflake-ai-data-predictions/ | R9: Link | AH9: 1
B10: Mon | C10: 45705 | D10: 9 a.m. | E10: Predictions -- Cybersecurity | H10: X | K10: MP4; Wrike; done | L10: 13 | M10: 54 | O10: AI & Data Predictions 2025: Evolving Security Threats | P10: Cybersecurity Predictions From Snowflake | Q10: In this session from Snowflake's AI & Data Predictions 2025 virtual event, Snowflake's CISO Brad Jones and Head of Product Security Anoosh Saboori share their thoughts about the security threats that lie ahead. One prediction: Bad actors will start to move into the ML infrastructure layer itself, forcing the model to provide the wrong answer or, worse, divulge private information—such as the data on which it was trained. Organizations then will be forced to establish a rigorous security approach to operationalizing AI. For more on this and the rest of the cybersecurity predictions, download the AI & Data Predictions 2025 e-book here: https://www.snowflake.com/en/lp/snowflake-ai-data-predictions/ | R10: link | AH10: 1
B11: Mon | C11: 45705 | D11: 9 a.m. | E11: Predictions - Forward Motion Round Robin | H11: X | K11: MP4; FrameIO; Wrike;done | L11: 9 | M11: 33 | O11: AI & Data Predictions 2025: A Roud Robin Discussion About the Road Ahead | P11: AI Is Rapidly Transforming How Businesses Operate. Are You Ready For What’s Next? | Q11: AI remains the top story across every business and sector. As we all look out on 2025, Baris Gultekin, Head of AI, Christian Kleinerman, EVP of Product, and Vivek Raghunathan, SVP of Engineering, join Amanda Kelly, Director of Product Experiences and Co-Founder of Streamlit, to discuss what they are most excited about and their hot takes. For more on this and other predictions about the road ahead, download the AI & Data Predictions 2025 e-book here: https://www.snowflake.com/en/lp/snowflake-ai-data-predictions/ | R11: Link | AH11: 1
B13: Tues | C13: 45713 | D13: 6 a.m. | E13: Customer-One NZ Dials in its AI Strategy | H13: X | K13: MP4; Wrike; done | L13: 2 | M13: 15 | O13: Key Benefits of Cortex AI | P13: One NZ Dials In Its AI Strategy With The Help Of Snowflake Cortex AI | Q13: One NZ, New Zealand's leading network provider, embraces Snowflake's Cortex AI to drive its implementation of generative AI. In this video, Johnny Huang, Head of Data and AI Products at One NZ, explains how Cortex AI's easy-to-use interface and its ability to keep data secure have been critical to One NZ's ability to use AI to enhance its operations. | R13: Link | Y13: 1
B14: Wed | C14: 45714 | D14: 8 a.m. | E14: Customer-Spark NZ sets data foundations | H14: X | K14: MP4; Wrike; done | L14: 2 | M14: 26 | O14: Building AI Solutions On A Strong Data Foundation | P14: Spark NZ Sets Secure, Governed Data Foundations For The Era Of AI | Q14: Over the past few years, Spark New Zealand has tackled the challenge of creating a strong data foundation by moving all of its data warehouses into Snowflake to create a centralised data platform. Now, explains Pritha Chattopadhyay, Domain Chapter Lead at Spark, this telecommunications leader and digital services provider is diving into artificial intelligence with the help of Snowflake Cortex AI. Tune in to learn about the benefits it provides. | R14: Link | Y14: 1
B15: Wed | C15: 45714 | D15: 3:45 p.m. | E15: Short-Sridhar Announces Open AI Partnership with MS | H15: X | K15: MP4; Wrike; done | L15: 1 | M15: 26 | O15: NA | P15: Snowflake Securely Integrates Microsoft Azure OpenAI Service | Q15: Learn how Snowflake is expanding its partnership with Microsoft to bring OpenAI’s state-of-the-art models to Snowflake Cortex AI. Go here to learn more: https://bit.ly/SnowflakeIntegrateOpenAI | R15: NA | AE15: 1
B16: Thurs | C16: 45715 | D16: 11 a.m. | E16: DCN at HIMSS Promo | H16: X | K16: MP4; Wrike; | L16: 0 | M16: 38 | O16: The AI Data Cloud For Healthcare and Life Sciences | P16: Snowflake Brings The AI Data Cloud For Healthcare and Life Sciences To HIMSS 2025 | Q16: "Data Cloud Now" anchor Ryan Green will be traveling to the 2025 HIMSS Global Health Conference & Exhibition in Las Vegas during the first week of March to report on data and AI trends in the healthcare and life sciences industries. Snowflake will be there in force showcasing how its technology can improve health outcomes, speed time to market, optimize supply chains and build client 360s. To learn more about Snowflake's presence at the show, click here: https://www.snowflake.com/visit-snowflake-at-himss-2025-2/ | R16: Link | AE16: 1
B17: Friday | C17: 45716 | D17: 10 a.m. | E17: Feature Friday-Data Quality Monitoring | H17: X | K17: MP4; Wrike; done | L17: 12 | M17: 54 | O17: Continuous Data Quality Monitoring | P17: Data Quality Monitoring: Enabling Reliable, High-Integrity Data | Q17: In this demo, we’ll show you how to create a custom Data Metric Function (DMF), associate it with your tables for continuous data quality monitoring, and query the results from a centralized table. Watch to learn how built-in monitoring helps you track critical data objects, identify quality issues, and take quick action to ensure reliable, high-integrity data across your organization. | R17: Link | T17: Link | AI17: 1 | AQ17: 1
B18: Friday | C18: 45716 | D18: 11 a.m. | E18: Promo--Snowflake BUILD EMEA 2025 | H18: X | K18: MP4; Wrike; (leave this as Unlisted?) | L18: 1 | M18: 6 | O18: Just used a still from the video | P18: Get Ready for BUILD 2025 | Q18: BUILD: The Dev Conference for AI and Apps is coming soon! Make your plans now to join developers, data scientists, engineers, and all data professionals for three days of exclusive product announcements,“how to” technical sessions, and hands-on labs focused on Snowflake’s latest innovations. Learn how to build data pipelines, models and apps in the age of generative AI and LLMs. | R18: NA | AE18: 1
B20: Wed | C20: 45721 | D20: 6 a.m. | E20: Customer-BAMA Creates a Fresh and Healthy Future with Snowflake | H20: X | K20: MP4; Wrike; done | L20: 1 | M20: 51 | O20: Bulding ML Models To Enhance Financial Operations | P20: BAMA Creates A Fresh And Healthy Future With Snowflake | Q20: BAMA Gruppen AS is Norway's largest private distributor of fruits and vegetables. In this video, Hans Martin Espegren, Manager of Data Science at BAMA, explains how Snowflake’s centralized data platform makes BAMA’s data more available across the organization, empowering them to make smarter business decisions. | R20: Link | Y20: 1
A21: FALSE | B21: Thur | C21: 45722 | D21: 1:30 p.m. | E21: Snow Report for March | H21: X | K21: MP4; Wrike; thumb done (still needs to be scheduled; also need the proper link to the newsletter) | L21: 2 | M21: 32 | O21: Snow Report March | P21: Snow Report: What's Happening At Snowflake In March | Q21: This month's edition of the Snowflake Snow Report provides information on Snowflake's Data for Breakfast events and the Accelerate 2025 virtual event series. It also provides details on Snowflake Cortex Agents, now in public preview, pandas on Snowflake, Snowflake ML, and much more. To access the full newsletter, click here: https://info.snowflake.com/index.php/email/emailWebview?email=MjUyLVJGTy0yMjcAAAGX5gIhRarFZk2dlFtoV6FlR3-Vf-ZMZxinzW9VeeCQOyYYozYCfYaw-yw3xLj62nlX1-GBLvMsLvzwQ6HTlj3ZSkpG79Hft1vnIq8&_ga=2.180186918.322876961.1741295503-1517567723.1741195236 | R21: Link | S21: Link | T21: Under 200MB version; | AC21: 1
B22: Thur | C22: 45722 | D22: 11:30 a.m. | E22: 30-second Version of Accelerate Trailer | H22: X | K22: MP4; Wrike; (leave this unlisted) | L22: 0 | M22: 27 | O22: Accelerate 2025 | P22: Accelerate 2025 | Registration Is Now Open For This Virtual Event Series That Runs From March - April | Q22: Accelerate, Snowflake’s annual virtual event series, showcases how industry technology leaders are accelerating with data and AI strategies using The AI Data Cloud. Learn about the blueprints of an enterprise data architecture that puts secure self-service data consumption at its core. Hear about the latest AI / ML use cases driving efficiencies AND new data experiences. See customer proof points, demos, and real-world use cases that turn the art of the possible into real implementations. VIRTUAL EVENT DATES: Financial Services - March 6, 2025 Retail & Consumer Goods - March 20, 2025 Manufacturing - March 27, 2025 Advertising, Media & Entertainment - April 3, 2025 Public Sector - April 24, 2025 Healthcare & Life Sciences - April 30, 2025 Register now at https://www.snowflake.com/Accelerate | R22: Link | AE22: 1
B23: Friday | C23: 45723 | D23: 10 a.m. | E23: Feature Friday-Dynamic Tables | H23: X | K23: MP4; Wrike; done | L23: 16 | M23: 35 | O23: Dynamic Tables for Data Engineering | P23: Building Cost-Effective, Real-Time Pipelines with Snowflake Dynamic Tables | Q23: Join Sales Engineer Gabriel Mullen as he demonstrates how Snowflake’s Dynamic Tables streamline real-time data pipelines. Discover a simple, declarative approach to ingest data incrementally, maintain cost efficiency, and keep insights fresh. This demo will walk through setting target lag, leveraging incremental refreshes, and automating orchestration, allowing you to power analytics and BI dashboards with minimal overhead and maximum performance. | R23: Link | AI23: 1
A24: FALSE
A25: FALSE | B25: Mon | C25: 45726 | D25: 6 a.m. | E25: Customer-2degrees | H25: X | K25: MP4; Wrike; done | L25: 3 | M25: 17 | O25: Optimizing Data-Driven Marketing Efforts | P25: Delivering The Right Message To The Right Person At The Right Time With Help From the AI Data Cloud | Q25: 2degrees is a full-service telco, infrastructure owner, and an energy retailer connecting people and businesses all around New Zealand. The combined business has approximately 1,600 employees who serve 2 million-plus customers. In 2022, the company experienced a significant merger, which resulted in the challenge of having three billing platforms, two finance ERPs, two data warehouses, and two completely separate data teams. Snowflake not only made it easy to unify that data but improved the ease and speed of accessing that data, enabling the business to optimize its marketing efforts so that it could deliver the right message to the right person at the right time. In this video, 2degrees colleagues Stephen Kurzeja, Peter McCallum, and Anna Gavin share details about the 2degrees data journey. | R25: Link | Y25: 1
A26: FALSE | B26: Fri | C26: 45730 | D26: 10 a.m. | E26: Feature Friday-Trust Center | H26: X | K26: MP4; FrameIO; Wrike; Wrike-Prep done | L26: 8 | M26: 0 | O26: Using Snowflake's Trust Center | P26: Strengthen Your Cloud Security With Snowflake’s Trust Center | Q26: Snowflake’s Trust Center, now in general availability, delivers a unified way to identify, address, and monitor security risks. Discover how scanner packages (Security Essentials, CIS Benchmark, and more) streamline compliance checks, reduce costs, and simplify account security across multiple clouds. See how to configure scans, resolve vulnerabilities, and enforce best practices for user authentication, network policies, and more. Take a proactive approach to safeguarding sensitive data and learn how the Trust Center supports Snowflake’s shared security model. | R26: Link | AI26: 1
A27: FALSE | B27: Fri | C27: 45730 | D27: 11 a.m. | E27: Customer- AI Data Cloud helps GXS Bank | H27: X | K27: MP4; Wrike; done | L27: 3 | M27: 25 | O27: Scalability, Ease of Use, And Data Integration | P27: AI Data Cloud Helps GXS Bank On Its Next Stage Of Growth | Q27: GxS Bank in Singapore embraces Snowflake to power innovation and its next stage of growth. Its wide-ranging benefits include the following: - Comprehensive integration of systems: Seamlessly connecting with various business-critical systems, Snowflake has successfully unified GxS Bank's entire data ecosystem, including Axiom for regulatory reporting, Oracle for finance operations, Salesforce for marketing activities, and dbt for transformation logic and quality assurance. - Simplicity and ease of use empowers more workers: Snowflake's user-friendly interface has dramatically simplified data operations, enabling even non-SQL experts to perform daily data extraction tasks. The platform was quickly implemented, taking just a few days to complete the setup to a medallion architecture. - Dynamic scalability to support cost-management goals: Offering exceptional flexibility in resource management, Snowflake allows GxS Bank to scale computing power up or down based on demand. This adaptability enables the bank to customize its data solutions, while maintaining cost controls through precise resource allocation. | R27: Link | Y27: 1
A28: FALSE
A29: FALSE | B29: Tues | C29: 45734 | D29: 6 a.m. | E29: Customer- Domain Drives better customer experiences with Cortex AI | H29: X | K29: MP4; Wrike; done | L29: 1 | M29: 27 | O29: Bringing AI To The Property Marketplace | P29: Providing Better Customer Experiences With The Help Of Cortex AI | Q29: Headquartered in Sydney, Domain Group is a leading Australian property marketplace. Its mission is to inspire confidence in life’s property decisions, and its property marketplace tools reach an average audience of 7 million Australians every month. A long-time Snowflake customer, Domain has started to work with Cortex Analyst in order to enable its staff to query its large data sets using natural language. Thanks to a successful POC, Domain is now looking to extend the solution out to the broader business, enabling its team to drive even better customer experiences. | R29: Link | Y29: 1
A30: FALSE | B30: Fri | C30: 45737 | D30: 10 a.m. | E30: Feature Friday--Snowflake Pandas | H30: X | K30: MP4; FrameIO; Wrike; done (do A/B test on thumbs) | L30: 15 | M30: 25 | O30: Working with Pandas on Snowflake | P30: Scale Your Python Analytics with Pandas on Snowflake | Q30: Massive data sets can overwhelm native Pandas, causing memory issues and slow performance. Pandas on Snowflake eliminates these constraints by running Python code directly in Snowflake, with no rewrites needed. This demo shows how to transform and visualize large datasets using the familiar Pandas API with Snowflake’s distributed compute. Boost your data workflows and maintain security and governance, all while staying within the Pandas ecosystem. | R30: ThumbA; ThumbB | S30: Link | T30: Under 200MB version | AI30: 1
A31: FALSE
A32: FALSE | B32: Tues | C32: 45741 | D32: 8 a.m. | E32: Short-Customer - Purple | H32: X | K32: MP4; Wrike; done | L32: 0 | M32: 39 | O32: NA | P32: Production That Never Hits Snooze | Q32: Purple uses Snowflake to optimize production, track inventory in real time, and deliver mattresses faster. With better data insights, they ensure a seamless experience—so customers can rest easy. Sweet dreams! | R32: NA | Z32: 1
A33: FALSE
A34: FALSE | B34: Fri | C34: 45751 | D34: 6 a.m. | E34: Customer - The RAC Fuels its AI Ambitions | H34: X | K34: MP4; Wrike; done | L34: 1 | M34: 49 | O34: AI Data Cloud Improves Roadside Assistance | P34: RAC Achieves Faster Time To Insights With Data Consolidated On Snowflake's AI Data Cloud | Q34: Discover how UK-based RAC, a household name in roadside assistance, is transforming its customer service and operations with Snowflake’s AI Data Cloud. By unifying its data platform, RAC has cut call handling times by 30%, enhanced decision-making with real-time insights, and streamlined collaboration with partners. Snowflake’s scalability and AI capabilities are empowering RAC to deliver smarter, more personalized services as well as better customer experiences. To read more, click here: https://www.snowflake.com/en/customers/all-customers/case-study/rac/?clear-cache=ooeot | R34: Link | Y34: 1
A35: FALSE | B35: Sat | C35: 45752 | D35: 6 a.m. | E35: Snow Report April | K35: MP4; FrameIO; Wrike; done | L35: 2 | M35: 41 | O35: Snow Report April | P35: Snow Report: What's Happening At Snowflake In April | Q35: Learn about the beneftis of Snowflake Notebooks on Container Runtime and Snowflake's Internal Marketplace in this month's edition of the Snow Report. The issue also offers helpful tips on how to use Cortext AI to build AI apps and enterprise-grade AI agents as well as details about coming events. To access the newsletter, click here: https://info.snowflake.com/index.php/email/emailWebview?email=MjUyLVJGTy0yMjcAAAGZoTatdruuBfY4TqhQhtqX19ZNslVUdtXZIcZo09kqFPXVCswAF_JDjeETXnMwhJpl_iAMhQKLvlPyNvVHYJR6Rp8jt9Qp3H0qOGs | R35: Link | S35: Link | AC35: 1
A36: FALSE
A37: FALSE | B37: Mon | C37: 45754 | D37: 8:30 a.m | E37: International-Data for Breakfast Tokyo 2025 Highlights | H37: X | K37: MP4; Wrike; done | L37: 1 | M37: 29 | O37: In Japanese | P37: 2025年3月27日（金）｜Data for Breakfast Tokyo | Q37: Snowflakeの創設者であるBenoit Dageville（ベノワ・デイジビル）とThierry Cruanes（ティエリー・クルアネス）を迎え開催されたData for Breakfast Tokyo 2025。コカ・コーラボトラーズジャパン、野村ホールディングスによる国内導入カスタマーセッションをはじめ、AWS、Qlik、CONFLUENT、dbt Labs、Fivetranによるパートナー・ソリューションのご紹介など、AIとデータを活用したビジネス変革に向けた具体的なステップを探求する半日イベント。大盛況の様子をハイライトでご覧ください。 Snowflakeについて、さらに理解を深めるにはこちらをご参照ください。 リソース：https://www.snowflake.com/ja/resources/ | R37: LINK | AF37: 1
A38: FALSE | B38: Tues | C38: 45755 | D38: 1:59 a.m. | E38: Podcast-Sridhar Interview | H38: X | K38: MP4; FrameIO; Wrike; done | L38: 38 | M38: 24 | O38: Making AI Useful for Enterprises | P38: Beyond the Hype: Putting Enterprise AI to Work | Q38: In this episode, Dana Gardner, Principal Analyst at Interarbor Solutions is joined by Sridhar Ramaswamy, CEO of Snowflake. They discuss the impactful integration of AI with enterprise data, Snowflake's efforts to demystify AI for its customers, and future prospects for agentic AI and its potential to transform business processes. | R38: Link | AD38: 1
A39: FALSE | B39: Thurs | C39: 45757 | D39: Noon | E39: Short-Podcast-Sridhar Interview | H39: NA | K39: MP4; | L39: 0 | M39: 46 | O39: NA | P39: Beyond the Hype: Putting Enterprise AI to Work | Q39: Find the full podcast interview here: https://youtu.be/c95B1arxZlU | R39: NA | Z39: 1
A40: FALSE
A41: FALSE | B41: All | C41: April 2 - 16 | D41: 6 a.m. | E41: International - Snowflake World Tour Seoul 2024 (22 videos) | H41: X | K41: MP4; Wrike; Spreadsheet; (for international channel) | O41: See spreadsheet | P41: SEE ALL VIDEOS IN THIS PLAYLIST | Q41: See spreadsheet | R41: See Spreadsheet for links | AF41: 22
A42: FALSE | B42: Wed | C42: 45763 | D42: 6 a.m. | E42: Roundtable Discussion-Cortex AI Unstructured Data | H42: X | K42: MP4;FrameIO; headshots; Wrike; done | L42: 12 | M42: 11 | O42: Batch LLM Inference At Scale | P42: Unstructured Data Analytics For Enterprises | Q42: Get insights from your unstructured data in minutes without wrestling with pipelines or infrastructure. Using simple SQL, enterprises can translate multi-language text, understand and extract sentiment from reviews, classify key themes, and summarize millions of records faster than ever. With built-in governance, enterprise-grade security, and production scalability, you can trust the speed and reliability of your intelligence. Join Snowflake’s Arun Agarwal, Renee Huang, and Vino Duraisamy to see how Snowflake Cortex AI makes this easy. To learn more, click on the links below: Get started with Cortex LLMs with this guided course (Coursera) https://bit.ly/SF-GenAI-Course Blog: Scale Unstructured Text Analytics with Efficient Batch LLM Inference https://bit.ly/SF-Blog-LLMinference Customer Reviews Analytics Quickstart https://bit.ly/SF-Quickstart-UnstructuredData To view the other two videos in this GenAI roundtable series, click on these links: (ADD LINKS) | R42: Link | AA42: 1
A43: FALSE | B43: Thurs | C43: 45764 | D43: 6 a.m. | E43: Short-Roundtable-Cortex AI Unstructured Data | H43: NA | K43: MP4; Wrike; done | L43: 0 | M43: 36 | O43: NA | P43: Unstructured Data Analytics For Enterprises | Q43: View the full roundtable discussion here: https://www.youtube.com/watch?v=gRj2_9nLFzQ | R43: NA | Z43: 1
A44: FALSE
A45: FALSE | B45: Tues | C45: 45769 | D45: 1:59 a.m. | E45: Podcast-Sanofi | H45: X | K45: MP4; FrameIO; Wrike; done | L45: 35 | M45: 34 | O45: Pharma Transformed: The AI Revolution | P45: From Data to Action: How AI Is Changing Pharma -- A Conversation With Dimitrije Jankovic of Sanofi | Q45: In this episode, Dana Gardner, Principal Analyst at Interarbor Solutions is joined by Dimitrije Jankovic, Global Head of Digital Strategy and Operations at Sanofi. They explore Sanofi’s comprehensive integration of AI to drive strategic transformation across the pharma lifecycle. Insights include the role of data modernization, the establishment of AI centers of excellence, and the innovative deployment of AI agents and virtual workforces. | R45: Link | S45: Link | AD45: 1
A46: FALSE | B46: Tues | C46: 45769 | D46: 6 a.m. | E46: Roundtable discussion--Cortex AI Data Agents | H46: X | K46: MP4; Wrike; headshot folder; text description doc; done (AB Test two options) | L46: 9 | M46: 12 | O46: Building AI Agents Is Easy | P46: Why Building Data Agents Is Hard (And How To Fix It) | Q46: Get fast, reliable answers from both structured and unstructured data, directly in tools like Slack and MS Teams. Cortex Agents, built on Snowflake Cortex AI, combines data sources, secure access, and state-of-the-art LLMs to orchestrate SQL analysis, vector search, and AI reasoning in one governed environment. Just ask a question and surface insights instantly, whether prepping a sales briefing or analyzing contracts, all without manual work or complex pipelines. Join Snowflake's Arun Agarwal, Dash Dasai, and Danmei Xu as they dive into Cortex Agents in this in-depth roundtable discussion. To learn more, click on the links below: A Practical Guide to AI Agents (Free Ebook) https://bit.ly/GuideToAIAgents Blog: Your Enterprise Needs An Agent (Cortex Agents announcement) https://bit.ly/CortexAgents Getting Started With Cortex Agents (Quickstart Guide) https://bit.ly/CortexAgentsQuickstart To view the other two videos in this GenAI roundtable series, click on these links: (ADD LINKS) | R46: Multiple options to choose from | AB46: 1
A47: FALSE | B47: Wed | C47: 45770 | D47: 6 a.m. | E47: Short-Roundtable-Cortex AI Data Agents | H47: NA | K47: MP4; Wrike; done | L47: 0 | M47: 48 | O47: NA | P47: Why Building Data Agents Is Hard (And How To Fix It) | Q47: View the full roundtable discussion here: https://www.youtube.com/watch?v=jcnJsXVWM8A | R47: NA | Z47: 1
A48: FALSE | B48: Wed | C48: 45770 | E48: Short-Podcast-Sanofi | H48: NA | K48: MP4; Wrike; done | L48: 0 | M48: 43 | O48: NA | P48: Pharma Transformed: The AI Revolution | Q48: View the full podcast interview here: https://youtu.be/Vax2l8Y63yI | R48: NA | Z48: 1
A49: FALSE | B49: Thurs | C49: 45771 | D49: 6 a.m. | E49: Roundtable Discussion-LLM Flexibilty for AI Agents | H49: X | K49: MP4; FrameIO; headshots; Wrike; done | L49: 7 | M49: 18 | O49: Multiple AI Models, One Platform | P49: Choosing The Right LLM: Why Flexibility Is Key | Q49: In this Cortex AI roundtable, Snowflake's Arun Agarwal, Yusuf Ozuysal, and James Cha-Earley highlight why AI model flexibility is crucial for real-world applications. Recognizing that no single large language model excels at everything — coding, reasoning, extraction, or conversation — Snowflake Cortex AI brings the strengths of different LLMs together by integrating leading LLMs like OpenAI, Mistral, Anthropic, and Meta into one secure platform. This unified environment simplifies integration, provides seamless model switching, and ensures consistent governance, empowering teams to build flexible, scalable, and production-ready AI agents and apps. To learn more, click on the links below: Meta Llama 4 (now available on Snowflake Cortex AI) https://bit.ly/LlamaOnCortex Anthropic Claude 3.5 models (now available on Snowflake Cortex AI) https://bit.ly/ClaudeOnCortex Getting Started with Anthropic on Snowflake Cortex (Quickstart Guide) https://bit.ly/AnthropicOnCortexQuickstart To view the other two videos in this GenAI roundtable series, click on these links: (ADD LINKS) | R49: Link | AA49: 1
A50: FALSE | B50: Fri | C50: 45772 | D50: 11 a.m. | E50: Short-Roundtable-LLM Flexibilty for AI Agents | H50: NA | K50: MP4; Wrike; done | L50: 0 | M50: 43 | O50: NA | P50: Choosing The Right LLM: Why Flexibility Is Key | Q50: View the full roundtable discussion here: https://youtu.be/ZUZsEzFptAA | R50: NA | Z50: 1
A51: FALSE
A52: FALSE | B52: Mon | C52: 45776 | D52: 8 a.m. | E52: Cannes Lions promo | H52: X | K52: MP4; Wrike; done | L52: 0 | M52: 45 | O52: Join Us At Cannes Lions | P52: Snowflake At Cannes Lions 2025 | Q52: Discover opportunities to simplify your advertising data foundation and deliver superior customer experiences through AI and applications, all within a single, unified platform. Meet the Snowflake team at Cannes Lions: www.snowflake.com/canneslions. | R52: Link
A53: FALSE | B53: Mon | C53: 45775 | D53: 2 p.m. | E53: Promo - SF and Blue Yonder at ICON | H53: NA | K53: MP4; Wrike; done (video is currenlty set to Unlisted) | L53: 2 | M53: 2 | O53: ICON 2025 | Snowflake Joins Blue Yonder In Nashville | P53: AI Data Cloud Takes Nashville | Snowflake And Blue Yonder At ICON 2025 | Q53: Excitement is building as the AI Data Cloud heads to Nashville for ICON! Join us as we explore the future of supply chain with industry leaders like Blue Yonder. Discover how Snowflake is partnering to enable seamless data sharing, collaboration, and faster actionable insights. | R53: Link | AE53: 1
A54: FALSE | B54: Tues | C54: 45776 | D54: 9 a.m. | E54: Cracking the Code-Khushboo Khatia | H54: X | K54: MP4; FrameIO; Wrike; WrikePrep; headshot folder; SRT File; done | L54: 3 | M54: 27 | O54: Interview Tips | How to Ace Your Coding Interview at Snowflake | P54: Preparing for Your Coding Interview at Snowflake | Q54: Senior Software Engineer Khushboo Bhaitia takes you behind the scenes of Snowflake’s coding interviews, breaking down what to expect and how to succeed. In this video, Khushboo shares practical strategies, gives insider tips, and walks through a mock scenario to help you feel more confident and prepared. Get ready to COAST through the interview process, as Khushboo helps crack the code to success in Snowflake’s coding interviews. Explore open jobs and learn more about careers at Snowflake: bit.ly/3QAsZcQ Follow us: Twitter: @snowflake Instagram: _snowflake_inc Facebook: snowflakedb LinkedIn: snowflake-computing | R54: Link | AB54: 1
A55: FALSE | B55: Tues | C55: 45776 | D55: 9 a.m. | E55: Cracking the Code-Paulita Paulus | H55: X | K55: MP4; FrameIO; Wrike; WrikePrep; headshot folder; SRT file done | L55: 4 | M55: 29 | O55: Interview Tips | How to Ace Your System Design Interview at Snowflake | P55: Preparing for Your System Design Interview at Snowflake | Q55: Principal Software Engineer Polita Paulus is no stranger to Snowflake’s interview process. In this video, she offers a behind-the-scenes look at how to approach our system design interviews with confidence and clarity. Drawing from her own experience, Polita shares practical strategies, insider tips, and a clear breakdown of what interviewers are really looking for. You’ll gain a better understanding of how to think through complex design challenges, communicate your ideas effectively, and showcase your technical strengths. Get ready to COAST through the interview process as Polita helps you crack the code to success in Snowflake’s system design interviews. Explore open jobs and learn more about careers at Snowflake: bit.ly/3QAsZcQ Follow us: Twitter: @snowflake Instagram: _snowflake_inc Facebook: snowflakedb LinkedIn: snowflake-computing | R55: Link | AB55: 1
A56: FALSE
A57: FALSE | C57: TOTAL TALLY FOR 1ST QUARTER OF FY2026 | Y57: =SUM('Snowflake YT Channel'!Y4:Y23) -> 0 | Z57: =SUM('Snowflake YT Channel'!Z4:Z23) -> 0 | AA57: =SUM('Snowflake YT Channel'!AA4:AA23) -> 0 | AB57: =SUM('Snowflake YT Channel'!AB4:AB23) -> 0 | AC57: =SUM('Snowflake YT Channel'!AC4:AC23) -> 0 | AD57: =SUM('Snowflake YT Channel'!AD4:AD23) -> 0 | AE57: =SUM('Snowflake YT Channel'!AE4:AE23) -> 1 | AF57: =SUM('Snowflake YT Channel'!AF4:AF23) -> 0 | AG57: =SUM('Snowflake YT Channel'!AG3:AG23) -> 0 | AH57: =SUM('Snowflake YT Channel'!AH4:AH23) -> 0 | AI57: =SUM('Snowflake YT Channel'!AI3:AI23) -> 0 | AJ57: 0 | AK57: 0 | AL57: 0 | AM57: 0
A58: FALSE
A59: FALSE | B59: Tues | C59: 45783 | D59: 6 a.m. | E59: Customer - Carma | H59: X | K59: MP4; Wrike; done | L59: 1 | M59: 26 | O59: Building A New Business On Snowflake | P59: Carma's Investment In Snowflake Generates A Positive Return On Investment | Q59: When CTO Florian Pasquier joined Carma, a startup Australian company whose mission is to be a one-stop destination for buying and selling cars, he knew from previous experience that the company needed to build its business upon the Snowflake platform. Tune in to hear him discuss the ROI that the platform delivers and the potential benefits that he expects to realize from the use of artificial intelligence via Cortex AI. | R59: Link | Y59: 1
A60: FALSE | B60: Tues | C60: 45783 | D60: 4 p.m. | E60: Podcast--Accenture | H60: X | K60: MPR; Wrike; done | L60: 29 | M60: 44 | O60: Fueling Enterprise Success With AI | P60: The AI-Driven Enterprise Advantage | Teresa Tung, Global Data Capabilities Lead at Accenture | Q60: In this episode, Dana Gardner, Principal Analyst at Interarbor Solutions is joined by Teresa Tung, Global Data Capabilities Lead at Accenture. They discuss how enterprises can accelerate and broaden the application of data to attain more business value through agentic AI, the pivotal role of proprietary data as a competitive advantage, and the need for data practitioners to adapt to new responsibilities involving data quality and AI agent interaction. | R60: Link | AD60: 1
A61: FALSE | B61: Wed | C61: 45784 | D61: 6 a.m. | E61: Customer- Airtasker | H61: X | K61: MP4; Wrike; done | L61: 1 | M61: 23 | O61: Embarking on an AI Journey | P61: Airtasker Explores AI With A Secure Data Foundation | Q61: Airtasker is a community platform that connects people who need to outsource tasks with people who are looking to earn money and are ready to work. A long-time Snowflake user, Airtasker relies on Snowflake as its core data platform. Now it is beginnning its journey into artificial intelligence using Cortex AI. In this video, Calvin NG, VP of Data for this Australian-based company, shares his thoughts on the potential benefits of the technology. | R61: Link | Y61: 1
A62: FALSE | B62: Thurs | C62: 45785 | D62: 10 a.m. | E62: May Snow Report | H62: X | K62: MP4; WrikePrep; WrikeThumb; done | L62: 3 | M62: 35 | O62: Snow Report May | P62: Snow Report: What's Happening At Snowflake In May | Q62: Learn about recent additions to the Snowflake Horizons catalog as well as new resources for updating your data skills in this month's edition of the Snow Report. You'll also find information on Summit 2025, Snowflake's premiere annual conference, as well as links to podcasts, news announcements, and more. | R62: Link | S62: LINK | T62: Under 200MB version | AC62: 1
A63: FALSE
A64: FALSE | B64: Wed | C64: 45791 | D64: 6 a.m. | E64: Promo -- Road to Summit-One Word | H64: X | K64: MP4 with Broll; MP4 no Broll; Wrike; WrikPrep; WrikeThumb; Social copy; folder with vidoes and thumbs; done | L64: 0 | M64: 43 | O64: Snowflake Summit 25 | P64: Snowflake Summit 2025: Data, AI & Impact | Q64: Snowflake Summit 2025 is just around the corner! Visionary leaders, innovators and data professionals will come together to unlock the future of AI and apps. Join us June 2–5 in San Francisco to explore how the world’s most forward-thinking organizations are building what’s next—in the AI Data Cloud. | R64: Link | T64: Social Cut 9x16 | AE64: 1
A65: FALSE
A66: FALSE | B66: Tues | C66: 45797 | D66: 1:59 a.m. | E66: Podcast-Disney Advertising | H66: X | K66: Podcast Tracker; MP4; done | L66: 31 | M66: 32 | O66: Disney's Magic: AI Powers Storytelling | P66: Unlocking Disney's Magic: AI and Automation in Multimedia Storytelling | Q66: In this episode, Dana Gardner, Principal Analyst at Interarbor Solutions is joined by Nick Winfrey, Vice President of Data Science and Data Strategy at The Walt Disney Company. They explore Disney's extensive use of AI, automation, and data science to optimize advertising and enhance fan experiences. The conversation also delves into the importance of diversity in data teams, the crucial role of AI and ML in media and entertainment, and how Disney leverages audience behavior and loyalty across different platforms. | R66: Link | AD66: 1
A67: FALSE | B67: Wed | C67: 45797 | D67: 8 a.m. | E67: Promo-Road to Summit with Ryan Green | H67: X | K67: MP4; Wrike; WrikeThumb; Social copy; done | L67: 0 | M67: 55 | O67: The Road to Summit 25 | P67: Unlock The Future Of AI And Apps At Snowflake Summit 2025 | Q67: "Data Cloud Now" anchor Ryan Green invites you to join him at Snowflake Summit 2025, June 2-5 in San Francisco. This is Snowflake's biggest event of the year, and it's where visionary leaders, innovators and data professionals come together to unlock the future of AI and apps. Come level up your skills by participating in the more than 500 workshops and conference sessions. Come explore how the world’s most forward-thinking organizations are building what’s next — in the AI Data Cloud. | R67: Link | AE67: 1
A68: FALSE
A69: FALSE | B69: Tues | C69: 45804 | D69: 8 a.m. | E69: Podcast-S&P Global | H69: X | K69: Podcast Tracker; MP4; | L69: 33 | M69: 42 | O69: Decoding Finance Through AI Insights | P69: AI and the Future of Finance: Decoding Earnings Calls | Q69: In this episode, Dana Gardner, Principal Analyst at Interarbor Solutions is joined by Liam Hynes, Global Head of New Product Development at S&P Global Market Intelligence. They discuss how S&P Global Market Intelligence utilizes AI to analyze corporate earnings calls to guide and improve financial reporting. These insights help businesses enhance communication, refine executive performance, and predict market outcomes. The conversation also highlights the use of Snowflake Cortex AI platform and the importance of data-driven decision-making in the financial sector. | R69: Link | AD69: 1
A70: FALSE
A71: FALSE | B71: Mon | C71: 45810 | E71: Short - Summit Promo | P71: Get ready to experience the future at #SnowflakeSummit 2025! | X71: 1 | Z71: 1
A72: FALSE | B72: Tues | C72: 45811 | D72: 9 a.m. | E72: Summit 25 | Platform Keynote Demo 1 - OpenFlow and dbt | H72: X | K72: MP4; Wrike; Keynote Demo Tracker; done | L72: 7 | M72: 36 | O72: ETL And Deploying Data Pipelines | P72: Snowflake For Data Engineering: Snowflake Openflow And dbt Projects | Q72: Join Snowflake's Amanda Kelly, Director of Product, to learn how data engineers can use Snowflake Openflow and dbt Projects to: - Connect to any data source and any target with the flexibility to customize and extend - Deploy and execute pipelines inside a VPC or via Snowpark Container Services, with both control and simplicity - Bridge the gap from pipeline building to deployment, natively in Snowflake - Tackle AI-ready data using unstructured data connector, with AI-enabled parsing and chunking built into the ETL pipelines Find More Resources: Snowflake for data engineering: https://www.snowflake.com/en/product/data-engineering/ Snowflake Openflow: https://www.snowflake.com/en/product/features/openflow/ dbt Projects: https://www.youtube.com/watch?v=w7C7OkmYPFs | R72: Link | X72: 1
A73: FALSE | B73: Tues | C73: 45811 | D73: 9 a.m. | E73: Summit 25 | Platform Keynote Demo 2 - Cortex AISQL | H73: X | K73: MP4; Wrike; done | L73: 6 | M73: 14 | O73: Multi-Modal Analytics for AI/BI | P73: Leveraging Cortex AISQL For Multi-Modal Analytics | Q73: Snowflake's Senior Product Manager Renee Huang demonstrates how to leverage Snowflake's powerful Cortex AISQL functions for advanced analytics on unstructured and structured data. Her demonstration includes a look at how to use functions like AI_AGG, AI_CLASSIFY, AI_COMPLETE, and AI_FILTER on your data to accelerate insights. | R73: Link | X73: 1
A74: FALSE | B74: Tues | C74: 45811 | D74: 9 a.m. | E74: Summit 25 | Platform Keynote Demo 3 - Snowflake Intelligence | H74: X | K74: MP4; Wrike; WrikeThumb; done | L74: 8 | M74: 41 | O74: Talk To Enterprise Data Instantly | P74: Talk To Your Data: Snowflake Intelligence Demo | Q74: Unlock instant insights from ALL your data using agentic AI. In this demo, Snowflake's Director of Product Management Jeff Hollan shows how Snowflake Intelligence lets anyone in your enterprise use natural language to talk to data – structured, unstructured, and external. See how agents help you understand what happened and why, and even enable you to take action. Transform your data experience with Snowflake Intelligence. Easy, Connected, Trusted. To learn more, click here: https://www.google.com/url?q=https://www.snowflake.com/en/blog/snowflake-intelligence-talk-to-data/&sa=D&source=editors&ust=1748610503492852&usg=AOvVaw2Be59sotySFKTYAAU5b0pL | R74: Link | X74: 1
A75: FALSE | B75: Tues | C75: 45811 | D75: 9:30 p.m. | E75: Summit - Day 1 Highlights | H75: X | K75: done | L75: 1 | M75: 32 | O75: Day 1 | P75: Summit 2025 | Day 1 Hightlights | Q75: Wow, what a Day 1 at Snowflake Summit 2025! This recap video brings you all the major highlights, from product announcements to a keynote conversation between Snowflake CEO Sridhar Ramaswamy and OpenAI CEO Sam Altman, moderated by Sarah Guo, founder and managing partner of Conviction. Adding to the day's robust lineup of visionary leaders, we also heard from Lynn Martin, President of the NYSE, who joined Sridhar Ramaswamy in a compelling keynote conversation. Finally, there was the announcement that Snowflake has been named the official data collaboration partner of the Los Angeles U.S. Olympic Games. We can't wait to see what Day 2 brings! | X75: 1
A76: FALSE | B76: Wed | C76: 45812 | D76: 5 p.m. | E76: Summit - Opening Keynote | H76: X | K76: done | L76: 57 | M76: 41 | O76: just the logo | P76: Snowflake Summit 2025 Opening Keynote With Sridhar Ramaswamy, Sam Altman, And Sarah Guo | Q76: Snowflake Summit got off to an incredible start with an opening keynote featuring a conversation between Snowflake CEO Sridhar Ramaswamy and OpenAI CEO Sam Altman. The conversation was moderated by Sarah Guo, founder and managing partner of Conviction. Lynn Martin, President of the NYSE, also joined Sridhar Ramaswamy for a compelling keynote conversation, and members of the Snowflake team shared exciting new product announcements. Rounding out the event was the news that Snowflake has been named the official data collaboration partner of the Los Angeles U.S. Olympic Games. Tune in here: https://www.snowflake.com/en/summit/?utm_campaign=linkedin&utm_content=1748932432&utm_medium=&utm_source=Snowflake | X76: 1
A77: FALSE | B77: Wed | C77: 45812 | D77: 7 p.m. | E77: Summit - Platform Keynote | H77: X | K77: done | L77: 101 | M77: 17 | O77: Platform Keynote | P77: Snowflake Summit 2025 Platform Keynote | Q77: The Snowflake Summit 2025 Platform Keynote, led by Snowflake Co-Founder and President of Product Benoit Dageville and EVP of Product Christian Kleinerman, focused on how Snowflake's AI Data Cloud simplifies and accelerates data utilization, enabling businesses to leverage AI at scale. Key announcements included: -Future-Proof Data Architecture -Comprehensive Data Governance -Seamless Data Integration -Delivering More Business Impact -Faster Insights -AI-Ready Data -Accelerating Business Growth with AI Agents | X77: 1
A78: FALSE | B78: Wed | C78: 45812 | D78: 11 p.m. | E78: Summit - Day 2 Highlights | H78: X | K78: done | L78: 1 | M78: 53 | O78: Day 2 | P78: Summit 2025 | Day 2 Hightlights | Q78: Day 2 of #SnowflakeSummit flew by, but not before attendees were treated to a mountain of announcements during the Platform Keynote! Among the key Snowflake announcements were the introduction of Adaptive Compute, Snowflake Openflow, Cortex AISQL, Semantic Model Sharing, Snowflake Intelligence, and much more. Catch up on all the news by going to https://www.snowflake.com/en/blog/announcements-snowflake-summit-2025/ | X78: 1
A79: FALSE | B79: Thurs | C79: 45813 | D79: 10 p.m. | E79: Summit - Day 3 Highlights | H79: X | L79: 2 | M79: 33 | O79: Day 3 | P79: Summit 2025 | Day 3 Highlights | Q79: Maximizing the use of AI and agentic tools was the hot topic during Day 3 of Snowflake Summit 2025, where a record number of people sought to grow their skills and knowledge by attending the Builder Keynote sessions and Dev Day Luminary talks as well as by participating in a multitude of breakout sessions and hands-on labs. The day also saw Lumilinks take top honors in this year's Startup Challenge, and it saw Snowflake announce its plans to open a Silicon Valley AI Hub in the fall. | X79: 1
A80: FALSE | B80: Fri | C80: 45814 | E80: Short - Summit 2025 Day 3 Highlights | P80: Snowflake Summit 2025 Day 3 Highlights | X80: 1 | Z80: 1
A81: FALSE
A82: FALSE | B82: Mon | C82: 45817 | D82: 11:30 a.m. | E82: BUILT[By] - Snowflake Intelligence | H82: X | K82: MP4; Wrike; WrikePrep; WrikeThumb; done | L82: 4 | M82: 15 | O82: Get Insights By Talking To Your Data | P82: Snowflake Intelligence | Built[By] Reza Akhavan | Q82: Software Engineering Manager Reza Akhavan is leading the charge on the future of data agents for enterprise AI. In this Built[By] spotlight, Reza shares how his team is transforming how businesses interact with their data, eliminating silos, and enabling teams to generate insights using natural language. Gain insights into the challenges faced during the development of Snowflake Intelligence, the journey from concept to first-party solution, and how this groundbreaking solution is democratizing data access for organizations worldwide. Ready to harness the power of generative AI? Join engineers like Reza on the journey to building what’s next in data intelligence at Snowflake. For more information about careers at Snowflake, click here: -- https://bit.ly/4lCXzRU . Let’s build the next big thing together. #SoftwareEngineering #Hiring | R82: Link | AG82: 1
A83: FALSE | B83: Wed | C83: 45819 | D83: 6 a.m. | E83: Customer-VodafoneZiggo Cuts Costs | H83: X | K83: MP4; Wrike; WrikePrep; WrikeThumb; done | L83: 1 | M83: 53 | O83: New Data Platform Delivers Big Benefits | P83: VodafoneZiggo Cuts Costs And Gains Real-Time Insights With Move To New Data Platform | Q83: When VodafoneZiggo, one of the largest telcos in The Netherlands, ran into a problem with its legacy data platform being unable to handle workloads in a timely manner, it made the decision to adopt an integrated AWS and Snowflake solution.The result has been a 50% drop in costs and a 96% improvement in data processing time. It's a change that has resulted in the ability to generate real-time insights and deliver a superior customer experience. | R83: Link | X83: 1
A84: FALSE | B84: Wed | C84: 45819 | D84: 7 a.m. | E84: Snowflake Summit 2025 Conference Highlights | H84: X | K84: MP4; Wrike; | L84: 2 | M84: 1 | O84: Snowflake Summit 2025 | P84: Snowflake Summit 2025 Conference Highlights | Q84: Relive some of the most exciting moments at Snowflake Summit 2025 in this fast-paced, high-energy conference highlights video. This record-breaking event attracted more than 20,000 attendees and featured more than 500 sessions and 150 product announcements. The biggest names in data and AI were on hand and on stage, and the excitement over the rapid pace of technological advances was contagious. If you missed it, don't despair. All the keynote presentations are already posted to here on this YouTube channel, and the Luminary Talks and breakout sessions will be posted will be posted to the Snowflake Developers YouTube channel over the course of the coming weeks. To access that channel, click here: https://www.youtube.com/@snowflakedevelopers | R84: Link | X84: 1
A85: FALSE | B85: Wed | C85: 45819 | D85: 2 p.m. | E85: Summit - Startup Challenge Finale | K85: MP4; Wrike; thumb done | L85: 60 | M85: 48 | O85: The Startup Challenge | P85: Snowflake Startup Challenge 2025 Finale at Dev Day | And The Winner Is .... | Q85: Tune in to watch what happened when the three finalists in this year's Snowflake Startup Challenge came together on the last day of Snowflake Summit to participate in the final round of competition. Their task was to pitch their "Powered By Snowflake" product to a panel of four judges charged with selecting the winner. It all took place before a live audience, and the prize at stake was a chance to win up to $1 million in funding from Snowflake Ventures and gain significant market exposure. The three finalists stepping up to the challenge were DeepTempo, which pitched a cybersecurity product that utilizes deep learning; LumiLinks, which showcased its centralized AI-driven applications for extracting cost-saving insights from diverse data sets; and Winning Variant, which presented a new type of split-testing platform. And the winner was....spoiler alert ... Lumilinks! Watch the video to find out why. | R85: Link | X85: 1
A86: FALSE | B86: Wed | C86: 45819 | E86: Short - Summit Dev Day 2025 Highlights | P86: Snowflake Dev Day 2025 Highlights | X86: 1 | Z86: 1
A87: FALSE | B87: Fri | C87: 45821 | E87: Short - Summit Announcements | P87: Snowflake Summit Announcements | X87: 1 | Z87: 1
A88: FALSE | B88: Sat | C88: 45822 | E88: Short - Summit - AI On Snowflake | P88: AI On Snowflake | X88: 1 | Z88: 1
A89: FALSE | B89: Sun | C89: 45823 | E89: Short - Summit -Snowflake AI Data Cloud Updates | P89: Snowflake AI Data Cloud Updates | X89: 1 | Z89: 1
A90: FALSE
A91: FALSE | B91: Mon | C91: 45824 | E91: Short -Summit - Building Snowflake Intelligence | P91: Building Snowflake Intelligence | X91: 1 | Z91: 1
A92: FALSE | B92: Mon | C92: 45824 | D92: 10 a.m. | E92: June Snow Report | H92: X | K92: MP4 ;WrikePrep; WrikeThumb; done | L92: 2 | M92: 43 | O92: Snow Report June | P92: Snow Report: What's Happening At Snowflake In June | Q92: This edition of The Snow Report recaps some of the key announcements made at Summit 2025, including Snowflake Intelligence, Cortex AISQL, the Data Science Agent, and Adaptive Compute and Adaptive Warehouses. You'll also find user stories, tech tips, and information on upcoming events. To access the newsletter, click here: https://info.snowflake.com/index.php/email/emailWebview?mkt_tok=MjUyLVJGTy0yMjcAAAGbBVRXadLm8ij8HOPmb1JMQ-SSJ9AKhaVYuaLL898yOJtK8yxW2uPJgQrrCgooXDLflZwyVR7d_gFnoK2gKYG70fLEAs4&email=MjUyLVJGTy0yMjcAAAGbCVD6F4lDzyeKMCvD3wBKCSY31LLn6uVYCLSCPLRHXc0DoKIiaUfXaWYT_aPkBLTqXSH5eOIAPydFkfUdTVHhxcCVPIW0w6Kjlfc | R92: Link | AC92: 1
A93: FALSE | B93: Tues | C93: 45825 | D93: 1:59 a.m. | E93: Podcast--Capital One | H93: X | K93: Podcast Tracker; MP4; WrikePrep; done | L93: 26 | M93: 38 | O93: AI For Better Banking Journeys | P93: Beyond Banking: The Journey Into AI-Powered Customer Experiences | Q93: In this episode of the "Data Cloud Podcast," Dana Gardner, Principal Analyst at Interarbor Solutions, sits down with Ameesh Paleja, Executive Vice President of Enterprise Platform Technology at Capital One. They explore how Capital One leverages modern data architecture, automation, and AI to improve customer interactions and experiences. The conversation delves into the importance of standardized data, the role of AI-driven personalized services, and the integration of marketing and AI strategies. | R93: Link | AD93: 1
A94: FALSE
A95: FALSE | B95: Tues | C95: 45832 | D95: 8:30 a.m. | E95: International - AIネイティブなエンジニアを目指す！Snowflake Discover | H95: X | K95: MP4; WrikePrep; done | L95: 0 | M95: 31 | P95: AIネイティブなエンジニアを目指す！Snowflake Discover | Q95: AIデータ・クラウドの可能性を探求し、深く理解するためのエンジニア向け無料ライブ・ウェビナーです。本ウェビナーでは、データ、AI/ML、アプリケーションの最新トレンドやベストプラクティスを、Snowflakeの技術エキスパートが日本のお客様向けにお届けします。 「SUMMIT25」のアップデート総まとめが聞けるDay 1と、Snowflakeの技術を実際に体験しながら学べるバーチャル・ハンズオンのDay 2。 データとAIの最前線を体験し、実践スキルを一気にレベルアップしましょう。 詳しくはこちら：https://www.snowflake.com/about/webinars/snowflake-discover-ja/?utm_source=ytube | R95: Link | AF95: 1
A96: FALSE | B96: Fri | C96: 45835 | D96: 6 a.m. | E96: International - Snowflake World Tour Promo | H96: X | K96: MP4; WrikeEdit; WrikePrep; done (KEEP UNLISTED) (For international channel) | L96: 0 | M96: 30 | O96: Snowflake World Tour | P96: Snowflake Word Tour 2025 Is Coming | Q96: Get ready! Snowflake World Tour 2025 is coming to a city near you! | T96: Short; | AF96: 1
A97: FALSE | B97: Fri | C97: 45835 | D97: 9 a.m. | E97: AstraZeneca Customer Spotlight Video | H97: X | K97: MP4; WrikeEdit; WrikeThumb; done | L97: 1 | M97: 57 | O97: Using AI To Drive Medical Advances | P97: AI-Driven Data Cuts Time, Boosts Innovation, And Saves Lives at AstraZeneca | Q97: A look at how AstraZeneca, a global biopharmaceutical company focused on the discovery, development, and commercialization of innovative medicine, leveraged Snowflake to accelerate data product creation, drive $10M+ in productivity savings, and enable AI-driven innovations that improve early disease detection and patient outcomes. | R97: Link | Y97: 1
A98: FALSE
A99: FALSE | B99: Tues | C99: 45839 | D99: 1:59 a.m. | E99: Podcast--Ericsson | H99: X | K99: MP4; WrikePrep; WrikePost; Podcast Tracker; done | L99: 33 | M99: 55 | O99: Smarter Telecom With Unified AI | P99: Unified Data and AI: Elevating Telecom Customer Experiences | Q99: In this episode, Dana Gardner, Principal Analyst at Interarbor Solutions, is joined by Soren Marklund, Vice President of Global Services, Technology Consulting, and AI Data Strategy at Ericsson. They explore how Ericsson leverages modern data architectures to enhance customer interactions and drive business benefits. The discussion covers the importance of a unified data operating model, challenges faced with data silos, and the role of AI and machine learning in improving customer service. | R99: Link | AD99: 1
A100: FALSE | B100: Tues | C100: 45839 | D100: 6 a.m. | E100: Built[By] - Danmei - Cortex Agents | H100: X | K100: MP4; WrikePrep1; WrikeEdit; WrikePrep2; WrikeThumb; Project Folder; done | L100: 5 | M100: 5 | O100: The Evolution From Chatbot Demo To Cortex Agents OR Access, Accuracy, and Agentic Answers | P100: Cortex Agents | Built[By] Danmei Xu | Q100: Cortex Agents are changing how Snowflake customers access insights across structured and unstructured data—but they didn’t build themselves. In this Built[By] spotlight, Senior Software Engineer Danmei Xu shares how her team brought Cortex Agents to life by combining powerful LLMs, retrieval systems, and thoughtful orchestration. From early product planning to complex query quality, Danmei helped engineer systems that make enterprise data conversational and accessible. Learn how Cortex Agents use tools like Cortex Search and Cortex Analyst to turn disconnected data into accurate, AI-powered answers. Let’s build the next big thing together: https://bit.ly/4kb3POW #Software Engineering #Hiring | R100: Link1; Link2 | T100: Short1; Short2 | AG100: 1
A101: FALSE | B101: Tues | C101: 45839 | D101: 11 a.m. | E101: Built[By] - Danmei Teaser - Cortex Agents | H101: NA | K101: MP4; WrikeEdit; | L101: 0 | M101: 28 | O101: NA | P101: Cortex Agents | Built[By] Danmei Xu | Q101: Find the full profile of Danmei Xu's work on Cortex Agents here: https://youtu.be/x4YXsGz8hvM | R101: NA | AG101: 1
A102: FALSE | B102: Wed | C102: 45840 | D102: 8 a.m. | E102: Built[By] - Danmei Short - Cortex Agents | H102: NA | K102: MP4; WrikeEdit; done | L102: 0 | M102: 28 | O102: NA | P102: Rapid Fire with Danmei Xu | Q102: Find the full profile of Danmei Xu's work on Cortex Agents here: https://youtu.be/x4YXsGz8hvM | R102: NA | AG102: 1
A103: FALSE | B103: Wed | C103: 45840 | D103: 8 a.m. | E103: International - Snowflake World Tour Korea | H103: X | K103: MP4; WrikePrep; (LEAVE IT UNLISTED) | L103: 0 | M103: 30 | O103: Snowflake World Tour Korea | P103: Snowflake World Tour 2025 - Korea | Q103: Get ready for the Snowflake World Tour! | T103: Link | AF103: 1
A104: FALSE
...

Sheet 2025 Archive Devs YT
A1: Scheduled / Published | B1: YouTube Publishing Date | D1: Time of Publishing (PST) | E1: Wrike Request Name | F1: Social Request Submitted? | G1: Producer | H1: Playlist Designated? | I1: MP4 | J1: THUMB | K1: NOTES | L1: LENGTH OF VIDEO | N1: YT Link | O1: Thumbnail Title | P1: YouTube Title | Q1: YouTube Description | R1: Link to Thumbnail | S1: Link to Video Transcript | T1: Link to Social Cut MP4 | U1: Link to Social Cut on LI | V1: Link to Social Cut on X | X1: Summit (The shorts in this tally are duplicated in the Shorts column) | Y1: Demos | Z1: Shorts | AA1: Professional Services | AB1: Behind the Cape | AC1: Solutions Center (also marked as Demo) | AD1: User Groups | AE1: Individual Videos | AF1: Events | AG1: BUILD/Builder Bytes | AH1: Customer | AI1: AI Builders | AJ1: Podcast
B2: Day | C2: Date | L2: Minutes | M2: Seconds
A3: FALSE | B3: Thurs | C3: 45694 | D3: 5:30 a.m. | E3: SC-Build Deep Learning Models with Distributed PyTorch | H3: X | K3: MP4; Wrike; done | L3: 26 | M3: 31 | O3: Using Snowflake ML To Build Computer Vision Models | P3: Build Deep Learning Models With Distributed PyTorch On GPUs From Snowflake Notebooks | Q3: Tune into this demo with ML expert Vinay Sridhar to learn how to build and deploy scalable computer vision models from Snowflake Notebooks. Distributed training has become crucial for handling increasingly complex deep learning models and massive data sets. With Snowflake Notebooks on Container Runtime, developers can leverage multiple GPUs to accelerate PyTorch development by sharding, distributing, and training on Snowflake data in parallel. Models can then be easily productionized in Snowflake through seamless integration to model serving with GPUs and observability. In this session, we show you how easy it is to work with any open source package, configure resources, and build scalable end-to-end workflows. | R3: Link | Y3: 1 | AC3: 1
A4: FALSE | B4: Fri | C4: 45695 | D4: 6 a.m. | E4: Gen AI Day: Embeddings Demo | H4: X | K4: MP4; Wrike; done | L4: 6 | M4: 15 | O4: Converting Data Into Vector Representations | P4: Scale Embeddings With GPUs From Snowflake Notebooks On Container Runtime | Q4: Embeddings are the first part of several powerful AI/ML applications. They help convert data (text, images, documents, etc) into vector representations for use in recommendation engines, search, chatbots, ad campaigns, and multi-modal applications. Watch this demo with Caleb Baechtold, Principal AI Architect at Snowflake, to learn how to scale custom embeddings with GPUs in Snowflake Notebooks on Container Runtime. Follow along in this Quickstart Guide: -- https://quickstarts.snowflake.com/guide/scale-embeddings-with-snowflake-notebooks-on-container-runtime/ Learn more about Snowflake ML here: https://www.snowflake.com/en/data-cloud/snowflake-ml/ | R4: Link | Y4: 1
A5: FALSE
A6: FALSE | B6: Wed | C6: 45700 | D6: 6 a.m. | E6: Getting Started with Cortex Agents Dev YT | H6: X | K6: MP4, Wrike, thumb done (Internally by Ai-vy) | L6: 4 | M6: 26 | O6: Snowflake Cortex Agents | P6: Getting Started with Cortex Agents | Q6: 🚀 Unlock the Power of Your Enterprise Data with Snowflake Cortex Agents! 🔍 Discover how Snowflake is revolutionizing data insights with Cortex Agents, a game-changing solution that transforms how businesses access and understand their structured and unstructured data. In this demo, we dive into a real-world insurance claims scenario to showcase: - Instant data retrieval across complex document collections - Semantic understanding of data with Cortex Analyst - Powerful search capabilities using Cortex Search Service - Effortless insights generation in seconds Key Highlights: - Process both structured and unstructured data seamlessly - Get accurate, contextualized answers to complex queries - Access insights from PDFs, contracts, and other documents - Simplify information retrieval with AI-powered tools Perfect for data professionals, business analysts, and decision-makers looking to unlock the full potential of their enterprise data. Get started with Cortex Agents with this Quickstart! https://quickstarts.snowflake.com/guide/getting_started_with_cortex_agents/index.html?index=..%2F..index#0 | Y6: 1
A7: FALSE | B7: Fri | C7: 45702 | D7: 6 a.m. | E7: Apache Iceberg 1.8 Release Video | H7: X | K7: MP4; Wrike-Edit; Wrike-Prep;done | L7: 7 | M7: 53 | O7: What's New in Apache Iceberg 1.8 | P7: An Overview Of Core Changes And New Features in Apache Iceberg 1.8 | Q7: Apache Iceberg™ 1.8 is here! Follow along as Danica Fine (Lead Developer Advocate OSS, Snowflake), shares highlights of the latest Apache Iceberg version. The release is split up into Core Changes and New Features, Spec Work (including v3 work), and Deprecations and Removals. 0:00 - Intro 0:33 - rewriteDataFiles Delete File Ratio 1:00 - Loosen ParallelIterable Memory Usage 1:46 - Change Default Delete File Granularity 2:28 - rewriteTablePath Spark Action 2:53 - Spark computeTableStats Procedure 3:23 - Clean Up Unused Specs When Expiring Snapshots 3:46 - Write to Multiple Spec During “Fast Append” 4:34 - Ignore Type-Narrowing When Merging Schemas 5:09 - Default Values 6:01 - Delete Vectors 6:55 - Remove Hive Runtime Module 7:09 - Deprecate snapshot-id of setStatisticsUpdate 7:22 - Close Have a watch to learn more about the Apache Iceberg 1.8 release! RESOURCES ► Peruse the release notes for Apache Iceberg 1.8: https://iceberg.apache.org/releases/#180-release ► Check out the Apache Iceberg 1.8 docs: https://iceberg.apache.org/docs/1.8.0/ ► Download and try out Apache Iceberg: https://iceberg.apache.org/releases/#downloads #iceberg #apacheiceberg | R7: Link | S7: Link | Y7: 1
A8: FALSE
A9: FALSE | B9: Wed | C9: 45707 | D9: 6 a.m. | E9: Data Analysis with DeepSeek | H9: X | K9: MP4; Wrike; done | L9: 11 | M9: 58 | O9: Doing Data Analysis With A LLM | P9: Conducting Data Analysis With The DeepSeek-R1 LLM In Snowflake Notebooks | Q9: Chanin Nantasenamat, PhD, demonstrates how to implement a Snowflake Notebook that can answer questions about data via the use of a LLM reasoning model, namely the DeepSeek-R1. Code: -- https://github.com/Snowflake-Labs/snowflake-demo-notebooks/tree/main/Data_Analysis_with_LLM DeepSeek-R1 via Snowflake Cortex: -- https://www.snowflake.com/en/blog/deepseek-preview-snowflake-cortex-ai/ | R9: Link | Y9: 1
A10: FALSE | B10: Thur | C10: 45708 | D10: 6 a.m. | E10: SC-Detection of functional equivalence issues | H10: X | K10: MP4; Wrike; done | L10: 14 | M10: 52 | O10: Getting Started with Snowpark Checkpoints | P10: Snowpark Checkpoints: Detection Of Functional Equivalence Issues When Migrating From PySpark To Snowpark | Q10: David Martínez, Software Developer at Snowflake, demonstrates how to detect functional equivalence differences when migrating from PySpark to Snowpark using the Snowpark Checkpoints Framework with the Visual Studio Code extension for Snowflake. The Snowpark Checkpoints Framework is a powerful tool for comparing the schema and data consistency between PySpark and Snowpark to preserve the exact behavior of data frames due to operations made over them. Learn more about this powerful tool in this documentation: http://docs.snowflake.com/en/developer-guide/snowpark/python/snowpark-checkpoints-library | R10: Link | Y10: 1 | AC10: 1
A11: FALSE | B11: Thur | C11: 45708 | D11: 9 a.m. | E11: SC-Dynamic Route Optimization in Snowflake | H11: X | K11: MP4; FrameIO; Wrike; done | L11: 17 | M11: 16 | O11: Dynamic Route Optimization | P11: Leveraging Geospatial Data For Dynamic Route Optimization In Snowflake | Q11: Becky O'Connor, a Solution Innovation Architect at Snowflake, demonstrates how to leverage geospatial analytics, Snowflake Cortex, and the freely available route optimization service to build a dynamic route simulator app that lets you simulate deliveries to real places across any industry, anywhere in the world. Imagine trying to understand how you would deliver to locations from a new depot location. This application uses the CARTO Overture points of interest -- freely available in the Snowflake Marketplace -- to understand what potential deliveries might look like. It also lets you try out the optimization services prior to implementing the solution on real use cases. | R11: Link | Y11: 1 | AC11: 1
A12: FALSE | B12: Fri | C12: 45709 | D12: 6 a.m. | E12: Behind The Cape - Snowflake Certifications | H12: X | K12: MP4; Wrike; done | L12: 29 | M12: 24 | O12: Acquiring Snowflake Certifications | P12: Behind The Cape: Panel Discussion About Acquiring Snowflake Certifications | Q12: In this episode of "Behind the Cape," host Keith Belanger chats with a panel of Data Superheroes about Snowflake certifications. Augusto Rosa, Jyoti Pathak, Chris Hastie, and Frederic share their perspectives on earning Snowflake certifications. They also discuss how exam questions are structured, effective training and preparation strategies, and their thoughts on achieving one or multiple certifications. Snowflake certification info can be found here: https://www.snowflake.com/en/resources/learn/certifications/ Study Notes for the Snowflake SnowPro Core Certification Exam can be found here: https://github.com/Infostrux-Solutions/snowflake-snowpro-core-study-notes | R12: Link | AB12: 1
A13: FALSE
A14: FALSE | B14: Wed | C14: 45714 | E14: Short-Which Office Is The Best? | P14: Short-Which Office Is The Best? | Z14: 1
A15: FALSE | B15: Thurs | C15: 45715 | D15: 8 a.m. | E15: How to build a DeepSeek-R1 chatbot | H15: X | K15: MP4; Wrike; done | L15: 11 | M15: 22 | O15: How To Build A DeepSeek-R1 Chatbot | P15: How To Build A DeepSeek-R1 Chatbot In Python | Q15: Chanin Nantasenamat, PhD, demonstrates how to build a DeepSeek-R1 chatbot in Python. Briefly, Streamlit is used for the frontend, while on the backend the LLM model that is powering the app’s response is made possible through API calls to the DeepSeek-R1 model hosted in Snowflake. Code: https://github.com/Snowflake-Labs/snowflake-demo-streamlit/tree/main/DeepSeek-R1%20chatbot DeepSeek-R1 via Snowflake Cortex: https://www.snowflake.com/en/blog/deepseek-preview-snowflake-cortex-ai/ | R15: Link | Y15: 1
A16: FALSE | B16: Fri | C16: 45716 | D16: 7:30 a.m. | E16: Query Iceberg tables in Glue | H16: X | K16: MP4; FrameIO; Wrike; thumb requested from Superside | L16: 5 | M16: 10 | O16: Using Iceberg Tables Wtih AWS Glue | P16: Connecting To AWS Glue And Querying Iceberg Tables Using Credentials Vended By Lake Formation | Q16: This video demonstrates how to connect Snowflake to AWS Glue and query Iceberg Tables defined in AWS Glue via the Iceberg REST API. You will also learn how to configure AWS Glue and Lake Formation so that Snowflake uses the credentials vended by Lake Formation to run the queries. This is a private preview feature. | R16: Link | Y16: 1
A17: FALSE | B17: Fri | C17: 45716 | D17: 10 a.m. | E17: Deloitte Smart Factory Demo | H17: NA | K17: MP4; Wrike; done (this video will remain Unlisted) | L17: 0 | M17: 33 | O17: AI Co-Pilot Optimizes Production Processes | P17: Empowering Operations: Deloitte’s Smart Factory Solution For Resolving Manufacturing Production Anomalies | Q17: Discover Deloitte’s Smart Factory solution, designed to help organizations detect and address production anomalies. This innovative co-pilot provides customers with an intuitive, guided research experience, leveraging historical incident data to pinpoint and resolve operational challenges swiftly and effectively. By combining advanced analytics with actionable insights, it empowers businesses to optimize production processes and drive operational excellence. | R17: Link | Y17: 1
A18: FALSE | B18: Fri | C18: 45716 | E18: What Do Your Kids Think You Do For A Living? | P18: What Do Your Kids Think You Do For A Living? | Z18: 1
A19: FALSE
A20: FALSE | B20: Tues | C20: 45720 | D20: 6 a.m. | E20: Building an AI Agent for Healthcare | H20: X | K20: MP4; FrameIO; Wrike; Wrike-prep; done | L20: 21 | M20: 39 | O20: Enhancing Healthcare Payer Contact Center Operations | P20: Building An AI Agent For Healthcare Payers Contact Center In Snowflake | Q20: Contact Center is a critical business function for a Payer/Health Plan. There is heightened focus particularly with the growing market demand for customer-centric experiences in healthcare. Improving the operational efficiency of contact centers and reducing agent burnout are also key priorities for all enterprises. Jeevan Rag, a Principal Industry Architect in Healthcare at Snowflake, shows you how to easily build an AI agent entirely in Snowflake using a Snowflake Notebook on Container Runtime to process unstructured data (audio files and PDFs) and build a Caller Intent ML Classification Model as well as a Chatbot application using Snowflake Cortex and Streamlit in Snowflake. | R20: Link | Y20: 1
A21: FALSE | B21: Tues | C21: 45720 | D21: 9 a.m. | E21: User Group-Snowflake in Action: Prediction with ML | H21: X | K21: MP4; Wrike; done (this video stays unlisted) | L21: 55 | M21: 27 | O21: Pulled from video | P21: Women on Snowflake: Prediction With Machine Learning Functions And Career Tips | Q21: This virtual meetup focuses on mastering prediction with Snowflake's powerful ML functions. The event features a hands-on demo showcasing real-world applications of predictive modeling with Snowflake, as well as a panel offering relatable career advice. Led by an experienced data architect, Maja Ferle, we dive deep into building accurate predictions while sharing practical tips! Join the Women on Snowflake user group chapter to stay updated on future events: https://usergroups.snowflake.com/women-on-snowflake/ | R21: NA | AD21: 1
A22: FALSE | B22: Tues | C22: 45720 | D22: 9 a.m. | E22: User Group- Unlocking More Value from Data with Data Vault & Knowledge Graphs | H22: X | K22: MP4; Wrike; done (this video stays unlisted) | L22: 59 | M22: 1 | O22: Pulled from video | P22: Data Vault User Group: Unlocking More Value From Data With Data Vault And Knowledge Graphs | Q22: Can Data Vault and Knowledge Graphs complement each other to unlock more value from data? Do they work better together by enhancing each other's strengths to maximize the power of your data? Join industry experts and fellow data practitioners as we explore how Data Vault enables flexible, long-term data storage while ensuring consistency, traceability, and auditability. We’ll also dive into how Knowledge Graphs enrich data by creating meaningful relationships and improving discoverability. Together, we’ll explore what it takes to integrate them effectively. This will be an interactive discussion, so bring your questions and insights! --- Join the Data Vault User Group to stay updated on future events: https://usergroups.snowflake.com/data-vault/ | R22: NA | AD22: 1
A23: FALSE | B23: Tues | C23: 45720 | D23: 10 a.m. | E23: User Group-Jyoti Pathak presentation | H23: X | K23: MP4; Wrike; done (this video stays unlisted) | L23: 58 | M23: 57 | O23: Pulled from video | P23: Women on Snowflake: Navigating Challenges And Embracing Opportunities In The Tech Industry | Q23: This session is a celebration of resilience, diversity, and the power of turning challenges into opportunities. Our guest speaker, Jyoti Pathak (https://www.linkedin.com/in/jyotipathak/), shares her journey in a heartfelt and insightful talk, offering her perspective on navigating challenges and embracing opportunities in the tech industry. Jyoti Pathak is a Snowflake Data SuperHero and award-winning Data Analytics Professional of the Year. Driven by passion for innovation, Jyoti built her success story through expertise in data and AI. She transformed technology teams at Fortune 50 companies and now leads her own tech company, providing innovative solutions in data, AI, and cybersecurity. Beyond business success, Jyoti serves on non-profit boards and dedicates herself to mentoring others, especially women and minorities in tech. As a certified life coach, she helps professionals build fulfilling careers while making a positive impact in their communities. Her journey from technologist to respected industry leader shows that with determination and expertise, you can break barriers and create pathways for others to follow. Together, we explore a range of impactful topics, including: - How different backgrounds shape career paths and opportunities. - Strategies for overcoming roadblocks, biases, and breaking through the glass ceiling. - The importance of self-care, recognizing burnout, and nurturing energy to sustain growth. - Transitioning to entrepreneurship or leadership roles and becoming a role model for others. - Educating and advocating for diversity to combat biases and pioneer change. - Striking a balance between blending in and standing out in the workplace. Join the Women on Snowflake user group chapter to stay updated on future events: https://usergroups.snowflake.com/women-on-snowflake/ | R23: NA | AD23: 1
A24: FALSE | B24: Tues | C24: 45720 | D24: 11 a.m. | E24: User Group-A Case Study of a Modern Data Platform with Data Vault in the Financial Services Sector by Ignition | H24: X | K24: MP4; Wrike; done (this video stays unlisted) | L24: 60 | M24: 35 | O24: Pulled from video | P24: Data Vault User Group: A Case Study of a Modern Data Platform with Data Vault in the Financial Services Sector by Ignition | Q24: Ignition Data, the DV2 Certification training partner in Australia, will present on the project approach and architecture used recently for a financial services customer to deploy a modern data hub, leveraging Snowflake, Data Factory, and IRiS for Data Vault automation to deliver a full Lakehouse with orchestration, CICD, automated test, data quality and control Frameworks. Ignition will also provide a brief demo of the new IRIS Data Vault Automation tool that has been designed to complement large industry standard data management platforms by adding DV2 automation without disruption or integration effort. It has been built with a simple development process, intuitive interface, and supporting knowledge hub to reduce the learning curve associated with building and maintaining Data Vaults. Join the Data Vault user group chapter to stay updated on future events: https://usergroups.snowflake.com/women-on-snowflake/ | R24: NA | AD24: 1
A25: FALSE | B25: Tues | C25: 45720 | D25: 12 p.m. | E25: User Group-An Irishman's Journey to the Data Vault (2.0) | H25: X | K25: MP4; Wrike; done (this video stays unlisted) | L25: 57 | M25: 50 | O25: Pulled from video | P25: Data Vault User Group: An Irishman's Journey to the Data Vault (2.0) | Q25: This presentation will tell the story of the warehouse projects Keith Evans worked on and how and why the Data Vault would have made them more successful. It will also tell the story of how and why he learned Data Vault. Keith is the Director of Data Architecture at Right Triangle and a Certified Data Vault 2.0 Practitioner. Connect with him at: https://www.linkedin.com/in/keithevans2/ Join the Data Vault user group chapter to stay updated on future events: https://usergroups.snowflake.com/data-vault/ | R25: NA | AD25: 1
